Workbook
Name APRIL22: #REF!
Name AUGUST22: #REF!
Name BPKOTTAYAM: #REF!
Name DECEMBER22: #REF!
Name FEBRUARY22: #REF!
Name JANUARY22: #REF!
Name JULY22: #REF!
Name JUNE22: #REF!
Name MARCH22: #REF!
Name MAYY22: #REF!
Name NOVEMBER22: #REF!
Name OCTOBER22: #REF!
Name PMGRKOTTAYAM: #REF!
Name SEPTEMBER22: #REF!

Sheet GT-SERV
A1: SUMMARY | N1: BRIDGEWAY MOTORS - MIS REPORT | O1: SUMMARY | AC1: SUMMARY | AQ1: CALICUT | BD1: =N1 -> BRIDGEWAY MOTORS - MIS REPORT | BE1: CALICUT | BS1: CALICUT | CE1: CALICUT | CG1: THRISSUR | CT1: =BD1 -> BRIDGEWAY MOTORS - MIS REPORT | CU1: THRISSUR | DI1: THRISSUR | DW1: KOTTAYAM | EJ1: =CT1 -> BRIDGEWAY MOTORS - MIS REPORT | EK1: KOTTAYAM | EY1: KOTTAYAM
A2: 45292 | B2: 45323 | C2: 45352 | D2: 45383 | E2: 45413 | F2: 45444 | G2: 45474 | H2: 45505 | I2: 45536 | J2: 45566 | K2: 45597 | L2: 45627 | M2: YTD 2024 | N2: Particulars | O2: 45658 | P2: 45689 | Q2: 45717 | R2: 45748 | S2: 45778 | T2: 45809 | U2: 45839 | V2: 45870 | W2: 45901 | X2: 45931 | Y2: 45962 | Z2: 45992 | AA2: YTD 2025 | AC2: 45658 | AD2: 45689 | AE2: 45717 | AF2: 45748 | AG2: 45778 | AH2: 45809 | AI2: 45839 | AJ2: 45870 | AK2: 45901 | AL2: 45931 | AM2: 45962 | AN2: 45992 | AO2: YTD 2025 | AQ2: 45292 | AR2: 45323 | AS2: 45352 | AT2: 45383 | AU2: 45413 | AV2: 45444 | AW2: 45474 | AX2: 45505 | AY2: 45536 | AZ2: 45566 | BA2: 45597 | BB2: 45627 | BC2: YTD 2024 | BD2: Particulars | BE2: 45658 | BF2: 45689 | BG2: 45717 | BH2: 45748 | BI2: 45778 | BJ2: 45809 | BK2: 45839 | BL2: 45870 | BM2: 45901 | BN2: 45931 | BO2: 45962 | BP2: 45992 | BQ2: YTD 2025 | BS2: 45658 | BT2: 45689 | BU2: 45717 | BV2: 45748 | BW2: 45778 | BX2: 45809 | BY2: 45839 | BZ2: 45870 | CA2: 45901 | CB2: 45931 | CC2: 45962 | CD2: 45992 | CE2: YTD 2025 | CG2: 45292 | CH2: 45323 | CI2: 45352 | CJ2: 45383 | CK2: 45413 | CL2: 45444 | CM2: 45474 | CN2: 45505 | CO2: 45536 | CP2: 45566 | CQ2: 45597 | CR2: 45627 | CS2: YTD 2024 | CT2: Particulars | CU2: 45658 | CV2: 45689 | CW2: 45717 | CX2: 45748 | CY2: 45778 | CZ2: 45809 | DA2: 45839 | DB2: 45870 | DC2: 45901 | DD2: 45931 | DE2: 45962 | DF2: 45992 | DG2: YTD 2025 | DI2: 45658 | DJ2: 45689 | DK2: 45717 | DL2: 45748 | DM2: 45778 | DN2: 45809 | DO2: 45839 | DP2: 45870 | DQ2: 45901 | DR2: 45931 | DS2: 45962 | DT2: 45992 | DU2: YTD 2025 | DW2: 45292 | DX2: 45323 | DY2: 45352 | DZ2: 45383 | EA2: 45413 | EB2: 45444 | EC2: 45474 | ED2: 45505 | EE2: 45536 | EF2: 45566 | EG2: 45597 | EH2: 45627 | EI2: YTD 2024 | EJ2: Particulars | EK2: 45658 | EL2: 45689 | EM2: 45717 | EN2: 45748 | EO2: 45778 | EP2: 45809 | EQ2: 45839 | ER2: 45870 | ES2: 45901 | ET2: 45931 | EU2: 45962 | EV2: 45992 | EW2: YTD 2025 | EY2: 45658 | EZ2: 45689 | FA2: 45717 | FB2: 45748 | FC2: 45778 | FD2: 45809 | FE2: 45839 | FF2: 45870 | FG2: 45901 | FH2: 45931 | FI2: 45962 | FJ2: 45992 | FK2: YTD 2025
A3: Actual | B3: Actual | C3: Actual | D3: Actual | E3: Actual | F3: Actual | G3: Actual | H3: Actual | I3: Actual | J3: Actual | K3: Actual | L3: Actual | M3: Actual | N3: Rs in Lakhs | O3: Actual | P3: Actual | Q3: Actual | R3: Actual | S3: Actual | T3: Actual | U3: Actual | V3: Actual | W3: Actual | X3: Actual | Y3: Actual | Z3: Actual | AA3: Actual | AC3: Budget | AD3: Budget | AE3: Budget | AF3: Budget | AG3: Budget | AH3: Budget | AI3: Budget | AJ3: Budget | AK3: Budget | AL3: Budget | AM3: Budget | AN3: Budget | AO3: Budget | AQ3: Actual | AR3: Actual | AS3: Actual | AT3: Actual | AU3: Actual | AV3: Actual | AW3: Actual | AX3: Actual | AY3: Actual | AZ3: Actual | BA3: Actual | BB3: Actual | BC3: Actual | BD3: =N3 -> Rs in Lakhs | BE3: Actual | BF3: Actual | BG3: Actual | BH3: Actual | BI3: Actual | BJ3: Actual | BK3: Actual | BL3: Actual | BM3: Actual | BN3: Actual | BO3: Actual | BP3: Actual | BQ3: Actual | BS3: Budget | BT3: Budget | BU3: Budget | BV3: Budget | BW3: Budget | BX3: Budget | BY3: Budget | BZ3: Budget | CA3: Budget | CB3: Budget | CC3: Budget | CD3: Budget | CE3: Budget | CG3: Actual | CH3: Actual | CI3: Actual | CJ3: Actual | CK3: Actual | CL3: Actual | CM3: Actual | CN3: Actual | CO3: Actual | CP3: Actual | CQ3: Actual | CR3: Actual | CS3: Actual | CT3: =BD3 -> Rs in Lakhs | CU3: Actual | CV3: Actual | CW3: Actual | CX3: Actual | CY3: Actual | CZ3: Actual | DA3: Actual | DB3: Actual | DC3: Actual | DD3: Actual | DE3: Actual | DF3: Actual | DG3: Actual | DI3: Budget | DJ3: Budget | DK3: Budget | DL3: Budget | DM3: Budget | DN3: Budget | DO3: Budget | DP3: Budget | DQ3: Budget | DR3: Budget | DS3: Budget | DT3: Budget | DU3: Budget | DW3: Actual | DX3: Actual | DY3: Actual | DZ3: Actual | EA3: Actual | EB3: Actual | EC3: Actual | ED3: Actual | EE3: Actual | EF3: Actual | EG3: Actual | EH3: Actual | EI3: Actual | EJ3: =CT3 -> Rs in Lakhs | EK3: Actual | EL3: Actual | EM3: Actual | EN3: Actual | EO3: Actual | EP3: Actual | EQ3: Actual | ER3: Actual | ES3: Actual | ET3: Actual | EU3: Actual | EV3: Actual | EW3: Actual | EY3: Budget | EZ3: Budget | FA3: Budget | FB3: Budget | FC3: Budget | FD3: Budget | FE3: Budget | FF3: Budget | FG3: Budget | FH3: Budget | FI3: Budget | FJ3: Budget | FK3: Budget
A4: =+AQ4+CG4+DW4 -> 0 | B4: =+AR4+CH4+DX4 -> 0 | C4: =+AS4+CI4+DY4 -> 0 | D4: =+AT4+CJ4+DZ4 -> 0 | E4: =+AU4+CK4+EA4 -> 0 | F4: =+AV4+CL4+EB4 -> 0 | G4: =+AW4+CM4+EC4 -> 0 | H4: =+AX4+CN4+ED4 -> 0 | ... L4: =+BB4+CR4+EH4 -> 0 | M4: =+SUM(A4:L4) -> 0 | N4: No of Cars | O4: =+BE4+CU4+EK4 -> 0 | P4: =+BF4+CV4+EL4 -> 0 | Q4: =+BG4+CW4+EM4 -> 0 | R4: =+BH4+CX4+EN4 -> 0 | S4: =+BI4+CY4+EO4 -> 0 | T4: =+BJ4+CZ4+EP4 -> 0 | U4: =+BK4+DA4+EQ4 -> 0 | V4: =+BL4+DB4+ER4 -> 0 | ... Z4: =+BP4+DF4+EV4 -> 0 | AA4: =+SUM(O4:Z4) -> 0 | AC4: =+BS4+DI4+EY4 -> 0 | AD4: =+BT4+DJ4+EZ4 -> 0 | AE4: =+BU4+DK4+FA4 -> 0 | AF4: =+BV4+DL4+FB4 -> 0 | AG4: =+BW4+DM4+FC4 -> 0 | AH4: =+BX4+DN4+FD4 -> 0 | AI4: =+BY4+DO4+FE4 -> 0 | AJ4: =+BZ4+DP4+FF4 -> 0 | ... AN4: =+CD4+DT4+FJ4 -> 0 | AO4: =+SUM(AC4:AN4) -> 0 | AQ4: =+PMGR!AQ4+BP!AQ4 -> 0 | AR4: =+PMGR!AR4+BP!AR4 -> 0 | AS4: =+PMGR!AS4+BP!AS4 -> 0 | AT4: =+PMGR!AT4+BP!AT4 -> 0 | AU4: =+PMGR!AU4+BP!AU4 -> 0 | AV4: =+PMGR!AV4+BP!AV4 -> 0 | AW4: =+PMGR!AW4+BP!AW4 -> 0 | AX4: =+PMGR!AX4+BP!AX4 -> 0 | ... BB4: =+PMGR!BB4+BP!BB4 -> 0 | BC4: =+SUM(AQ4:BB4) -> 0 | BD4: =N4 -> No of Cars | BE4: =+PMGR!BE4+BP!BE4 -> 0 | BF4: =+PMGR!BF4+BP!BF4 -> 0 | BG4: =+PMGR!BG4+BP!BG4 -> 0 | BH4: =+PMGR!BH4+BP!BH4 -> 0 | BI4: =+PMGR!BI4+BP!BI4 -> 0 | BJ4: =+PMGR!BJ4+BP!BJ4 -> 0 | BK4: =+PMGR!BK4+BP!BK4 -> 0 | BL4: =+PMGR!BL4+BP!BL4 -> 0 | ... BP4: =+PMGR!BP4+BP!BP4 -> 0 | BQ4: =+SUM(BE4:BP4) -> 0 | BS4: =+PMGR!BS4+BP!BS4 -> 0 | BT4: =+PMGR!BT4+BP!BT4 -> 0 | BU4: =+PMGR!BU4+BP!BU4 -> 0 | BV4: =+PMGR!BV4+BP!BV4 -> 0 | BW4: =+PMGR!BW4+BP!BW4 -> 0 | BX4: =+PMGR!BX4+BP!BX4 -> 0 | BY4: =+PMGR!BY4+BP!BY4 -> 0 | BZ4: =+PMGR!BZ4+BP!BZ4 -> 0 | ... CD4: =+PMGR!CD4+BP!CD4 -> 0 | CE4: =+SUM(BS4:CD4) -> 0 | CG4: =+PMGR!CG4+BP!CG4 -> 0 | CH4: =+PMGR!CH4+BP!CH4 -> 0 | CI4: =+PMGR!CI4+BP!CI4 -> 0 | CJ4: =+PMGR!CJ4+BP!CJ4 -> 0 | CK4: =+PMGR!CK4+BP!CK4 -> 0 | CL4: =+PMGR!CL4+BP!CL4 -> 0 | CM4: =+PMGR!CM4+BP!CM4 -> 0 | CN4: =+PMGR!CN4+BP!CN4 -> 0 | ... CR4: =+PMGR!CR4+BP!CR4 -> 0 | CS4: =+SUM(CG4:CR4) -> 0 | CT4: =BD4 -> No of Cars | CU4: =+PMGR!CU4+BP!CU4 -> 0 | CV4: =+PMGR!CV4+BP!CV4 -> 0 | CW4: =+PMGR!CW4+BP!CW4 -> 0 | CX4: =+PMGR!CX4+BP!CX4 -> 0 | CY4: =+PMGR!CY4+BP!CY4 -> 0 | CZ4: =+PMGR!CZ4+BP!CZ4 -> 0 | DA4: =+PMGR!DA4+BP!DA4 -> 0 | DB4: =+PMGR!DB4+BP!DB4 -> 0 | ... DF4: =+PMGR!DF4+BP!DF4 -> 0 | DG4: =+SUM(CU4:DF4) -> 0 | DI4: =+PMGR!DI4+BP!DI4 -> 0 | DJ4: =+PMGR!DJ4+BP!DJ4 -> 0 | DK4: =+PMGR!DK4+BP!DK4 -> 0 | DL4: =+PMGR!DL4+BP!DL4 -> 0 | DM4: =+PMGR!DM4+BP!DM4 -> 0 | DN4: =+PMGR!DN4+BP!DN4 -> 0 | DO4: =+PMGR!DO4+BP!DO4 -> 0 | DP4: =+PMGR!DP4+BP!DP4 -> 0 | ... DT4: =+PMGR!DT4+BP!DT4 -> 0 | DU4: =+SUM(DI4:DT4) -> 0 | DW4: =+PMGR!DW4+BP!DW4 -> 0 | DX4: =+PMGR!DX4+BP!DX4 -> 0 | DY4: =+PMGR!DY4+BP!DY4 -> 0 | DZ4: =+PMGR!DZ4+BP!DZ4 -> 0 | EA4: =+PMGR!EA4+BP!EA4 -> 0 | EB4: =+PMGR!EB4+BP!EB4 -> 0 | EC4: =+PMGR!EC4+BP!EC4 -> 0 | ED4: =+PMGR!ED4+BP!ED4 -> 0 | ... EH4: =+PMGR!EH4+BP!EH4 -> 0 | EI4: =+SUM(DW4:EH4) -> 0 | EJ4: =CT4 -> No of Cars | EK4: =+PMGR!EK4+BP!EK4 -> 0 | EL4: =+PMGR!EL4+BP!EL4 -> 0 | EM4: =+PMGR!EM4+BP!EM4 -> 0 | EN4: =+PMGR!EN4+BP!EN4 -> 0 | EO4: =+PMGR!EO4+BP!EO4 -> 0 | EP4: =+PMGR!EP4+BP!EP4 -> 0 | EQ4: =+PMGR!EQ4+BP!EQ4 -> 0 | ER4: =+PMGR!ER4+BP!ER4 -> 0 | ... EV4: =+PMGR!EV4+BP!EV4 -> 0 | EW4: =+SUM(EK4:EV4) -> 0 | EY4: =+PMGR!EY4+BP!EY4 -> 0 | EZ4: =+PMGR!EZ4+BP!EZ4 -> 0 | FA4: =+PMGR!FA4+BP!FA4 -> 0 | FB4: =+PMGR!FB4+BP!FB4 -> 0 | FC4: =+PMGR!FC4+BP!FC4 -> 0 | FD4: =+PMGR!FD4+BP!FD4 -> 0 | FE4: =+PMGR!FE4+BP!FE4 -> 0 | FF4: =+PMGR!FF4+BP!FF4 -> 0 | ... FJ4: =+PMGR!FJ4+BP!FJ4 -> 0 | FK4: =+SUM(EY4:FJ4) -> 0
N5: New Car Sales | AQ5: =+PMGR!AQ5+BP!AQ5 -> 0 | AR5: =+PMGR!AR5+BP!AR5 -> 0 | AS5: =+PMGR!AS5+BP!AS5 -> 0 | AT5: =+PMGR!AT5+BP!AT5 -> 0 | AU5: =+PMGR!AU5+BP!AU5 -> 0 | AV5: =+PMGR!AV5+BP!AV5 -> 0 | AW5: =+PMGR!AW5+BP!AW5 -> 0 | AX5: =+PMGR!AX5+BP!AX5 -> 0 | ... BB5: =+PMGR!BB5+BP!BB5 -> 0 | BD5: =N5 -> New Car Sales | BE5: =+PMGR!BE5+BP!BE5 -> 0 | BF5: =+PMGR!BF5+BP!BF5 -> 0 | BG5: =+PMGR!BG5+BP!BG5 -> 0 | BH5: =+PMGR!BH5+BP!BH5 -> 0 | BI5: =+PMGR!BI5+BP!BI5 -> 0 | BJ5: =+PMGR!BJ5+BP!BJ5 -> 0 | BK5: =+PMGR!BK5+BP!BK5 -> 0 | BL5: =+PMGR!BL5+BP!BL5 -> 0 | ... BP5: =+PMGR!BP5+BP!BP5 -> 0 | BS5: =+PMGR!BS5+BP!BS5 -> 0 | BT5: =+PMGR!BT5+BP!BT5 -> 0 | BU5: =+PMGR!BU5+BP!BU5 -> 0 | BV5: =+PMGR!BV5+BP!BV5 -> 0 | BW5: =+PMGR!BW5+BP!BW5 -> 0 | BX5: =+PMGR!BX5+BP!BX5 -> 0 | BY5: =+PMGR!BY5+BP!BY5 -> 0 | BZ5: =+PMGR!BZ5+BP!BZ5 -> 0 | ... CD5: =+PMGR!CD5+BP!CD5 -> 0 | CG5: =+PMGR!CG5+BP!CG5 -> 0 | CH5: =+PMGR!CH5+BP!CH5 -> 0 | CI5: =+PMGR!CI5+BP!CI5 -> 0 | CJ5: =+PMGR!CJ5+BP!CJ5 -> 0 | CK5: =+PMGR!CK5+BP!CK5 -> 0 | CL5: =+PMGR!CL5+BP!CL5 -> 0 | CM5: =+PMGR!CM5+BP!CM5 -> 0 | CN5: =+PMGR!CN5+BP!CN5 -> 0 | ... CR5: =+PMGR!CR5+BP!CR5 -> 0 | CT5: =BD5 -> New Car Sales | CU5: =+PMGR!CU5+BP!CU5 -> 0 | CV5: =+PMGR!CV5+BP!CV5 -> 0 | CW5: =+PMGR!CW5+BP!CW5 -> 0 | CX5: =+PMGR!CX5+BP!CX5 -> 0 | CY5: =+PMGR!CY5+BP!CY5 -> 0 | CZ5: =+PMGR!CZ5+BP!CZ5 -> 0 | DA5: =+PMGR!DA5+BP!DA5 -> 0 | DB5: =+PMGR!DB5+BP!DB5 -> 0 | ... DF5: =+PMGR!DF5+BP!DF5 -> 0 | DI5: =+PMGR!DI5+BP!DI5 -> 0 | DJ5: =+PMGR!DJ5+BP!DJ5 -> 0 | DK5: =+PMGR!DK5+BP!DK5 -> 0 | DL5: =+PMGR!DL5+BP!DL5 -> 0 | DM5: =+PMGR!DM5+BP!DM5 -> 0 | DN5: =+PMGR!DN5+BP!DN5 -> 0 | DO5: =+PMGR!DO5+BP!DO5 -> 0 | DP5: =+PMGR!DP5+BP!DP5 -> 0 | ... DT5: =+PMGR!DT5+BP!DT5 -> 0 | DW5: =+PMGR!DW5+BP!DW5 -> 0 | DX5: =+PMGR!DX5+BP!DX5 -> 0 | DY5: =+PMGR!DY5+BP!DY5 -> 0 | DZ5: =+PMGR!DZ5+BP!DZ5 -> 0 | EA5: =+PMGR!EA5+BP!EA5 -> 0 | EB5: =+PMGR!EB5+BP!EB5 -> 0 | EC5: =+PMGR!EC5+BP!EC5 -> 0 | ED5: =+PMGR!ED5+BP!ED5 -> 0 | ... EH5: =+PMGR!EH5+BP!EH5 -> 0 | EJ5: =CT5 -> New Car Sales | EK5: =+PMGR!EK5+BP!EK5 -> 0 | EL5: =+PMGR!EL5+BP!EL5 -> 0 | EM5: =+PMGR!EM5+BP!EM5 -> 0 | EN5: =+PMGR!EN5+BP!EN5 -> 0 | EO5: =+PMGR!EO5+BP!EO5 -> 0 | EP5: =+PMGR!EP5+BP!EP5 -> 0 | EQ5: =+PMGR!EQ5+BP!EQ5 -> 0 | ER5: =+PMGR!ER5+BP!ER5 -> 0 | ... EV5: =+PMGR!EV5+BP!EV5 -> 0 | EY5: =+PMGR!EY5+BP!EY5 -> 0 | EZ5: =+PMGR!EZ5+BP!EZ5 -> 0 | FA5: =+PMGR!FA5+BP!FA5 -> 0 | FB5: =+PMGR!FB5+BP!FB5 -> 0 | FC5: =+PMGR!FC5+BP!FC5 -> 0 | FD5: =+PMGR!FD5+BP!FD5 -> 0 | FE5: =+PMGR!FE5+BP!FE5 -> 0 | FF5: =+PMGR!FF5+BP!FF5 -> 0 | ... FJ5: =+PMGR!FJ5+BP!FJ5 -> 0
A6: =+A7+A8+A13 -> 0 | B6: =+B7+B8+B13 -> 0 | C6: =+C7+C8+C13 -> 0 | D6: =+D7+D8+D13 -> 0 | E6: =+E7+E8+E13 -> 0 | F6: =+F7+F8+F13 -> 0 | G6: =+G7+G8+G13 -> 0 | H6: =+H7+H8+H13 -> 0 | ... L6: =+L7+L8+L13 -> 0 | M6: =+SUM(A6:L6) -> 0 | N6: Total Commission | O6: =+O7+O8+O13 -> 0 | P6: =+P7+P8+P13 -> 0 | Q6: =+Q7+Q8+Q13 -> 0 | R6: =+R7+R8+R13 -> 0 | S6: =+S7+S8+S13 -> 0 | T6: =+T7+T8+T13 -> 0 | U6: =+U7+U8+U13 -> 0 | V6: =+V7+V8+V13 -> 0 | ... Z6: =+Z7+Z8+Z13 -> 0 | AA6: =+SUM(O6:Z6) -> 0 | AC6: =+AC7+AC8+AC13 -> 0 | AD6: =+AD7+AD8+AD13 -> 0 | AE6: =+AE7+AE8+AE13 -> 0 | AF6: =+AF7+AF8+AF13 -> 0 | AG6: =+AG7+AG8+AG13 -> 0 | AH6: =+AH7+AH8+AH13 -> 0 | AI6: =+AI7+AI8+AI13 -> 0 | AJ6: =+AJ7+AJ8+AJ13 -> 0 | ... AN6: =+AN7+AN8+AN13 -> 0 | AO6: =+SUM(AC6:AN6) -> 0 | AQ6: =+AQ7+AQ8+AQ13 -> 0 | AR6: =+AR7+AR8+AR13 -> 0 | AS6: =+AS7+AS8+AS13 -> 0 | AT6: =+AT7+AT8+AT13 -> 0 | AU6: =+AU7+AU8+AU13 -> 0 | AV6: =+AV7+AV8+AV13 -> 0 | AW6: =+AW7+AW8+AW13 -> 0 | AX6: =+AX7+AX8+AX13 -> 0 | ... BB6: =+BB7+BB8+BB13 -> 0 | BC6: =+SUM(AQ6:BB6) -> 0 | BD6: =N6 -> Total Commission | BE6: =+BE7+BE8+BE13 -> 0 | BF6: =+BF7+BF8+BF13 -> 0 | BG6: =+BG7+BG8+BG13 -> 0 | BH6: =+BH7+BH8+BH13 -> 0 | BI6: =+BI7+BI8+BI13 -> 0 | BJ6: =+BJ7+BJ8+BJ13 -> 0 | BK6: =+BK7+BK8+BK13 -> 0 | BL6: =+BL7+BL8+BL13 -> 0 | ... BP6: =+BP7+BP8+BP13 -> 0 | BQ6: =+SUM(BE6:BP6) -> 0 | BS6: =+BS7+BS8+BS13 -> 0 | BT6: =+BT7+BT8+BT13 -> 0 | BU6: =+BU7+BU8+BU13 -> 0 | BV6: =+BV7+BV8+BV13 -> 0 | BW6: =+BW7+BW8+BW13 -> 0 | BX6: =+BX7+BX8+BX13 -> 0 | BY6: =+BY7+BY8+BY13 -> 0 | BZ6: =+BZ7+BZ8+BZ13 -> 0 | ... CD6: =+CD7+CD8+CD13 -> 0 | CE6: =+SUM(BS6:CD6) -> 0 | CG6: =+CG7+CG8+CG13 -> 0 | CH6: =+CH7+CH8+CH13 -> 0 | CI6: =+CI7+CI8+CI13 -> 0 | CJ6: =+CJ7+CJ8+CJ13 -> 0 | CK6: =+CK7+CK8+CK13 -> 0 | CL6: =+CL7+CL8+CL13 -> 0 | CM6: =+CM7+CM8+CM13 -> 0 | CN6: =+CN7+CN8+CN13 -> 0 | ... CR6: =+CR7+CR8+CR13 -> 0 | CS6: =+SUM(CG6:CR6) -> 0 | CT6: =BD6 -> Total Commission | CU6: =+CU7+CU8+CU13 -> 0 | CV6: =+CV7+CV8+CV13 -> 0 | CW6: =+CW7+CW8+CW13 -> 0 | CX6: =+CX7+CX8+CX13 -> 0 | CY6: =+CY7+CY8+CY13 -> 0 | CZ6: =+CZ7+CZ8+CZ13 -> 0 | DA6: =+DA7+DA8+DA13 -> 0 | DB6: =+DB7+DB8+DB13 -> 0 | ... DF6: =+DF7+DF8+DF13 -> 0 | DG6: =+SUM(CU6:DF6) -> 0 | DI6: =+DI7+DI8+DI13 -> 0 | DJ6: =+DJ7+DJ8+DJ13 -> 0 | DK6: =+DK7+DK8+DK13 -> 0 | DL6: =+DL7+DL8+DL13 -> 0 | DM6: =+DM7+DM8+DM13 -> 0 | DN6: =+DN7+DN8+DN13 -> 0 | DO6: =+DO7+DO8+DO13 -> 0 | DP6: =+DP7+DP8+DP13 -> 0 | ... DT6: =+DT7+DT8+DT13 -> 0 | DU6: =+SUM(DI6:DT6) -> 0 | DW6: =+DW7+DW8+DW13 -> 0 | DX6: =+DX7+DX8+DX13 -> 0 | DY6: =+DY7+DY8+DY13 -> 0 | DZ6: =+DZ7+DZ8+DZ13 -> 0 | EA6: =+EA7+EA8+EA13 -> 0 | EB6: =+EB7+EB8+EB13 -> 0 | EC6: =+EC7+EC8+EC13 -> 0 | ED6: =+ED7+ED8+ED13 -> 0 | ... EH6: =+EH7+EH8+EH13 -> 0 | EI6: =+SUM(DW6:EH6) -> 0 | EJ6: =CT6 -> Total Commission | EK6: =+EK7+EK8+EK13 -> 0 | EL6: =+EL7+EL8+EL13 -> 0 | EM6: =+EM7+EM8+EM13 -> 0 | EN6: =+EN7+EN8+EN13 -> 0 | EO6: =+EO7+EO8+EO13 -> 0 | EP6: =+EP7+EP8+EP13 -> 0 | EQ6: =+EQ7+EQ8+EQ13 -> 0 | ER6: =+ER7+ER8+ER13 -> 0 | ... EV6: =+EV7+EV8+EV13 -> 0 | EW6: =+SUM(EK6:EV6) -> 0 | EY6: =+EY7+EY8+EY13 -> 0 | EZ6: =+EZ7+EZ8+EZ13 -> 0 | FA6: =+FA7+FA8+FA13 -> 0 | FB6: =+FB7+FB8+FB13 -> 0 | FC6: =+FC7+FC8+FC13 -> 0 | FD6: =+FD7+FD8+FD13 -> 0 | FE6: =+FE7+FE8+FE13 -> 0 | FF6: =+FF7+FF8+FF13 -> 0 | ... FJ6: =+FJ7+FJ8+FJ13 -> 0 | FK6: =+SUM(EY6:FJ6) -> 0
A7: =+AQ7+CG7+DW7 -> 0 | B7: =+AR7+CH7+DX7 -> 0 | C7: =+AS7+CI7+DY7 -> 0 | D7: =+AT7+CJ7+DZ7 -> 0 | E7: =+AU7+CK7+EA7 -> 0 | F7: =+AV7+CL7+EB7 -> 0 | G7: =+AW7+CM7+EC7 -> 0 | H7: =+AX7+CN7+ED7 -> 0 | ... L7: =+BB7+CR7+EH7 -> 0 | M7: =+SUM(A7:L7) -> 0 | N7: Fixed Commission | O7: =+BE7+CU7+EK7 -> 0 | P7: =+BF7+CV7+EL7 -> 0 | Q7: =+BG7+CW7+EM7 -> 0 | R7: =+BH7+CX7+EN7 -> 0 | S7: =+BI7+CY7+EO7 -> 0 | T7: =+BJ7+CZ7+EP7 -> 0 | U7: =+BK7+DA7+EQ7 -> 0 | V7: =+BL7+DB7+ER7 -> 0 | ... Z7: =+BP7+DF7+EV7 -> 0 | AA7: =+SUM(O7:Z7) -> 0 | AC7: =+BS7+DI7+EY7 -> 0 | AD7: =+BT7+DJ7+EZ7 -> 0 | AE7: =+BU7+DK7+FA7 -> 0 | AF7: =+BV7+DL7+FB7 -> 0 | AG7: =+BW7+DM7+FC7 -> 0 | AH7: =+BX7+DN7+FD7 -> 0 | AI7: =+BY7+DO7+FE7 -> 0 | AJ7: =+BZ7+DP7+FF7 -> 0 | ... AN7: =+CD7+DT7+FJ7 -> 0 | AO7: =+SUM(AC7:AN7) -> 0 | AQ7: =+PMGR!AQ7+BP!AQ7 -> 0 | AR7: =+PMGR!AR7+BP!AR7 -> 0 | AS7: =+PMGR!AS7+BP!AS7 -> 0 | AT7: =+PMGR!AT7+BP!AT7 -> 0 | AU7: =+PMGR!AU7+BP!AU7 -> 0 | AV7: =+PMGR!AV7+BP!AV7 -> 0 | AW7: =+PMGR!AW7+BP!AW7 -> 0 | AX7: =+PMGR!AX7+BP!AX7 -> 0 | ... BB7: =+PMGR!BB7+BP!BB7 -> 0 | BC7: =+SUM(AQ7:BB7) -> 0 | BD7: =N7 -> Fixed Commission | BE7: =+PMGR!BE7+BP!BE7 -> 0 | BF7: =+PMGR!BF7+BP!BF7 -> 0 | BG7: =+PMGR!BG7+BP!BG7 -> 0 | BH7: =+PMGR!BH7+BP!BH7 -> 0 | BI7: =+PMGR!BI7+BP!BI7 -> 0 | BJ7: =+PMGR!BJ7+BP!BJ7 -> 0 | BK7: =+PMGR!BK7+BP!BK7 -> 0 | BL7: =+PMGR!BL7+BP!BL7 -> 0 | ... BP7: =+PMGR!BP7+BP!BP7 -> 0 | BQ7: =+SUM(BE7:BP7) -> 0 | BS7: =+PMGR!BS7+BP!BS7 -> 0 | BT7: =+PMGR!BT7+BP!BT7 -> 0 | BU7: =+PMGR!BU7+BP!BU7 -> 0 | BV7: =+PMGR!BV7+BP!BV7 -> 0 | BW7: =+PMGR!BW7+BP!BW7 -> 0 | BX7: =+PMGR!BX7+BP!BX7 -> 0 | BY7: =+PMGR!BY7+BP!BY7 -> 0 | BZ7: =+PMGR!BZ7+BP!BZ7 -> 0 | ... CD7: =+PMGR!CD7+BP!CD7 -> 0 | CE7: =+SUM(BS7:CD7) -> 0 | CG7: =+PMGR!CG7+BP!CG7 -> 0 | CH7: =+PMGR!CH7+BP!CH7 -> 0 | CI7: =+PMGR!CI7+BP!CI7 -> 0 | CJ7: =+PMGR!CJ7+BP!CJ7 -> 0 | CK7: =+PMGR!CK7+BP!CK7 -> 0 | CL7: =+PMGR!CL7+BP!CL7 -> 0 | CM7: =+PMGR!CM7+BP!CM7 -> 0 | CN7: =+PMGR!CN7+BP!CN7 -> 0 | ... CR7: =+PMGR!CR7+BP!CR7 -> 0 | CS7: =+SUM(CG7:CR7) -> 0 | CT7: =BD7 -> Fixed Commission | CU7: =+PMGR!CU7+BP!CU7 -> 0 | CV7: =+PMGR!CV7+BP!CV7 -> 0 | CW7: =+PMGR!CW7+BP!CW7 -> 0 | CX7: =+PMGR!CX7+BP!CX7 -> 0 | CY7: =+PMGR!CY7+BP!CY7 -> 0 | CZ7: =+PMGR!CZ7+BP!CZ7 -> 0 | DA7: =+PMGR!DA7+BP!DA7 -> 0 | DB7: =+PMGR!DB7+BP!DB7 -> 0 | ... DF7: =+PMGR!DF7+BP!DF7 -> 0 | DG7: =+SUM(CU7:DF7) -> 0 | DI7: =+PMGR!DI7+BP!DI7 -> 0 | DJ7: =+PMGR!DJ7+BP!DJ7 -> 0 | DK7: =+PMGR!DK7+BP!DK7 -> 0 | DL7: =+PMGR!DL7+BP!DL7 -> 0 | DM7: =+PMGR!DM7+BP!DM7 -> 0 | DN7: =+PMGR!DN7+BP!DN7 -> 0 | DO7: =+PMGR!DO7+BP!DO7 -> 0 | DP7: =+PMGR!DP7+BP!DP7 -> 0 | ... DT7: =+PMGR!DT7+BP!DT7 -> 0 | DU7: =+SUM(DI7:DT7) -> 0 | DW7: =+PMGR!DW7+BP!DW7 -> 0 | DX7: =+PMGR!DX7+BP!DX7 -> 0 | DY7: =+PMGR!DY7+BP!DY7 -> 0 | DZ7: =+PMGR!DZ7+BP!DZ7 -> 0 | EA7: =+PMGR!EA7+BP!EA7 -> 0 | EB7: =+PMGR!EB7+BP!EB7 -> 0 | EC7: =+PMGR!EC7+BP!EC7 -> 0 | ED7: =+PMGR!ED7+BP!ED7 -> 0 | ... EH7: =+PMGR!EH7+BP!EH7 -> 0 | EI7: =+SUM(DW7:EH7) -> 0 | EJ7: =CT7 -> Fixed Commission | EK7: =+PMGR!EK7+BP!EK7 -> 0 | EL7: =+PMGR!EL7+BP!EL7 -> 0 | EM7: =+PMGR!EM7+BP!EM7 -> 0 | EN7: =+PMGR!EN7+BP!EN7 -> 0 | EO7: =+PMGR!EO7+BP!EO7 -> 0 | EP7: =+PMGR!EP7+BP!EP7 -> 0 | EQ7: =+PMGR!EQ7+BP!EQ7 -> 0 | ER7: =+PMGR!ER7+BP!ER7 -> 0 | ... EV7: =+PMGR!EV7+BP!EV7 -> 0 | EW7: =+SUM(EK7:EV7) -> 0 | EY7: =+PMGR!EY7+BP!EY7 -> 0 | EZ7: =+PMGR!EZ7+BP!EZ7 -> 0 | FA7: =+PMGR!FA7+BP!FA7 -> 0 | FB7: =+PMGR!FB7+BP!FB7 -> 0 | FC7: =+PMGR!FC7+BP!FC7 -> 0 | FD7: =+PMGR!FD7+BP!FD7 -> 0 | FE7: =+PMGR!FE7+BP!FE7 -> 0 | FF7: =+PMGR!FF7+BP!FF7 -> 0 | ... FJ7: =+PMGR!FJ7+BP!FJ7 -> 0 | FK7: =+SUM(EY7:FJ7) -> 0
A8: =+SUM(A9:A12) -> 0 | B8: =+SUM(B9:B12) -> 0 | C8: =+SUM(C9:C12) -> 0 | D8: =+SUM(D9:D12) -> 0 | E8: =+SUM(E9:E12) -> 0 | F8: =+SUM(F9:F12) -> 0 | G8: =+SUM(G9:G12) -> 0 | H8: =+SUM(H9:H12) -> 0 | ... L8: =+SUM(L9:L12) -> 0 | M8: =+SUM(A8:L8) -> 0 | N8: Target achievement bonus | O8: =+SUM(O9:O12) -> 0 | P8: =+SUM(P9:P12) -> 0 | Q8: =+SUM(Q9:Q12) -> 0 | R8: =+SUM(R9:R12) -> 0 | S8: =+SUM(S9:S12) -> 0 | T8: =+SUM(T9:T12) -> 0 | U8: =+SUM(U9:U12) -> 0 | V8: =+SUM(V9:V12) -> 0 | ... Z8: =+SUM(Z9:Z12) -> 0 | AA8: =+SUM(O8:Z8) -> 0 | AC8: =+SUM(AC9:AC12) -> 0 | AD8: =+SUM(AD9:AD12) -> 0 | AE8: =+SUM(AE9:AE12) -> 0 | AF8: =+SUM(AF9:AF12) -> 0 | AG8: =+SUM(AG9:AG12) -> 0 | AH8: =+SUM(AH9:AH12) -> 0 | AI8: =+SUM(AI9:AI12) -> 0 | AJ8: =+SUM(AJ9:AJ12) -> 0 | ... AN8: =+SUM(AN9:AN12) -> 0 | AO8: =+SUM(AC8:AN8) -> 0 | AQ8: =+SUM(AQ9:AQ12) -> 0 | AR8: =+SUM(AR9:AR12) -> 0 | AS8: =+SUM(AS9:AS12) -> 0 | AT8: =+SUM(AT9:AT12) -> 0 | AU8: =+SUM(AU9:AU12) -> 0 | AV8: =+SUM(AV9:AV12) -> 0 | AW8: =+SUM(AW9:AW12) -> 0 | AX8: =+SUM(AX9:AX12) -> 0 | ... BB8: =+SUM(BB9:BB12) -> 0 | BC8: =+SUM(AQ8:BB8) -> 0 | BD8: =N8 -> Target achievement bonus | BE8: =+SUM(BE9:BE12) -> 0 | BF8: =+SUM(BF9:BF12) -> 0 | BG8: =+SUM(BG9:BG12) -> 0 | BH8: =+SUM(BH9:BH12) -> 0 | BI8: =+SUM(BI9:BI12) -> 0 | BJ8: =+SUM(BJ9:BJ12) -> 0 | BK8: =+SUM(BK9:BK12) -> 0 | BL8: =+SUM(BL9:BL12) -> 0 | ... BP8: =+SUM(BP9:BP12) -> 0 | BQ8: =+SUM(BE8:BP8) -> 0 | BS8: =+SUM(BS9:BS12) -> 0 | BT8: =+SUM(BT9:BT12) -> 0 | BU8: =+SUM(BU9:BU12) -> 0 | BV8: =+SUM(BV9:BV12) -> 0 | BW8: =+SUM(BW9:BW12) -> 0 | BX8: =+SUM(BX9:BX12) -> 0 | BY8: =+SUM(BY9:BY12) -> 0 | BZ8: =+SUM(BZ9:BZ12) -> 0 | ... CD8: =+SUM(CD9:CD12) -> 0 | CE8: =+SUM(BS8:CD8) -> 0 | CG8: =+SUM(CG9:CG12) -> 0 | CH8: =+SUM(CH9:CH12) -> 0 | CI8: =+SUM(CI9:CI12) -> 0 | CJ8: =+SUM(CJ9:CJ12) -> 0 | CK8: =+SUM(CK9:CK12) -> 0 | CL8: =+SUM(CL9:CL12) -> 0 | CM8: =+SUM(CM9:CM12) -> 0 | CN8: =+SUM(CN9:CN12) -> 0 | ... CR8: =+SUM(CR9:CR12) -> 0 | CS8: =+SUM(CG8:CR8) -> 0 | CT8: =BD8 -> Target achievement bonus | CU8: =+SUM(CU9:CU12) -> 0 | CV8: =+SUM(CV9:CV12) -> 0 | CW8: =+SUM(CW9:CW12) -> 0 | CX8: =+SUM(CX9:CX12) -> 0 | CY8: =+SUM(CY9:CY12) -> 0 | CZ8: =+SUM(CZ9:CZ12) -> 0 | DA8: =+SUM(DA9:DA12) -> 0 | DB8: =+SUM(DB9:DB12) -> 0 | ... DF8: =+SUM(DF9:DF12) -> 0 | DG8: =+SUM(CU8:DF8) -> 0 | DI8: =+SUM(DI9:DI12) -> 0 | DJ8: =+SUM(DJ9:DJ12) -> 0 | DK8: =+SUM(DK9:DK12) -> 0 | DL8: =+SUM(DL9:DL12) -> 0 | DM8: =+SUM(DM9:DM12) -> 0 | DN8: =+SUM(DN9:DN12) -> 0 | DO8: =+SUM(DO9:DO12) -> 0 | DP8: =+SUM(DP9:DP12) -> 0 | ... DT8: =+SUM(DT9:DT12) -> 0 | DU8: =+SUM(DI8:DT8) -> 0 | DW8: =+SUM(DW9:DW12) -> 0 | DX8: =+SUM(DX9:DX12) -> 0 | DY8: =+SUM(DY9:DY12) -> 0 | DZ8: =+SUM(DZ9:DZ12) -> 0 | EA8: =+SUM(EA9:EA12) -> 0 | EB8: =+SUM(EB9:EB12) -> 0 | EC8: =+SUM(EC9:EC12) -> 0 | ED8: =+SUM(ED9:ED12) -> 0 | ... EH8: =+SUM(EH9:EH12) -> 0 | EI8: =+SUM(DW8:EH8) -> 0 | EJ8: =CT8 -> Target achievement bonus | EK8: =+SUM(EK9:EK12) -> 0 | EL8: =+SUM(EL9:EL12) -> 0 | EM8: =+SUM(EM9:EM12) -> 0 | EN8: =+SUM(EN9:EN12) -> 0 | EO8: =+SUM(EO9:EO12) -> 0 | EP8: =+SUM(EP9:EP12) -> 0 | EQ8: =+SUM(EQ9:EQ12) -> 0 | ER8: =+SUM(ER9:ER12) -> 0 | ... EV8: =+SUM(EV9:EV12) -> 0 | EW8: =+SUM(EK8:EV8) -> 0 | EY8: =+SUM(EY9:EY12) -> 0 | EZ8: =+SUM(EZ9:EZ12) -> 0 | FA8: =+SUM(FA9:FA12) -> 0 | FB8: =+SUM(FB9:FB12) -> 0 | FC8: =+SUM(FC9:FC12) -> 0 | FD8: =+SUM(FD9:FD12) -> 0 | FE8: =+SUM(FE9:FE12) -> 0 | FF8: =+SUM(FF9:FF12) -> 0 | ... FJ8: =+SUM(FJ9:FJ12) -> 0 | FK8: =+SUM(EY8:FJ8) -> 0
A9: =+AQ9+CG9+DW9 -> 0 | B9: =+AR9+CH9+DX9 -> 0 | C9: =+AS9+CI9+DY9 -> 0 | D9: =+AT9+CJ9+DZ9 -> 0 | E9: =+AU9+CK9+EA9 -> 0 | F9: =+AV9+CL9+EB9 -> 0 | G9: =+AW9+CM9+EC9 -> 0 | H9: =+AX9+CN9+ED9 -> 0 | ... L9: =+BB9+CR9+EH9 -> 0 | M9: =+SUM(A9:L9) -> 0 | N9: Sales Target Bonus | O9: =+BE9+CU9+EK9 -> 0 | P9: =+BF9+CV9+EL9 -> 0 | Q9: =+BG9+CW9+EM9 -> 0 | R9: =+BH9+CX9+EN9 -> 0 | S9: =+BI9+CY9+EO9 -> 0 | T9: =+BJ9+CZ9+EP9 -> 0 | U9: =+BK9+DA9+EQ9 -> 0 | V9: =+BL9+DB9+ER9 -> 0 | ... Z9: =+BP9+DF9+EV9 -> 0 | AA9: =+SUM(O9:Z9) -> 0 | AC9: =+BS9+DI9+EY9 -> 0 | AD9: =+BT9+DJ9+EZ9 -> 0 | AE9: =+BU9+DK9+FA9 -> 0 | AF9: =+BV9+DL9+FB9 -> 0 | AG9: =+BW9+DM9+FC9 -> 0 | AH9: =+BX9+DN9+FD9 -> 0 | AI9: =+BY9+DO9+FE9 -> 0 | AJ9: =+BZ9+DP9+FF9 -> 0 | ... AN9: =+CD9+DT9+FJ9 -> 0 | AO9: =+SUM(AC9:AN9) -> 0 | AQ9: =+PMGR!AQ9+BP!AQ9 -> 0 | AR9: =+PMGR!AR9+BP!AR9 -> 0 | AS9: =+PMGR!AS9+BP!AS9 -> 0 | AT9: =+PMGR!AT9+BP!AT9 -> 0 | AU9: =+PMGR!AU9+BP!AU9 -> 0 | AV9: =+PMGR!AV9+BP!AV9 -> 0 | AW9: =+PMGR!AW9+BP!AW9 -> 0 | AX9: =+PMGR!AX9+BP!AX9 -> 0 | ... BB9: =+PMGR!BB9+BP!BB9 -> 0 | BC9: =+SUM(AQ9:BB9) -> 0 | BD9: Sales Target Bonus | BE9: =+PMGR!BE9+BP!BE9 -> 0 | BF9: =+PMGR!BF9+BP!BF9 -> 0 | BG9: =+PMGR!BG9+BP!BG9 -> 0 | BH9: =+PMGR!BH9+BP!BH9 -> 0 | BI9: =+PMGR!BI9+BP!BI9 -> 0 | BJ9: =+PMGR!BJ9+BP!BJ9 -> 0 | BK9: =+PMGR!BK9+BP!BK9 -> 0 | BL9: =+PMGR!BL9+BP!BL9 -> 0 | ... BP9: =+PMGR!BP9+BP!BP9 -> 0 | BQ9: =+SUM(BE9:BP9) -> 0 | BS9: =+PMGR!BS9+BP!BS9 -> 0 | BT9: =+PMGR!BT9+BP!BT9 -> 0 | BU9: =+PMGR!BU9+BP!BU9 -> 0 | BV9: =+PMGR!BV9+BP!BV9 -> 0 | BW9: =+PMGR!BW9+BP!BW9 -> 0 | BX9: =+PMGR!BX9+BP!BX9 -> 0 | BY9: =+PMGR!BY9+BP!BY9 -> 0 | BZ9: =+PMGR!BZ9+BP!BZ9 -> 0 | ... CD9: =+PMGR!CD9+BP!CD9 -> 0 | CE9: =+SUM(BS9:CD9) -> 0 | CG9: =+PMGR!CG9+BP!CG9 -> 0 | CH9: =+PMGR!CH9+BP!CH9 -> 0 | CI9: =+PMGR!CI9+BP!CI9 -> 0 | CJ9: =+PMGR!CJ9+BP!CJ9 -> 0 | CK9: =+PMGR!CK9+BP!CK9 -> 0 | CL9: =+PMGR!CL9+BP!CL9 -> 0 | CM9: =+PMGR!CM9+BP!CM9 -> 0 | CN9: =+PMGR!CN9+BP!CN9 -> 0 | ... CR9: =+PMGR!CR9+BP!CR9 -> 0 | CS9: =+SUM(CG9:CR9) -> 0 | CT9: Sales Target Bonus | CU9: =+PMGR!CU9+BP!CU9 -> 0 | CV9: =+PMGR!CV9+BP!CV9 -> 0 | CW9: =+PMGR!CW9+BP!CW9 -> 0 | CX9: =+PMGR!CX9+BP!CX9 -> 0 | CY9: =+PMGR!CY9+BP!CY9 -> 0 | CZ9: =+PMGR!CZ9+BP!CZ9 -> 0 | DA9: =+PMGR!DA9+BP!DA9 -> 0 | DB9: =+PMGR!DB9+BP!DB9 -> 0 | ... DF9: =+PMGR!DF9+BP!DF9 -> 0 | DG9: =+SUM(CU9:DF9) -> 0 | DI9: =+PMGR!DI9+BP!DI9 -> 0 | DJ9: =+PMGR!DJ9+BP!DJ9 -> 0 | DK9: =+PMGR!DK9+BP!DK9 -> 0 | DL9: =+PMGR!DL9+BP!DL9 -> 0 | DM9: =+PMGR!DM9+BP!DM9 -> 0 | DN9: =+PMGR!DN9+BP!DN9 -> 0 | DO9: =+PMGR!DO9+BP!DO9 -> 0 | DP9: =+PMGR!DP9+BP!DP9 -> 0 | ... DT9: =+PMGR!DT9+BP!DT9 -> 0 | DU9: =+SUM(DI9:DT9) -> 0 | DW9: =+PMGR!DW9+BP!DW9 -> 0 | DX9: =+PMGR!DX9+BP!DX9 -> 0 | DY9: =+PMGR!DY9+BP!DY9 -> 0 | DZ9: =+PMGR!DZ9+BP!DZ9 -> 0 | EA9: =+PMGR!EA9+BP!EA9 -> 0 | EB9: =+PMGR!EB9+BP!EB9 -> 0 | EC9: =+PMGR!EC9+BP!EC9 -> 0 | ED9: =+PMGR!ED9+BP!ED9 -> 0 | ... EH9: =+PMGR!EH9+BP!EH9 -> 0 | EI9: =+SUM(DW9:EH9) -> 0 | EJ9: Sales Target Bonus | EK9: =+PMGR!EK9+BP!EK9 -> 0 | EL9: =+PMGR!EL9+BP!EL9 -> 0 | EM9: =+PMGR!EM9+BP!EM9 -> 0 | EN9: =+PMGR!EN9+BP!EN9 -> 0 | EO9: =+PMGR!EO9+BP!EO9 -> 0 | EP9: =+PMGR!EP9+BP!EP9 -> 0 | EQ9: =+PMGR!EQ9+BP!EQ9 -> 0 | ER9: =+PMGR!ER9+BP!ER9 -> 0 | ... EV9: =+PMGR!EV9+BP!EV9 -> 0 | EW9: =+SUM(EK9:EV9) -> 0 | EY9: =+PMGR!EY9+BP!EY9 -> 0 | EZ9: =+PMGR!EZ9+BP!EZ9 -> 0 | FA9: =+PMGR!FA9+BP!FA9 -> 0 | FB9: =+PMGR!FB9+BP!FB9 -> 0 | FC9: =+PMGR!FC9+BP!FC9 -> 0 | FD9: =+PMGR!FD9+BP!FD9 -> 0 | FE9: =+PMGR!FE9+BP!FE9 -> 0 | FF9: =+PMGR!FF9+BP!FF9 -> 0 | ... FJ9: =+PMGR!FJ9+BP!FJ9 -> 0 | FK9: =+SUM(EY9:FJ9) -> 0
A10: =+AQ10+CG10+DW10 -> 0 | B10: =+AR10+CH10+DX10 -> 0 | C10: =+AS10+CI10+DY10 -> 0 | D10: =+AT10+CJ10+DZ10 -> 0 | E10: =+AU10+CK10+EA10 -> 0 | F10: =+AV10+CL10+EB10 -> 0 | G10: =+AW10+CM10+EC10 -> 0 | H10: =+AX10+CN10+ED10 -> 0 | ... L10: =+BB10+CR10+EH10 -> 0 | M10: =+SUM(A10:L10) -> 0 | N10: EV | O10: =+BE10+CU10+EK10 -> 0 | P10: =+BF10+CV10+EL10 -> 0 | Q10: =+BG10+CW10+EM10 -> 0 | R10: =+BH10+CX10+EN10 -> 0 | S10: =+BI10+CY10+EO10 -> 0 | T10: =+BJ10+CZ10+EP10 -> 0 | U10: =+BK10+DA10+EQ10 -> 0 | V10: =+BL10+DB10+ER10 -> 0 | ... Z10: =+BP10+DF10+EV10 -> 0 | AA10: =+SUM(O10:Z10) -> 0 | AC10: =+BS10+DI10+EY10 -> 0 | AD10: =+BT10+DJ10+EZ10 -> 0 | AE10: =+BU10+DK10+FA10 -> 0 | AF10: =+BV10+DL10+FB10 -> 0 | AG10: =+BW10+DM10+FC10 -> 0 | AH10: =+BX10+DN10+FD10 -> 0 | AI10: =+BY10+DO10+FE10 -> 0 | AJ10: =+BZ10+DP10+FF10 -> 0 | ... AN10: =+CD10+DT10+FJ10 -> 0 | AO10: =+SUM(AC10:AN10) -> 0 | AQ10: =+PMGR!AQ10+BP!AQ10 -> 0 | AR10: =+PMGR!AR10+BP!AR10 -> 0 | AS10: =+PMGR!AS10+BP!AS10 -> 0 | AT10: =+PMGR!AT10+BP!AT10 -> 0 | AU10: =+PMGR!AU10+BP!AU10 -> 0 | AV10: =+PMGR!AV10+BP!AV10 -> 0 | AW10: =+PMGR!AW10+BP!AW10 -> 0 | AX10: =+PMGR!AX10+BP!AX10 -> 0 | ... BB10: =+PMGR!BB10+BP!BB10 -> 0 | BC10: =+SUM(AQ10:BB10) -> 0 | BD10: EV | BE10: =+PMGR!BE10+BP!BE10 -> 0 | BF10: =+PMGR!BF10+BP!BF10 -> 0 | BG10: =+PMGR!BG10+BP!BG10 -> 0 | BH10: =+PMGR!BH10+BP!BH10 -> 0 | BI10: =+PMGR!BI10+BP!BI10 -> 0 | BJ10: =+PMGR!BJ10+BP!BJ10 -> 0 | BK10: =+PMGR!BK10+BP!BK10 -> 0 | BL10: =+PMGR!BL10+BP!BL10 -> 0 | ... BP10: =+PMGR!BP10+BP!BP10 -> 0 | BQ10: =+SUM(BE10:BP10) -> 0 | BS10: =+PMGR!BS10+BP!BS10 -> 0 | BT10: =+PMGR!BT10+BP!BT10 -> 0 | BU10: =+PMGR!BU10+BP!BU10 -> 0 | BV10: =+PMGR!BV10+BP!BV10 -> 0 | BW10: =+PMGR!BW10+BP!BW10 -> 0 | BX10: =+PMGR!BX10+BP!BX10 -> 0 | BY10: =+PMGR!BY10+BP!BY10 -> 0 | BZ10: =+PMGR!BZ10+BP!BZ10 -> 0 | ... CD10: =+PMGR!CD10+BP!CD10 -> 0 | CE10: =+SUM(BS10:CD10) -> 0 | CG10: =+PMGR!CG10+BP!CG10 -> 0 | CH10: =+PMGR!CH10+BP!CH10 -> 0 | CI10: =+PMGR!CI10+BP!CI10 -> 0 | CJ10: =+PMGR!CJ10+BP!CJ10 -> 0 | CK10: =+PMGR!CK10+BP!CK10 -> 0 | CL10: =+PMGR!CL10+BP!CL10 -> 0 | CM10: =+PMGR!CM10+BP!CM10 -> 0 | CN10: =+PMGR!CN10+BP!CN10 -> 0 | ... CR10: =+PMGR!CR10+BP!CR10 -> 0 | CS10: =+SUM(CG10:CR10) -> 0 | CT10: EV | CU10: =+PMGR!CU10+BP!CU10 -> 0 | CV10: =+PMGR!CV10+BP!CV10 -> 0 | CW10: =+PMGR!CW10+BP!CW10 -> 0 | CX10: =+PMGR!CX10+BP!CX10 -> 0 | CY10: =+PMGR!CY10+BP!CY10 -> 0 | CZ10: =+PMGR!CZ10+BP!CZ10 -> 0 | DA10: =+PMGR!DA10+BP!DA10 -> 0 | DB10: =+PMGR!DB10+BP!DB10 -> 0 | ... DF10: =+PMGR!DF10+BP!DF10 -> 0 | DG10: =+SUM(CU10:DF10) -> 0 | DI10: =+PMGR!DI10+BP!DI10 -> 0 | DJ10: =+PMGR!DJ10+BP!DJ10 -> 0 | DK10: =+PMGR!DK10+BP!DK10 -> 0 | DL10: =+PMGR!DL10+BP!DL10 -> 0 | DM10: =+PMGR!DM10+BP!DM10 -> 0 | DN10: =+PMGR!DN10+BP!DN10 -> 0 | DO10: =+PMGR!DO10+BP!DO10 -> 0 | DP10: =+PMGR!DP10+BP!DP10 -> 0 | ... DT10: =+PMGR!DT10+BP!DT10 -> 0 | DU10: =+SUM(DI10:DT10) -> 0 | DW10: =+PMGR!DW10+BP!DW10 -> 0 | DX10: =+PMGR!DX10+BP!DX10 -> 0 | DY10: =+PMGR!DY10+BP!DY10 -> 0 | DZ10: =+PMGR!DZ10+BP!DZ10 -> 0 | EA10: =+PMGR!EA10+BP!EA10 -> 0 | EB10: =+PMGR!EB10+BP!EB10 -> 0 | EC10: =+PMGR!EC10+BP!EC10 -> 0 | ED10: =+PMGR!ED10+BP!ED10 -> 0 | ... EH10: =+PMGR!EH10+BP!EH10 -> 0 | EI10: =+SUM(DW10:EH10) -> 0 | EJ10: EV | EK10: =+PMGR!EK10+BP!EK10 -> 0 | EL10: =+PMGR!EL10+BP!EL10 -> 0 | EM10: =+PMGR!EM10+BP!EM10 -> 0 | EN10: =+PMGR!EN10+BP!EN10 -> 0 | EO10: =+PMGR!EO10+BP!EO10 -> 0 | EP10: =+PMGR!EP10+BP!EP10 -> 0 | EQ10: =+PMGR!EQ10+BP!EQ10 -> 0 | ER10: =+PMGR!ER10+BP!ER10 -> 0 | ... EV10: =+PMGR!EV10+BP!EV10 -> 0 | EW10: =+SUM(EK10:EV10) -> 0 | EY10: =+PMGR!EY10+BP!EY10 -> 0 | EZ10: =+PMGR!EZ10+BP!EZ10 -> 0 | FA10: =+PMGR!FA10+BP!FA10 -> 0 | FB10: =+PMGR!FB10+BP!FB10 -> 0 | FC10: =+PMGR!FC10+BP!FC10 -> 0 | FD10: =+PMGR!FD10+BP!FD10 -> 0 | FE10: =+PMGR!FE10+BP!FE10 -> 0 | FF10: =+PMGR!FF10+BP!FF10 -> 0 | ... FJ10: =+PMGR!FJ10+BP!FJ10 -> 0 | FK10: =+SUM(EY10:FJ10) -> 0
A11: =+AQ11+CG11+DW11 -> 0 | B11: =+AR11+CH11+DX11 -> 0 | C11: =+AS11+CI11+DY11 -> 0 | D11: =+AT11+CJ11+DZ11 -> 0 | E11: =+AU11+CK11+EA11 -> 0 | F11: =+AV11+CL11+EB11 -> 0 | G11: =+AW11+CM11+EC11 -> 0 | H11: =+AX11+CN11+ED11 -> 0 | ... L11: =+BB11+CR11+EH11 -> 0 | M11: =+SUM(A11:L11) -> 0 | N11: TEV | O11: =+BE11+CU11+EK11 -> 0 | P11: =+BF11+CV11+EL11 -> 0 | Q11: =+BG11+CW11+EM11 -> 0 | R11: =+BH11+CX11+EN11 -> 0 | S11: =+BI11+CY11+EO11 -> 0 | T11: =+BJ11+CZ11+EP11 -> 0 | U11: =+BK11+DA11+EQ11 -> 0 | V11: =+BL11+DB11+ER11 -> 0 | ... Z11: =+BP11+DF11+EV11 -> 0 | AA11: =+SUM(O11:Z11) -> 0 | AC11: =+BS11+DI11+EY11 -> 0 | AD11: =+BT11+DJ11+EZ11 -> 0 | AE11: =+BU11+DK11+FA11 -> 0 | AF11: =+BV11+DL11+FB11 -> 0 | AG11: =+BW11+DM11+FC11 -> 0 | AH11: =+BX11+DN11+FD11 -> 0 | AI11: =+BY11+DO11+FE11 -> 0 | AJ11: =+BZ11+DP11+FF11 -> 0 | ... AN11: =+CD11+DT11+FJ11 -> 0 | AO11: =+SUM(AC11:AN11) -> 0 | AQ11: =+PMGR!AQ11+BP!AQ11 -> 0 | AR11: =+PMGR!AR11+BP!AR11 -> 0 | AS11: =+PMGR!AS11+BP!AS11 -> 0 | AT11: =+PMGR!AT11+BP!AT11 -> 0 | AU11: =+PMGR!AU11+BP!AU11 -> 0 | AV11: =+PMGR!AV11+BP!AV11 -> 0 | AW11: =+PMGR!AW11+BP!AW11 -> 0 | AX11: =+PMGR!AX11+BP!AX11 -> 0 | ... BB11: =+PMGR!BB11+BP!BB11 -> 0 | BC11: =+SUM(AQ11:BB11) -> 0 | BD11: TEV | BE11: =+PMGR!BE11+BP!BE11 -> 0 | BF11: =+PMGR!BF11+BP!BF11 -> 0 | BG11: =+PMGR!BG11+BP!BG11 -> 0 | BH11: =+PMGR!BH11+BP!BH11 -> 0 | BI11: =+PMGR!BI11+BP!BI11 -> 0 | BJ11: =+PMGR!BJ11+BP!BJ11 -> 0 | BK11: =+PMGR!BK11+BP!BK11 -> 0 | BL11: =+PMGR!BL11+BP!BL11 -> 0 | ... BP11: =+PMGR!BP11+BP!BP11 -> 0 | BQ11: =+SUM(BE11:BP11) -> 0 | BS11: =+PMGR!BS11+BP!BS11 -> 0 | BT11: =+PMGR!BT11+BP!BT11 -> 0 | BU11: =+PMGR!BU11+BP!BU11 -> 0 | BV11: =+PMGR!BV11+BP!BV11 -> 0 | BW11: =+PMGR!BW11+BP!BW11 -> 0 | BX11: =+PMGR!BX11+BP!BX11 -> 0 | BY11: =+PMGR!BY11+BP!BY11 -> 0 | BZ11: =+PMGR!BZ11+BP!BZ11 -> 0 | ... CD11: =+PMGR!CD11+BP!CD11 -> 0 | CE11: =+SUM(BS11:CD11) -> 0 | CG11: =+PMGR!CG11+BP!CG11 -> 0 | CH11: =+PMGR!CH11+BP!CH11 -> 0 | CI11: =+PMGR!CI11+BP!CI11 -> 0 | CJ11: =+PMGR!CJ11+BP!CJ11 -> 0 | CK11: =+PMGR!CK11+BP!CK11 -> 0 | CL11: =+PMGR!CL11+BP!CL11 -> 0 | CM11: =+PMGR!CM11+BP!CM11 -> 0 | CN11: =+PMGR!CN11+BP!CN11 -> 0 | ... CR11: =+PMGR!CR11+BP!CR11 -> 0 | CS11: =+SUM(CG11:CR11) -> 0 | CT11: TEV | CU11: =+PMGR!CU11+BP!CU11 -> 0 | CV11: =+PMGR!CV11+BP!CV11 -> 0 | CW11: =+PMGR!CW11+BP!CW11 -> 0 | CX11: =+PMGR!CX11+BP!CX11 -> 0 | CY11: =+PMGR!CY11+BP!CY11 -> 0 | CZ11: =+PMGR!CZ11+BP!CZ11 -> 0 | DA11: =+PMGR!DA11+BP!DA11 -> 0 | DB11: =+PMGR!DB11+BP!DB11 -> 0 | ... DF11: =+PMGR!DF11+BP!DF11 -> 0 | DG11: =+SUM(CU11:DF11) -> 0 | DI11: =+PMGR!DI11+BP!DI11 -> 0 | DJ11: =+PMGR!DJ11+BP!DJ11 -> 0 | DK11: =+PMGR!DK11+BP!DK11 -> 0 | DL11: =+PMGR!DL11+BP!DL11 -> 0 | DM11: =+PMGR!DM11+BP!DM11 -> 0 | DN11: =+PMGR!DN11+BP!DN11 -> 0 | DO11: =+PMGR!DO11+BP!DO11 -> 0 | DP11: =+PMGR!DP11+BP!DP11 -> 0 | ... DT11: =+PMGR!DT11+BP!DT11 -> 0 | DU11: =+SUM(DI11:DT11) -> 0 | DW11: =+PMGR!DW11+BP!DW11 -> 0 | DX11: =+PMGR!DX11+BP!DX11 -> 0 | DY11: =+PMGR!DY11+BP!DY11 -> 0 | DZ11: =+PMGR!DZ11+BP!DZ11 -> 0 | EA11: =+PMGR!EA11+BP!EA11 -> 0 | EB11: =+PMGR!EB11+BP!EB11 -> 0 | EC11: =+PMGR!EC11+BP!EC11 -> 0 | ED11: =+PMGR!ED11+BP!ED11 -> 0 | ... EH11: =+PMGR!EH11+BP!EH11 -> 0 | EI11: =+SUM(DW11:EH11) -> 0 | EJ11: TEV | EK11: =+PMGR!EK11+BP!EK11 -> 0 | EL11: =+PMGR!EL11+BP!EL11 -> 0 | EM11: =+PMGR!EM11+BP!EM11 -> 0 | EN11: =+PMGR!EN11+BP!EN11 -> 0 | EO11: =+PMGR!EO11+BP!EO11 -> 0 | EP11: =+PMGR!EP11+BP!EP11 -> 0 | EQ11: =+PMGR!EQ11+BP!EQ11 -> 0 | ER11: =+PMGR!ER11+BP!ER11 -> 0 | ... EV11: =+PMGR!EV11+BP!EV11 -> 0 | EW11: =+SUM(EK11:EV11) -> 0 | EY11: =+PMGR!EY11+BP!EY11 -> 0 | EZ11: =+PMGR!EZ11+BP!EZ11 -> 0 | FA11: =+PMGR!FA11+BP!FA11 -> 0 | FB11: =+PMGR!FB11+BP!FB11 -> 0 | FC11: =+PMGR!FC11+BP!FC11 -> 0 | FD11: =+PMGR!FD11+BP!FD11 -> 0 | FE11: =+PMGR!FE11+BP!FE11 -> 0 | FF11: =+PMGR!FF11+BP!FF11 -> 0 | ... FJ11: =+PMGR!FJ11+BP!FJ11 -> 0 | FK11: =+SUM(EY11:FJ11) -> 0
A12: =+AQ12+CG12+DW12 -> 0 | B12: =+AR12+CH12+DX12 -> 0 | C12: =+AS12+CI12+DY12 -> 0 | D12: =+AT12+CJ12+DZ12 -> 0 | E12: =+AU12+CK12+EA12 -> 0 | F12: =+AV12+CL12+EB12 -> 0 | G12: =+AW12+CM12+EC12 -> 0 | H12: =+AX12+CN12+ED12 -> 0 | ... L12: =+BB12+CR12+EH12 -> 0 | M12: =+SUM(A12:L12) -> 0 | N12: Market Share Bonus | O12: =+BE12+CU12+EK12 -> 0 | P12: =+BF12+CV12+EL12 -> 0 | Q12: =+BG12+CW12+EM12 -> 0 | R12: =+BH12+CX12+EN12 -> 0 | S12: =+BI12+CY12+EO12 -> 0 | T12: =+BJ12+CZ12+EP12 -> 0 | U12: =+BK12+DA12+EQ12 -> 0 | V12: =+BL12+DB12+ER12 -> 0 | ... Z12: =+BP12+DF12+EV12 -> 0 | AA12: =+SUM(O12:Z12) -> 0 | AC12: =+BS12+DI12+EY12 -> 0 | AD12: =+BT12+DJ12+EZ12 -> 0 | AE12: =+BU12+DK12+FA12 -> 0 | AF12: =+BV12+DL12+FB12 -> 0 | AG12: =+BW12+DM12+FC12 -> 0 | AH12: =+BX12+DN12+FD12 -> 0 | AI12: =+BY12+DO12+FE12 -> 0 | AJ12: =+BZ12+DP12+FF12 -> 0 | ... AN12: =+CD12+DT12+FJ12 -> 0 | AO12: =+SUM(AC12:AN12) -> 0 | AQ12: =+PMGR!AQ12+BP!AQ12 -> 0 | AR12: =+PMGR!AR12+BP!AR12 -> 0 | AS12: =+PMGR!AS12+BP!AS12 -> 0 | AT12: =+PMGR!AT12+BP!AT12 -> 0 | AU12: =+PMGR!AU12+BP!AU12 -> 0 | AV12: =+PMGR!AV12+BP!AV12 -> 0 | AW12: =+PMGR!AW12+BP!AW12 -> 0 | AX12: =+PMGR!AX12+BP!AX12 -> 0 | ... BB12: =+PMGR!BB12+BP!BB12 -> 0 | BC12: =+SUM(AQ12:BB12) -> 0 | BD12: Market Share Bonus | BE12: =+PMGR!BE12+BP!BE12 -> 0 | BF12: =+PMGR!BF12+BP!BF12 -> 0 | BG12: =+PMGR!BG12+BP!BG12 -> 0 | BH12: =+PMGR!BH12+BP!BH12 -> 0 | BI12: =+PMGR!BI12+BP!BI12 -> 0 | BJ12: =+PMGR!BJ12+BP!BJ12 -> 0 | BK12: =+PMGR!BK12+BP!BK12 -> 0 | BL12: =+PMGR!BL12+BP!BL12 -> 0 | ... BP12: =+PMGR!BP12+BP!BP12 -> 0 | BQ12: =+SUM(BE12:BP12) -> 0 | BS12: =+PMGR!BS12+BP!BS12 -> 0 | BT12: =+PMGR!BT12+BP!BT12 -> 0 | BU12: =+PMGR!BU12+BP!BU12 -> 0 | BV12: =+PMGR!BV12+BP!BV12 -> 0 | BW12: =+PMGR!BW12+BP!BW12 -> 0 | BX12: =+PMGR!BX12+BP!BX12 -> 0 | BY12: =+PMGR!BY12+BP!BY12 -> 0 | BZ12: =+PMGR!BZ12+BP!BZ12 -> 0 | ... CD12: =+PMGR!CD12+BP!CD12 -> 0 | CE12: =+SUM(BS12:CD12) -> 0 | CG12: =+PMGR!CG12+BP!CG12 -> 0 | CH12: =+PMGR!CH12+BP!CH12 -> 0 | CI12: =+PMGR!CI12+BP!CI12 -> 0 | CJ12: =+PMGR!CJ12+BP!CJ12 -> 0 | CK12: =+PMGR!CK12+BP!CK12 -> 0 | CL12: =+PMGR!CL12+BP!CL12 -> 0 | CM12: =+PMGR!CM12+BP!CM12 -> 0 | CN12: =+PMGR!CN12+BP!CN12 -> 0 | ... CR12: =+PMGR!CR12+BP!CR12 -> 0 | CS12: =+SUM(CG12:CR12) -> 0 | CT12: Market Share Bonus | CU12: =+PMGR!CU12+BP!CU12 -> 0 | CV12: =+PMGR!CV12+BP!CV12 -> 0 | CW12: =+PMGR!CW12+BP!CW12 -> 0 | CX12: =+PMGR!CX12+BP!CX12 -> 0 | CY12: =+PMGR!CY12+BP!CY12 -> 0 | CZ12: =+PMGR!CZ12+BP!CZ12 -> 0 | DA12: =+PMGR!DA12+BP!DA12 -> 0 | DB12: =+PMGR!DB12+BP!DB12 -> 0 | ... DF12: =+PMGR!DF12+BP!DF12 -> 0 | DG12: =+SUM(CU12:DF12) -> 0 | DI12: =+PMGR!DI12+BP!DI12 -> 0 | DJ12: =+PMGR!DJ12+BP!DJ12 -> 0 | DK12: =+PMGR!DK12+BP!DK12 -> 0 | DL12: =+PMGR!DL12+BP!DL12 -> 0 | DM12: =+PMGR!DM12+BP!DM12 -> 0 | DN12: =+PMGR!DN12+BP!DN12 -> 0 | DO12: =+PMGR!DO12+BP!DO12 -> 0 | DP12: =+PMGR!DP12+BP!DP12 -> 0 | ... DT12: =+PMGR!DT12+BP!DT12 -> 0 | DU12: =+SUM(DI12:DT12) -> 0 | DW12: =+PMGR!DW12+BP!DW12 -> 0 | DX12: =+PMGR!DX12+BP!DX12 -> 0 | DY12: =+PMGR!DY12+BP!DY12 -> 0 | DZ12: =+PMGR!DZ12+BP!DZ12 -> 0 | EA12: =+PMGR!EA12+BP!EA12 -> 0 | EB12: =+PMGR!EB12+BP!EB12 -> 0 | EC12: =+PMGR!EC12+BP!EC12 -> 0 | ED12: =+PMGR!ED12+BP!ED12 -> 0 | ... EH12: =+PMGR!EH12+BP!EH12 -> 0 | EI12: =+SUM(DW12:EH12) -> 0 | EJ12: Market Share Bonus | EK12: =+PMGR!EK12+BP!EK12 -> 0 | EL12: =+PMGR!EL12+BP!EL12 -> 0 | EM12: =+PMGR!EM12+BP!EM12 -> 0 | EN12: =+PMGR!EN12+BP!EN12 -> 0 | EO12: =+PMGR!EO12+BP!EO12 -> 0 | EP12: =+PMGR!EP12+BP!EP12 -> 0 | EQ12: =+PMGR!EQ12+BP!EQ12 -> 0 | ER12: =+PMGR!ER12+BP!ER12 -> 0 | ... EV12: =+PMGR!EV12+BP!EV12 -> 0 | EW12: =+SUM(EK12:EV12) -> 0 | EY12: =+PMGR!EY12+BP!EY12 -> 0 | EZ12: =+PMGR!EZ12+BP!EZ12 -> 0 | FA12: =+PMGR!FA12+BP!FA12 -> 0 | FB12: =+PMGR!FB12+BP!FB12 -> 0 | FC12: =+PMGR!FC12+BP!FC12 -> 0 | FD12: =+PMGR!FD12+BP!FD12 -> 0 | FE12: =+PMGR!FE12+BP!FE12 -> 0 | FF12: =+PMGR!FF12+BP!FF12 -> 0 | ... FJ12: =+PMGR!FJ12+BP!FJ12 -> 0 | FK12: =+SUM(EY12:FJ12) -> 0
A13: =+SUM(A14:A17) -> 0 | B13: =+SUM(B14:B17) -> 0 | C13: =+SUM(C14:C17) -> 0 | D13: =+SUM(D14:D17) -> 0 | E13: =+SUM(E14:E17) -> 0 | F13: =+SUM(F14:F17) -> 0 | G13: =+SUM(G14:G17) -> 0 | H13: =+SUM(H14:H17) -> 0 | ... L13: =+SUM(L14:L17) -> 0 | M13: =+SUM(A13:L13) -> 0 | N13: Quantitative Margin | O13: =+SUM(O14:O17) -> 0 | P13: =+SUM(P14:P17) -> 0 | Q13: =+SUM(Q14:Q17) -> 0 | R13: =+SUM(R14:R17) -> 0 | S13: =+SUM(S14:S17) -> 0 | T13: =+SUM(T14:T17) -> 0 | U13: =+SUM(U14:U17) -> 0 | V13: =+SUM(V14:V17) -> 0 | ... Z13: =+SUM(Z14:Z17) -> 0 | AA13: =+SUM(O13:Z13) -> 0 | AC13: =+SUM(AC14:AC17) -> 0 | AD13: =+SUM(AD14:AD17) -> 0 | AE13: =+SUM(AE14:AE17) -> 0 | AF13: =+SUM(AF14:AF17) -> 0 | AG13: =+SUM(AG14:AG17) -> 0 | AH13: =+SUM(AH14:AH17) -> 0 | AI13: =+SUM(AI14:AI17) -> 0 | AJ13: =+SUM(AJ14:AJ17) -> 0 | ... AN13: =+SUM(AN14:AN17) -> 0 | AO13: =+SUM(AC13:AN13) -> 0 | AQ13: =+SUM(AQ14:AQ17) -> 0 | AR13: =+SUM(AR14:AR17) -> 0 | AS13: =+SUM(AS14:AS17) -> 0 | AT13: =+SUM(AT14:AT17) -> 0 | AU13: =+SUM(AU14:AU17) -> 0 | AV13: =+SUM(AV14:AV17) -> 0 | AW13: =+SUM(AW14:AW17) -> 0 | AX13: =+SUM(AX14:AX17) -> 0 | ... BB13: =+SUM(BB14:BB17) -> 0 | BC13: =+SUM(AQ13:BB13) -> 0 | BD13: =N13 -> Quantitative Margin | BE13: =+SUM(BE14:BE17) -> 0 | BF13: =+SUM(BF14:BF17) -> 0 | BG13: =+SUM(BG14:BG17) -> 0 | BH13: =+SUM(BH14:BH17) -> 0 | BI13: =+SUM(BI14:BI17) -> 0 | BJ13: =+SUM(BJ14:BJ17) -> 0 | BK13: =+SUM(BK14:BK17) -> 0 | BL13: =+SUM(BL14:BL17) -> 0 | ... BP13: =+SUM(BP14:BP17) -> 0 | BQ13: =+SUM(BE13:BP13) -> 0 | BS13: =+SUM(BS14:BS17) -> 0 | BT13: =+SUM(BT14:BT17) -> 0 | BU13: =+SUM(BU14:BU17) -> 0 | BV13: =+SUM(BV14:BV17) -> 0 | BW13: =+SUM(BW14:BW17) -> 0 | BX13: =+SUM(BX14:BX17) -> 0 | BY13: =+SUM(BY14:BY17) -> 0 | BZ13: =+SUM(BZ14:BZ17) -> 0 | ... CD13: =+SUM(CD14:CD17) -> 0 | CE13: =+SUM(BS13:CD13) -> 0 | CG13: =+SUM(CG14:CG17) -> 0 | CH13: =+SUM(CH14:CH17) -> 0 | CI13: =+SUM(CI14:CI17) -> 0 | CJ13: =+SUM(CJ14:CJ17) -> 0 | CK13: =+SUM(CK14:CK17) -> 0 | CL13: =+SUM(CL14:CL17) -> 0 | CM13: =+SUM(CM14:CM17) -> 0 | CN13: =+SUM(CN14:CN17) -> 0 | ... CR13: =+SUM(CR14:CR17) -> 0 | CS13: =+SUM(CG13:CR13) -> 0 | CT13: =BD13 -> Quantitative Margin | CU13: =+SUM(CU14:CU17) -> 0 | CV13: =+SUM(CV14:CV17) -> 0 | CW13: =+SUM(CW14:CW17) -> 0 | CX13: =+SUM(CX14:CX17) -> 0 | CY13: =+SUM(CY14:CY17) -> 0 | CZ13: =+SUM(CZ14:CZ17) -> 0 | DA13: =+SUM(DA14:DA17) -> 0 | DB13: =+SUM(DB14:DB17) -> 0 | ... DF13: =+SUM(DF14:DF17) -> 0 | DG13: =+SUM(CU13:DF13) -> 0 | DI13: =+SUM(DI14:DI17) -> 0 | DJ13: =+SUM(DJ14:DJ17) -> 0 | DK13: =+SUM(DK14:DK17) -> 0 | DL13: =+SUM(DL14:DL17) -> 0 | DM13: =+SUM(DM14:DM17) -> 0 | DN13: =+SUM(DN14:DN17) -> 0 | DO13: =+SUM(DO14:DO17) -> 0 | DP13: =+SUM(DP14:DP17) -> 0 | ... DT13: =+SUM(DT14:DT17) -> 0 | DU13: =+SUM(DI13:DT13) -> 0 | DW13: =+SUM(DW14:DW17) -> 0 | DX13: =+SUM(DX14:DX17) -> 0 | DY13: =+SUM(DY14:DY17) -> 0 | DZ13: =+SUM(DZ14:DZ17) -> 0 | EA13: =+SUM(EA14:EA17) -> 0 | EB13: =+SUM(EB14:EB17) -> 0 | EC13: =+SUM(EC14:EC17) -> 0 | ED13: =+SUM(ED14:ED17) -> 0 | ... EH13: =+SUM(EH14:EH17) -> 0 | EI13: =+SUM(DW13:EH13) -> 0 | EJ13: =CT13 -> Quantitative Margin | EK13: =+SUM(EK14:EK17) -> 0 | EL13: =+SUM(EL14:EL17) -> 0 | EM13: =+SUM(EM14:EM17) -> 0 | EN13: =+SUM(EN14:EN17) -> 0 | EO13: =+SUM(EO14:EO17) -> 0 | EP13: =+SUM(EP14:EP17) -> 0 | EQ13: =+SUM(EQ14:EQ17) -> 0 | ER13: =+SUM(ER14:ER17) -> 0 | ... EV13: =+SUM(EV14:EV17) -> 0 | EW13: =+SUM(EK13:EV13) -> 0 | EY13: =+SUM(EY14:EY17) -> 0 | EZ13: =+SUM(EZ14:EZ17) -> 0 | FA13: =+SUM(FA14:FA17) -> 0 | FB13: =+SUM(FB14:FB17) -> 0 | FC13: =+SUM(FC14:FC17) -> 0 | FD13: =+SUM(FD14:FD17) -> 0 | FE13: =+SUM(FE14:FE17) -> 0 | FF13: =+SUM(FF14:FF17) -> 0 | ... FJ13: =+SUM(FJ14:FJ17) -> 0 | FK13: =+SUM(EY13:FJ13) -> 0
A14: =+AQ14+CG14+DW14 -> 0 | B14: =+AR14+CH14+DX14 -> 0 | C14: =+AS14+CI14+DY14 -> 0 | D14: =+AT14+CJ14+DZ14 -> 0 | E14: =+AU14+CK14+EA14 -> 0 | F14: =+AV14+CL14+EB14 -> 0 | G14: =+AW14+CM14+EC14 -> 0 | H14: =+AX14+CN14+ED14 -> 0 | ... L14: =+BB14+CR14+EH14 -> 0 | M14: =+SUM(A14:L14) -> 0 | N14: Digital and Lead Management | O14: =+BE14+CU14+EK14 -> 0 | P14: =+BF14+CV14+EL14 -> 0 | Q14: =+BG14+CW14+EM14 -> 0 | R14: =+BH14+CX14+EN14 -> 0 | S14: =+BI14+CY14+EO14 -> 0 | T14: =+BJ14+CZ14+EP14 -> 0 | U14: =+BK14+DA14+EQ14 -> 0 | V14: =+BL14+DB14+ER14 -> 0 | ... Z14: =+BP14+DF14+EV14 -> 0 | AA14: =+SUM(O14:Z14) -> 0 | AC14: =+BS14+DI14+EY14 -> 0 | AD14: =+BT14+DJ14+EZ14 -> 0 | AE14: =+BU14+DK14+FA14 -> 0 | AF14: =+BV14+DL14+FB14 -> 0 | AG14: =+BW14+DM14+FC14 -> 0 | AH14: =+BX14+DN14+FD14 -> 0 | AI14: =+BY14+DO14+FE14 -> 0 | AJ14: =+BZ14+DP14+FF14 -> 0 | ... AN14: =+CD14+DT14+FJ14 -> 0 | AO14: =+SUM(AC14:AN14) -> 0 | AQ14: =+PMGR!AQ14+BP!AQ14 -> 0 | AR14: =+PMGR!AR14+BP!AR14 -> 0 | AS14: =+PMGR!AS14+BP!AS14 -> 0 | AT14: =+PMGR!AT14+BP!AT14 -> 0 | AU14: =+PMGR!AU14+BP!AU14 -> 0 | AV14: =+PMGR!AV14+BP!AV14 -> 0 | AW14: =+PMGR!AW14+BP!AW14 -> 0 | AX14: =+PMGR!AX14+BP!AX14 -> 0 | ... BB14: =+PMGR!BB14+BP!BB14 -> 0 | BC14: =+SUM(AQ14:BB14) -> 0 | BD14: =N14 -> Digital and Lead Management | BE14: =+PMGR!BE14+BP!BE14 -> 0 | BF14: =+PMGR!BF14+BP!BF14 -> 0 | BG14: =+PMGR!BG14+BP!BG14 -> 0 | BH14: =+PMGR!BH14+BP!BH14 -> 0 | BI14: =+PMGR!BI14+BP!BI14 -> 0 | BJ14: =+PMGR!BJ14+BP!BJ14 -> 0 | BK14: =+PMGR!BK14+BP!BK14 -> 0 | BL14: =+PMGR!BL14+BP!BL14 -> 0 | ... BP14: =+PMGR!BP14+BP!BP14 -> 0 | BQ14: =+SUM(BE14:BP14) -> 0 | BS14: =+PMGR!BS14+BP!BS14 -> 0 | BT14: =+PMGR!BT14+BP!BT14 -> 0 | BU14: =+PMGR!BU14+BP!BU14 -> 0 | BV14: =+PMGR!BV14+BP!BV14 -> 0 | BW14: =+PMGR!BW14+BP!BW14 -> 0 | BX14: =+PMGR!BX14+BP!BX14 -> 0 | BY14: =+PMGR!BY14+BP!BY14 -> 0 | BZ14: =+PMGR!BZ14+BP!BZ14 -> 0 | ... CD14: =+PMGR!CD14+BP!CD14 -> 0 | CE14: =+SUM(BS14:CD14) -> 0 | CG14: =+PMGR!CG14+BP!CG14 -> 0 | CH14: =+PMGR!CH14+BP!CH14 -> 0 | CI14: =+PMGR!CI14+BP!CI14 -> 0 | CJ14: =+PMGR!CJ14+BP!CJ14 -> 0 | CK14: =+PMGR!CK14+BP!CK14 -> 0 | CL14: =+PMGR!CL14+BP!CL14 -> 0 | CM14: =+PMGR!CM14+BP!CM14 -> 0 | CN14: =+PMGR!CN14+BP!CN14 -> 0 | ... CR14: =+PMGR!CR14+BP!CR14 -> 0 | CS14: =+SUM(CG14:CR14) -> 0 | CT14: =BD14 -> Digital and Lead Management | CU14: =+PMGR!CU14+BP!CU14 -> 0 | CV14: =+PMGR!CV14+BP!CV14 -> 0 | CW14: =+PMGR!CW14+BP!CW14 -> 0 | CX14: =+PMGR!CX14+BP!CX14 -> 0 | CY14: =+PMGR!CY14+BP!CY14 -> 0 | CZ14: =+PMGR!CZ14+BP!CZ14 -> 0 | DA14: =+PMGR!DA14+BP!DA14 -> 0 | DB14: =+PMGR!DB14+BP!DB14 -> 0 | ... DF14: =+PMGR!DF14+BP!DF14 -> 0 | DG14: =+SUM(CU14:DF14) -> 0 | DI14: =+PMGR!DI14+BP!DI14 -> 0 | DJ14: =+PMGR!DJ14+BP!DJ14 -> 0 | DK14: =+PMGR!DK14+BP!DK14 -> 0 | DL14: =+PMGR!DL14+BP!DL14 -> 0 | DM14: =+PMGR!DM14+BP!DM14 -> 0 | DN14: =+PMGR!DN14+BP!DN14 -> 0 | DO14: =+PMGR!DO14+BP!DO14 -> 0 | DP14: =+PMGR!DP14+BP!DP14 -> 0 | ... DT14: =+PMGR!DT14+BP!DT14 -> 0 | DU14: =+SUM(DI14:DT14) -> 0 | DW14: =+PMGR!DW14+BP!DW14 -> 0 | DX14: =+PMGR!DX14+BP!DX14 -> 0 | DY14: =+PMGR!DY14+BP!DY14 -> 0 | DZ14: =+PMGR!DZ14+BP!DZ14 -> 0 | EA14: =+PMGR!EA14+BP!EA14 -> 0 | EB14: =+PMGR!EB14+BP!EB14 -> 0 | EC14: =+PMGR!EC14+BP!EC14 -> 0 | ED14: =+PMGR!ED14+BP!ED14 -> 0 | ... EH14: =+PMGR!EH14+BP!EH14 -> 0 | EI14: =+SUM(DW14:EH14) -> 0 | EJ14: =CT14 -> Digital and Lead Management | EK14: =+PMGR!EK14+BP!EK14 -> 0 | EL14: =+PMGR!EL14+BP!EL14 -> 0 | EM14: =+PMGR!EM14+BP!EM14 -> 0 | EN14: =+PMGR!EN14+BP!EN14 -> 0 | EO14: =+PMGR!EO14+BP!EO14 -> 0 | EP14: =+PMGR!EP14+BP!EP14 -> 0 | EQ14: =+PMGR!EQ14+BP!EQ14 -> 0 | ER14: =+PMGR!ER14+BP!ER14 -> 0 | ... EV14: =+PMGR!EV14+BP!EV14 -> 0 | EW14: =+SUM(EK14:EV14) -> 0 | EY14: =+PMGR!EY14+BP!EY14 -> 0 | EZ14: =+PMGR!EZ14+BP!EZ14 -> 0 | FA14: =+PMGR!FA14+BP!FA14 -> 0 | FB14: =+PMGR!FB14+BP!FB14 -> 0 | FC14: =+PMGR!FC14+BP!FC14 -> 0 | FD14: =+PMGR!FD14+BP!FD14 -> 0 | FE14: =+PMGR!FE14+BP!FE14 -> 0 | FF14: =+PMGR!FF14+BP!FF14 -> 0 | ... FJ14: =+PMGR!FJ14+BP!FJ14 -> 0 | FK14: =+SUM(EY14:FJ14) -> 0
A15: =+AQ15+CG15+DW15 -> 0 | B15: =+AR15+CH15+DX15 -> 0 | C15: =+AS15+CI15+DY15 -> 0 | D15: =+AT15+CJ15+DZ15 -> 0 | E15: =+AU15+CK15+EA15 -> 0 | F15: =+AV15+CL15+EB15 -> 0 | G15: =+AW15+CM15+EC15 -> 0 | H15: =+AX15+CN15+ED15 -> 0 | ... L15: =+BB15+CR15+EH15 -> 0 | M15: =+SUM(A15:L15) -> 0 | N15: Customer Experience | O15: =+BE15+CU15+EK15 -> 0 | P15: =+BF15+CV15+EL15 -> 0 | Q15: =+BG15+CW15+EM15 -> 0 | R15: =+BH15+CX15+EN15 -> 0 | S15: =+BI15+CY15+EO15 -> 0 | T15: =+BJ15+CZ15+EP15 -> 0 | U15: =+BK15+DA15+EQ15 -> 0 | V15: =+BL15+DB15+ER15 -> 0 | ... Z15: =+BP15+DF15+EV15 -> 0 | AA15: =+SUM(O15:Z15) -> 0 | AC15: =+BS15+DI15+EY15 -> 0 | AD15: =+BT15+DJ15+EZ15 -> 0 | AE15: =+BU15+DK15+FA15 -> 0 | AF15: =+BV15+DL15+FB15 -> 0 | AG15: =+BW15+DM15+FC15 -> 0 | AH15: =+BX15+DN15+FD15 -> 0 | AI15: =+BY15+DO15+FE15 -> 0 | AJ15: =+BZ15+DP15+FF15 -> 0 | ... AN15: =+CD15+DT15+FJ15 -> 0 | AO15: =+SUM(AC15:AN15) -> 0 | AQ15: =+PMGR!AQ15+BP!AQ15 -> 0 | AR15: =+PMGR!AR15+BP!AR15 -> 0 | AS15: =+PMGR!AS15+BP!AS15 -> 0 | AT15: =+PMGR!AT15+BP!AT15 -> 0 | AU15: =+PMGR!AU15+BP!AU15 -> 0 | AV15: =+PMGR!AV15+BP!AV15 -> 0 | AW15: =+PMGR!AW15+BP!AW15 -> 0 | AX15: =+PMGR!AX15+BP!AX15 -> 0 | ... BB15: =+PMGR!BB15+BP!BB15 -> 0 | BC15: =+SUM(AQ15:BB15) -> 0 | BD15: =N15 -> Customer Experience | BE15: =+PMGR!BE15+BP!BE15 -> 0 | BF15: =+PMGR!BF15+BP!BF15 -> 0 | BG15: =+PMGR!BG15+BP!BG15 -> 0 | BH15: =+PMGR!BH15+BP!BH15 -> 0 | BI15: =+PMGR!BI15+BP!BI15 -> 0 | BJ15: =+PMGR!BJ15+BP!BJ15 -> 0 | BK15: =+PMGR!BK15+BP!BK15 -> 0 | BL15: =+PMGR!BL15+BP!BL15 -> 0 | ... BP15: =+PMGR!BP15+BP!BP15 -> 0 | BQ15: =+SUM(BE15:BP15) -> 0 | BS15: =+PMGR!BS15+BP!BS15 -> 0 | BT15: =+PMGR!BT15+BP!BT15 -> 0 | BU15: =+PMGR!BU15+BP!BU15 -> 0 | BV15: =+PMGR!BV15+BP!BV15 -> 0 | BW15: =+PMGR!BW15+BP!BW15 -> 0 | BX15: =+PMGR!BX15+BP!BX15 -> 0 | BY15: =+PMGR!BY15+BP!BY15 -> 0 | BZ15: =+PMGR!BZ15+BP!BZ15 -> 0 | ... CD15: =+PMGR!CD15+BP!CD15 -> 0 | CE15: =+SUM(BS15:CD15) -> 0 | CG15: =+PMGR!CG15+BP!CG15 -> 0 | CH15: =+PMGR!CH15+BP!CH15 -> 0 | CI15: =+PMGR!CI15+BP!CI15 -> 0 | CJ15: =+PMGR!CJ15+BP!CJ15 -> 0 | CK15: =+PMGR!CK15+BP!CK15 -> 0 | CL15: =+PMGR!CL15+BP!CL15 -> 0 | CM15: =+PMGR!CM15+BP!CM15 -> 0 | CN15: =+PMGR!CN15+BP!CN15 -> 0 | ... CR15: =+PMGR!CR15+BP!CR15 -> 0 | CS15: =+SUM(CG15:CR15) -> 0 | CT15: =BD15 -> Customer Experience | CU15: =+PMGR!CU15+BP!CU15 -> 0 | CV15: =+PMGR!CV15+BP!CV15 -> 0 | CW15: =+PMGR!CW15+BP!CW15 -> 0 | CX15: =+PMGR!CX15+BP!CX15 -> 0 | CY15: =+PMGR!CY15+BP!CY15 -> 0 | CZ15: =+PMGR!CZ15+BP!CZ15 -> 0 | DA15: =+PMGR!DA15+BP!DA15 -> 0 | DB15: =+PMGR!DB15+BP!DB15 -> 0 | ... DF15: =+PMGR!DF15+BP!DF15 -> 0 | DG15: =+SUM(CU15:DF15) -> 0 | DI15: =+PMGR!DI15+BP!DI15 -> 0 | DJ15: =+PMGR!DJ15+BP!DJ15 -> 0 | DK15: =+PMGR!DK15+BP!DK15 -> 0 | DL15: =+PMGR!DL15+BP!DL15 -> 0 | DM15: =+PMGR!DM15+BP!DM15 -> 0 | DN15: =+PMGR!DN15+BP!DN15 -> 0 | DO15: =+PMGR!DO15+BP!DO15 -> 0 | DP15: =+PMGR!DP15+BP!DP15 -> 0 | ... DT15: =+PMGR!DT15+BP!DT15 -> 0 | DU15: =+SUM(DI15:DT15) -> 0 | DW15: =+PMGR!DW15+BP!DW15 -> 0 | DX15: =+PMGR!DX15+BP!DX15 -> 0 | DY15: =+PMGR!DY15+BP!DY15 -> 0 | DZ15: =+PMGR!DZ15+BP!DZ15 -> 0 | EA15: =+PMGR!EA15+BP!EA15 -> 0 | EB15: =+PMGR!EB15+BP!EB15 -> 0 | EC15: =+PMGR!EC15+BP!EC15 -> 0 | ED15: =+PMGR!ED15+BP!ED15 -> 0 | ... EH15: =+PMGR!EH15+BP!EH15 -> 0 | EI15: =+SUM(DW15:EH15) -> 0 | EJ15: =CT15 -> Customer Experience | EK15: =+PMGR!EK15+BP!EK15 -> 0 | EL15: =+PMGR!EL15+BP!EL15 -> 0 | EM15: =+PMGR!EM15+BP!EM15 -> 0 | EN15: =+PMGR!EN15+BP!EN15 -> 0 | EO15: =+PMGR!EO15+BP!EO15 -> 0 | EP15: =+PMGR!EP15+BP!EP15 -> 0 | EQ15: =+PMGR!EQ15+BP!EQ15 -> 0 | ER15: =+PMGR!ER15+BP!ER15 -> 0 | ... EV15: =+PMGR!EV15+BP!EV15 -> 0 | EW15: =+SUM(EK15:EV15) -> 0 | EY15: =+PMGR!EY15+BP!EY15 -> 0 | EZ15: =+PMGR!EZ15+BP!EZ15 -> 0 | FA15: =+PMGR!FA15+BP!FA15 -> 0 | FB15: =+PMGR!FB15+BP!FB15 -> 0 | FC15: =+PMGR!FC15+BP!FC15 -> 0 | FD15: =+PMGR!FD15+BP!FD15 -> 0 | FE15: =+PMGR!FE15+BP!FE15 -> 0 | FF15: =+PMGR!FF15+BP!FF15 -> 0 | ... FJ15: =+PMGR!FJ15+BP!FJ15 -> 0 | FK15: =+SUM(EY15:FJ15) -> 0
A16: =+AQ16+CG16+DW16 -> 0 | B16: =+AR16+CH16+DX16 -> 0 | C16: =+AS16+CI16+DY16 -> 0 | D16: =+AT16+CJ16+DZ16 -> 0 | E16: =+AU16+CK16+EA16 -> 0 | F16: =+AV16+CL16+EB16 -> 0 | G16: =+AW16+CM16+EC16 -> 0 | H16: =+AX16+CN16+ED16 -> 0 | ... L16: =+BB16+CR16+EH16 -> 0 | M16: =+SUM(A16:L16) -> 0 | N16: Marketing And Process Steering | O16: =+BE16+CU16+EK16 -> 0 | P16: =+BF16+CV16+EL16 -> 0 | Q16: =+BG16+CW16+EM16 -> 0 | R16: =+BH16+CX16+EN16 -> 0 | S16: =+BI16+CY16+EO16 -> 0 | T16: =+BJ16+CZ16+EP16 -> 0 | U16: =+BK16+DA16+EQ16 -> 0 | V16: =+BL16+DB16+ER16 -> 0 | ... Z16: =+BP16+DF16+EV16 -> 0 | AA16: =+SUM(O16:Z16) -> 0 | AC16: =+BS16+DI16+EY16 -> 0 | AD16: =+BT16+DJ16+EZ16 -> 0 | AE16: =+BU16+DK16+FA16 -> 0 | AF16: =+BV16+DL16+FB16 -> 0 | AG16: =+BW16+DM16+FC16 -> 0 | AH16: =+BX16+DN16+FD16 -> 0 | AI16: =+BY16+DO16+FE16 -> 0 | AJ16: =+BZ16+DP16+FF16 -> 0 | ... AN16: =+CD16+DT16+FJ16 -> 0 | AO16: =+SUM(AC16:AN16) -> 0 | AQ16: =+PMGR!AQ16+BP!AQ16 -> 0 | AR16: =+PMGR!AR16+BP!AR16 -> 0 | AS16: =+PMGR!AS16+BP!AS16 -> 0 | AT16: =+PMGR!AT16+BP!AT16 -> 0 | AU16: =+PMGR!AU16+BP!AU16 -> 0 | AV16: =+PMGR!AV16+BP!AV16 -> 0 | AW16: =+PMGR!AW16+BP!AW16 -> 0 | AX16: =+PMGR!AX16+BP!AX16 -> 0 | ... BB16: =+PMGR!BB16+BP!BB16 -> 0 | BC16: =+SUM(AQ16:BB16) -> 0 | BD16: =N16 -> Marketing And Process Steering | BE16: =+PMGR!BE16+BP!BE16 -> 0 | BF16: =+PMGR!BF16+BP!BF16 -> 0 | BG16: =+PMGR!BG16+BP!BG16 -> 0 | BH16: =+PMGR!BH16+BP!BH16 -> 0 | BI16: =+PMGR!BI16+BP!BI16 -> 0 | BJ16: =+PMGR!BJ16+BP!BJ16 -> 0 | BK16: =+PMGR!BK16+BP!BK16 -> 0 | BL16: =+PMGR!BL16+BP!BL16 -> 0 | ... BP16: =+PMGR!BP16+BP!BP16 -> 0 | BQ16: =+SUM(BE16:BP16) -> 0 | BS16: =+PMGR!BS16+BP!BS16 -> 0 | BT16: =+PMGR!BT16+BP!BT16 -> 0 | BU16: =+PMGR!BU16+BP!BU16 -> 0 | BV16: =+PMGR!BV16+BP!BV16 -> 0 | BW16: =+PMGR!BW16+BP!BW16 -> 0 | BX16: =+PMGR!BX16+BP!BX16 -> 0 | BY16: =+PMGR!BY16+BP!BY16 -> 0 | BZ16: =+PMGR!BZ16+BP!BZ16 -> 0 | ... CD16: =+PMGR!CD16+BP!CD16 -> 0 | CE16: =+SUM(BS16:CD16) -> 0 | CG16: =+PMGR!CG16+BP!CG16 -> 0 | CH16: =+PMGR!CH16+BP!CH16 -> 0 | CI16: =+PMGR!CI16+BP!CI16 -> 0 | CJ16: =+PMGR!CJ16+BP!CJ16 -> 0 | CK16: =+PMGR!CK16+BP!CK16 -> 0 | CL16: =+PMGR!CL16+BP!CL16 -> 0 | CM16: =+PMGR!CM16+BP!CM16 -> 0 | CN16: =+PMGR!CN16+BP!CN16 -> 0 | ... CR16: =+PMGR!CR16+BP!CR16 -> 0 | CS16: =+SUM(CG16:CR16) -> 0 | CT16: =BD16 -> Marketing And Process Steering | CU16: =+PMGR!CU16+BP!CU16 -> 0 | CV16: =+PMGR!CV16+BP!CV16 -> 0 | CW16: =+PMGR!CW16+BP!CW16 -> 0 | CX16: =+PMGR!CX16+BP!CX16 -> 0 | CY16: =+PMGR!CY16+BP!CY16 -> 0 | CZ16: =+PMGR!CZ16+BP!CZ16 -> 0 | DA16: =+PMGR!DA16+BP!DA16 -> 0 | DB16: =+PMGR!DB16+BP!DB16 -> 0 | ... DF16: =+PMGR!DF16+BP!DF16 -> 0 | DG16: =+SUM(CU16:DF16) -> 0 | DI16: =+PMGR!DI16+BP!DI16 -> 0 | DJ16: =+PMGR!DJ16+BP!DJ16 -> 0 | DK16: =+PMGR!DK16+BP!DK16 -> 0 | DL16: =+PMGR!DL16+BP!DL16 -> 0 | DM16: =+PMGR!DM16+BP!DM16 -> 0 | DN16: =+PMGR!DN16+BP!DN16 -> 0 | DO16: =+PMGR!DO16+BP!DO16 -> 0 | DP16: =+PMGR!DP16+BP!DP16 -> 0 | ... DT16: =+PMGR!DT16+BP!DT16 -> 0 | DU16: =+SUM(DI16:DT16) -> 0 | DW16: =+PMGR!DW16+BP!DW16 -> 0 | DX16: =+PMGR!DX16+BP!DX16 -> 0 | DY16: =+PMGR!DY16+BP!DY16 -> 0 | DZ16: =+PMGR!DZ16+BP!DZ16 -> 0 | EA16: =+PMGR!EA16+BP!EA16 -> 0 | EB16: =+PMGR!EB16+BP!EB16 -> 0 | EC16: =+PMGR!EC16+BP!EC16 -> 0 | ED16: =+PMGR!ED16+BP!ED16 -> 0 | ... EH16: =+PMGR!EH16+BP!EH16 -> 0 | EI16: =+SUM(DW16:EH16) -> 0 | EJ16: =CT16 -> Marketing And Process Steering | EK16: =+PMGR!EK16+BP!EK16 -> 0 | EL16: =+PMGR!EL16+BP!EL16 -> 0 | EM16: =+PMGR!EM16+BP!EM16 -> 0 | EN16: =+PMGR!EN16+BP!EN16 -> 0 | EO16: =+PMGR!EO16+BP!EO16 -> 0 | EP16: =+PMGR!EP16+BP!EP16 -> 0 | EQ16: =+PMGR!EQ16+BP!EQ16 -> 0 | ER16: =+PMGR!ER16+BP!ER16 -> 0 | ... EV16: =+PMGR!EV16+BP!EV16 -> 0 | EW16: =+SUM(EK16:EV16) -> 0 | EY16: =+PMGR!EY16+BP!EY16 -> 0 | EZ16: =+PMGR!EZ16+BP!EZ16 -> 0 | FA16: =+PMGR!FA16+BP!FA16 -> 0 | FB16: =+PMGR!FB16+BP!FB16 -> 0 | FC16: =+PMGR!FC16+BP!FC16 -> 0 | FD16: =+PMGR!FD16+BP!FD16 -> 0 | FE16: =+PMGR!FE16+BP!FE16 -> 0 | FF16: =+PMGR!FF16+BP!FF16 -> 0 | ... FJ16: =+PMGR!FJ16+BP!FJ16 -> 0 | FK16: =+SUM(EY16:FJ16) -> 0
N17: Sales Demo Car | BD17: =N17 -> Sales Demo Car | CT17: =BD17 -> Sales Demo Car | EJ17: =CT17 -> Sales Demo Car
A18: =+AQ18+CG18+DW18 -> 0 | B18: =+AR18+CH18+DX18 -> 0 | C18: =+AS18+CI18+DY18 -> 0 | D18: =+AT18+CJ18+DZ18 -> 0 | E18: =+AU18+CK18+EA18 -> 0 | F18: =+AV18+CL18+EB18 -> 0 | G18: =+AW18+CM18+EC18 -> 0 | H18: =+AX18+CN18+ED18 -> 0 | ... L18: =+BB18+CR18+EH18 -> 0 | M18: =+SUM(A18:L18) -> 0 | N18: No of Cars Sold | O18: =+BE18+CU18+EK18 -> 0 | P18: =+BF18+CV18+EL18 -> 0 | Q18: =+BG18+CW18+EM18 -> 0 | R18: =+BH18+CX18+EN18 -> 0 | S18: =+BI18+CY18+EO18 -> 0 | T18: =+BJ18+CZ18+EP18 -> 0 | U18: =+BK18+DA18+EQ18 -> 0 | V18: =+BL18+DB18+ER18 -> 0 | ... Z18: =+BP18+DF18+EV18 -> 0 | AA18: =+SUM(O18:Z18) -> 0 | AC18: =+BS18+DI18+EY18 -> 0 | AD18: =+BT18+DJ18+EZ18 -> 0 | AE18: =+BU18+DK18+FA18 -> 0 | AF18: =+BV18+DL18+FB18 -> 0 | AG18: =+BW18+DM18+FC18 -> 0 | AH18: =+BX18+DN18+FD18 -> 0 | AI18: =+BY18+DO18+FE18 -> 0 | AJ18: =+BZ18+DP18+FF18 -> 0 | ... AN18: =+CD18+DT18+FJ18 -> 0 | AO18: =+SUM(AC18:AN18) -> 0 | AQ18: =+PMGR!AQ18+BP!AQ18 -> 0 | AR18: =+PMGR!AR18+BP!AR18 -> 0 | AS18: =+PMGR!AS18+BP!AS18 -> 0 | AT18: =+PMGR!AT18+BP!AT18 -> 0 | AU18: =+PMGR!AU18+BP!AU18 -> 0 | AV18: =+PMGR!AV18+BP!AV18 -> 0 | AW18: =+PMGR!AW18+BP!AW18 -> 0 | AX18: =+PMGR!AX18+BP!AX18 -> 0 | ... BB18: =+PMGR!BB18+BP!BB18 -> 0 | BC18: =+SUM(AQ18:BB18) -> 0 | BD18: =N18 -> No of Cars Sold | BE18: =+PMGR!BE18+BP!BE18 -> 0 | BF18: =+PMGR!BF18+BP!BF18 -> 0 | BG18: =+PMGR!BG18+BP!BG18 -> 0 | BH18: =+PMGR!BH18+BP!BH18 -> 0 | BI18: =+PMGR!BI18+BP!BI18 -> 0 | BJ18: =+PMGR!BJ18+BP!BJ18 -> 0 | BK18: =+PMGR!BK18+BP!BK18 -> 0 | BL18: =+PMGR!BL18+BP!BL18 -> 0 | ... BP18: =+PMGR!BP18+BP!BP18 -> 0 | BQ18: =+SUM(BE18:BP18) -> 0 | BS18: =+PMGR!BS18+BP!BS18 -> 0 | BT18: =+PMGR!BT18+BP!BT18 -> 0 | BU18: =+PMGR!BU18+BP!BU18 -> 0 | BV18: =+PMGR!BV18+BP!BV18 -> 0 | BW18: =+PMGR!BW18+BP!BW18 -> 0 | BX18: =+PMGR!BX18+BP!BX18 -> 0 | BY18: =+PMGR!BY18+BP!BY18 -> 0 | BZ18: =+PMGR!BZ18+BP!BZ18 -> 0 | ... CD18: =+PMGR!CD18+BP!CD18 -> 0 | CE18: =+SUM(BS18:CD18) -> 0 | CG18: =+PMGR!CG18+BP!CG18 -> 0 | CH18: =+PMGR!CH18+BP!CH18 -> 0 | CI18: =+PMGR!CI18+BP!CI18 -> 0 | CJ18: =+PMGR!CJ18+BP!CJ18 -> 0 | CK18: =+PMGR!CK18+BP!CK18 -> 0 | CL18: =+PMGR!CL18+BP!CL18 -> 0 | CM18: =+PMGR!CM18+BP!CM18 -> 0 | CN18: =+PMGR!CN18+BP!CN18 -> 0 | ... CR18: =+PMGR!CR18+BP!CR18 -> 0 | CS18: =+SUM(CG18:CR18) -> 0 | CT18: =BD18 -> No of Cars Sold | CU18: =+PMGR!CU18+BP!CU18 -> 0 | CV18: =+PMGR!CV18+BP!CV18 -> 0 | CW18: =+PMGR!CW18+BP!CW18 -> 0 | CX18: =+PMGR!CX18+BP!CX18 -> 0 | CY18: =+PMGR!CY18+BP!CY18 -> 0 | CZ18: =+PMGR!CZ18+BP!CZ18 -> 0 | DA18: =+PMGR!DA18+BP!DA18 -> 0 | DB18: =+PMGR!DB18+BP!DB18 -> 0 | ... DF18: =+PMGR!DF18+BP!DF18 -> 0 | DG18: =+SUM(CU18:DF18) -> 0 | DI18: =+PMGR!DI18+BP!DI18 -> 0 | DJ18: =+PMGR!DJ18+BP!DJ18 -> 0 | DK18: =+PMGR!DK18+BP!DK18 -> 0 | DL18: =+PMGR!DL18+BP!DL18 -> 0 | DM18: =+PMGR!DM18+BP!DM18 -> 0 | DN18: =+PMGR!DN18+BP!DN18 -> 0 | DO18: =+PMGR!DO18+BP!DO18 -> 0 | DP18: =+PMGR!DP18+BP!DP18 -> 0 | ... DT18: =+PMGR!DT18+BP!DT18 -> 0 | DU18: =+SUM(DI18:DT18) -> 0 | DW18: =+PMGR!DW18+BP!DW18 -> 0 | DX18: =+PMGR!DX18+BP!DX18 -> 0 | DY18: =+PMGR!DY18+BP!DY18 -> 0 | DZ18: =+PMGR!DZ18+BP!DZ18 -> 0 | EA18: =+PMGR!EA18+BP!EA18 -> 0 | EB18: =+PMGR!EB18+BP!EB18 -> 0 | EC18: =+PMGR!EC18+BP!EC18 -> 0 | ED18: =+PMGR!ED18+BP!ED18 -> 0 | ... EH18: =+PMGR!EH18+BP!EH18 -> 0 | EI18: =+SUM(DW18:EH18) -> 0 | EJ18: =CT18 -> No of Cars Sold | EK18: =+PMGR!EK18+BP!EK18 -> 0 | EL18: =+PMGR!EL18+BP!EL18 -> 0 | EM18: =+PMGR!EM18+BP!EM18 -> 0 | EN18: =+PMGR!EN18+BP!EN18 -> 0 | EO18: =+PMGR!EO18+BP!EO18 -> 0 | EP18: =+PMGR!EP18+BP!EP18 -> 0 | EQ18: =+PMGR!EQ18+BP!EQ18 -> 0 | ER18: =+PMGR!ER18+BP!ER18 -> 0 | ... EV18: =+PMGR!EV18+BP!EV18 -> 0 | EW18: =+SUM(EK18:EV18) -> 0 | EY18: =+PMGR!EY18+BP!EY18 -> 0 | EZ18: =+PMGR!EZ18+BP!EZ18 -> 0 | FA18: =+PMGR!FA18+BP!FA18 -> 0 | FB18: =+PMGR!FB18+BP!FB18 -> 0 | FC18: =+PMGR!FC18+BP!FC18 -> 0 | FD18: =+PMGR!FD18+BP!FD18 -> 0 | FE18: =+PMGR!FE18+BP!FE18 -> 0 | FF18: =+PMGR!FF18+BP!FF18 -> 0 | ... FJ18: =+PMGR!FJ18+BP!FJ18 -> 0 | FK18: =+SUM(EY18:FJ18) -> 0
A19: =+AQ19+CG19+DW19 -> 0 | B19: =+AR19+CH19+DX19 -> 0 | C19: =+AS19+CI19+DY19 -> 0 | D19: =+AT19+CJ19+DZ19 -> 0 | E19: =+AU19+CK19+EA19 -> 0 | F19: =+AV19+CL19+EB19 -> 0 | G19: =+AW19+CM19+EC19 -> 0 | H19: =+AX19+CN19+ED19 -> 0 | ... L19: =+BB19+CR19+EH19 -> 0 | M19: =+SUM(A19:L19) -> 0 | N19: Turnover. | O19: =+BE19+CU19+EK19 -> 0 | P19: =+BF19+CV19+EL19 -> 0 | Q19: =+BG19+CW19+EM19 -> 0 | R19: =+BH19+CX19+EN19 -> 0 | S19: =+BI19+CY19+EO19 -> 0 | T19: =+BJ19+CZ19+EP19 -> 0 | U19: =+BK19+DA19+EQ19 -> 0 | V19: =+BL19+DB19+ER19 -> 0 | ... Z19: =+BP19+DF19+EV19 -> 0 | AA19: =+SUM(O19:Z19) -> 0 | AC19: =+BS19+DI19+EY19 -> 0 | AD19: =+BT19+DJ19+EZ19 -> 0 | AE19: =+BU19+DK19+FA19 -> 0 | AF19: =+BV19+DL19+FB19 -> 0 | AG19: =+BW19+DM19+FC19 -> 0 | AH19: =+BX19+DN19+FD19 -> 0 | AI19: =+BY19+DO19+FE19 -> 0 | AJ19: =+BZ19+DP19+FF19 -> 0 | ... AN19: =+CD19+DT19+FJ19 -> 0 | AO19: =+SUM(AC19:AN19) -> 0 | AQ19: =+PMGR!AQ19+BP!AQ19 -> 0 | AR19: =+PMGR!AR19+BP!AR19 -> 0 | AS19: =+PMGR!AS19+BP!AS19 -> 0 | AT19: =+PMGR!AT19+BP!AT19 -> 0 | AU19: =+PMGR!AU19+BP!AU19 -> 0 | AV19: =+PMGR!AV19+BP!AV19 -> 0 | AW19: =+PMGR!AW19+BP!AW19 -> 0 | AX19: =+PMGR!AX19+BP!AX19 -> 0 | ... BB19: =+PMGR!BB19+BP!BB19 -> 0 | BC19: =+SUM(AQ19:BB19) -> 0 | BD19: =N19 -> Turnover. | BE19: =+PMGR!BE19+BP!BE19 -> 0 | BF19: =+PMGR!BF19+BP!BF19 -> 0 | BG19: =+PMGR!BG19+BP!BG19 -> 0 | BH19: =+PMGR!BH19+BP!BH19 -> 0 | BI19: =+PMGR!BI19+BP!BI19 -> 0 | BJ19: =+PMGR!BJ19+BP!BJ19 -> 0 | BK19: =+PMGR!BK19+BP!BK19 -> 0 | BL19: =+PMGR!BL19+BP!BL19 -> 0 | ... BP19: =+PMGR!BP19+BP!BP19 -> 0 | BQ19: =+SUM(BE19:BP19) -> 0 | BS19: =+PMGR!BS19+BP!BS19 -> 0 | BT19: =+PMGR!BT19+BP!BT19 -> 0 | BU19: =+PMGR!BU19+BP!BU19 -> 0 | BV19: =+PMGR!BV19+BP!BV19 -> 0 | BW19: =+PMGR!BW19+BP!BW19 -> 0 | BX19: =+PMGR!BX19+BP!BX19 -> 0 | BY19: =+PMGR!BY19+BP!BY19 -> 0 | BZ19: =+PMGR!BZ19+BP!BZ19 -> 0 | ... CD19: =+PMGR!CD19+BP!CD19 -> 0 | CE19: =+SUM(BS19:CD19) -> 0 | CG19: =+PMGR!CG19+BP!CG19 -> 0 | CH19: =+PMGR!CH19+BP!CH19 -> 0 | CI19: =+PMGR!CI19+BP!CI19 -> 0 | CJ19: =+PMGR!CJ19+BP!CJ19 -> 0 | CK19: =+PMGR!CK19+BP!CK19 -> 0 | CL19: =+PMGR!CL19+BP!CL19 -> 0 | CM19: =+PMGR!CM19+BP!CM19 -> 0 | CN19: =+PMGR!CN19+BP!CN19 -> 0 | ... CR19: =+PMGR!CR19+BP!CR19 -> 0 | CS19: =+SUM(CG19:CR19) -> 0 | CT19: =BD19 -> Turnover. | CU19: =+PMGR!CU19+BP!CU19 -> 0 | CV19: =+PMGR!CV19+BP!CV19 -> 0 | CW19: =+PMGR!CW19+BP!CW19 -> 0 | CX19: =+PMGR!CX19+BP!CX19 -> 0 | CY19: =+PMGR!CY19+BP!CY19 -> 0 | CZ19: =+PMGR!CZ19+BP!CZ19 -> 0 | DA19: =+PMGR!DA19+BP!DA19 -> 0 | DB19: =+PMGR!DB19+BP!DB19 -> 0 | ... DF19: =+PMGR!DF19+BP!DF19 -> 0 | DG19: =+SUM(CU19:DF19) -> 0 | DI19: =+PMGR!DI19+BP!DI19 -> 0 | DJ19: =+PMGR!DJ19+BP!DJ19 -> 0 | DK19: =+PMGR!DK19+BP!DK19 -> 0 | DL19: =+PMGR!DL19+BP!DL19 -> 0 | DM19: =+PMGR!DM19+BP!DM19 -> 0 | DN19: =+PMGR!DN19+BP!DN19 -> 0 | DO19: =+PMGR!DO19+BP!DO19 -> 0 | DP19: =+PMGR!DP19+BP!DP19 -> 0 | ... DT19: =+PMGR!DT19+BP!DT19 -> 0 | DU19: =+SUM(DI19:DT19) -> 0 | DW19: =+PMGR!DW19+BP!DW19 -> 0 | DX19: =+PMGR!DX19+BP!DX19 -> 0 | DY19: =+PMGR!DY19+BP!DY19 -> 0 | DZ19: =+PMGR!DZ19+BP!DZ19 -> 0 | EA19: =+PMGR!EA19+BP!EA19 -> 0 | EB19: =+PMGR!EB19+BP!EB19 -> 0 | EC19: =+PMGR!EC19+BP!EC19 -> 0 | ED19: =+PMGR!ED19+BP!ED19 -> 0 | ... EH19: =+PMGR!EH19+BP!EH19 -> 0 | EI19: =+SUM(DW19:EH19) -> 0 | EJ19: =CT19 -> Turnover. | EK19: =+PMGR!EK19+BP!EK19 -> 0 | EL19: =+PMGR!EL19+BP!EL19 -> 0 | EM19: =+PMGR!EM19+BP!EM19 -> 0 | EN19: =+PMGR!EN19+BP!EN19 -> 0 | EO19: =+PMGR!EO19+BP!EO19 -> 0 | EP19: =+PMGR!EP19+BP!EP19 -> 0 | EQ19: =+PMGR!EQ19+BP!EQ19 -> 0 | ER19: =+PMGR!ER19+BP!ER19 -> 0 | ... EV19: =+PMGR!EV19+BP!EV19 -> 0 | EW19: =+SUM(EK19:EV19) -> 0 | EY19: =+PMGR!EY19+BP!EY19 -> 0 | EZ19: =+PMGR!EZ19+BP!EZ19 -> 0 | FA19: =+PMGR!FA19+BP!FA19 -> 0 | FB19: =+PMGR!FB19+BP!FB19 -> 0 | FC19: =+PMGR!FC19+BP!FC19 -> 0 | FD19: =+PMGR!FD19+BP!FD19 -> 0 | FE19: =+PMGR!FE19+BP!FE19 -> 0 | FF19: =+PMGR!FF19+BP!FF19 -> 0 | ... FJ19: =+PMGR!FJ19+BP!FJ19 -> 0 | FK19: =+SUM(EY19:FJ19) -> 0
A20: =+AQ20+CG20+DW20 -> 0 | B20: =+AR20+CH20+DX20 -> 0 | C20: =+AS20+CI20+DY20 -> 0 | D20: =+AT20+CJ20+DZ20 -> 0 | E20: =+AU20+CK20+EA20 -> 0 | F20: =+AV20+CL20+EB20 -> 0 | G20: =+AW20+CM20+EC20 -> 0 | H20: =+AX20+CN20+ED20 -> 0 | ... L20: =+BB20+CR20+EH20 -> 0 | M20: =+SUM(A20:L20) -> 0 | N20: Cost of goods sold - Demo Car | O20: =+BE20+CU20+EK20 -> 0 | P20: =+BF20+CV20+EL20 -> 0 | Q20: =+BG20+CW20+EM20 -> 0 | R20: =+BH20+CX20+EN20 -> 0 | S20: =+BI20+CY20+EO20 -> 0 | T20: =+BJ20+CZ20+EP20 -> 0 | U20: =+BK20+DA20+EQ20 -> 0 | V20: =+BL20+DB20+ER20 -> 0 | ... Z20: =+BP20+DF20+EV20 -> 0 | AA20: =+SUM(O20:Z20) -> 0 | AC20: =+BS20+DI20+EY20 -> 0 | AD20: =+BT20+DJ20+EZ20 -> 0 | AE20: =+BU20+DK20+FA20 -> 0 | AF20: =+BV20+DL20+FB20 -> 0 | AG20: =+BW20+DM20+FC20 -> 0 | AH20: =+BX20+DN20+FD20 -> 0 | AI20: =+BY20+DO20+FE20 -> 0 | AJ20: =+BZ20+DP20+FF20 -> 0 | ... AN20: =+CD20+DT20+FJ20 -> 0 | AO20: =+SUM(AC20:AN20) -> 0 | AQ20: =+PMGR!AQ20+BP!AQ20 -> 0 | AR20: =+PMGR!AR20+BP!AR20 -> 0 | AS20: =+PMGR!AS20+BP!AS20 -> 0 | AT20: =+PMGR!AT20+BP!AT20 -> 0 | AU20: =+PMGR!AU20+BP!AU20 -> 0 | AV20: =+PMGR!AV20+BP!AV20 -> 0 | AW20: =+PMGR!AW20+BP!AW20 -> 0 | AX20: =+PMGR!AX20+BP!AX20 -> 0 | ... BB20: =+PMGR!BB20+BP!BB20 -> 0 | BC20: =+SUM(AQ20:BB20) -> 0 | BD20: =N20 -> Cost of goods sold - Demo Car | BE20: =+PMGR!BE20+BP!BE20 -> 0 | BF20: =+PMGR!BF20+BP!BF20 -> 0 | BG20: =+PMGR!BG20+BP!BG20 -> 0 | BH20: =+PMGR!BH20+BP!BH20 -> 0 | BI20: =+PMGR!BI20+BP!BI20 -> 0 | BJ20: =+PMGR!BJ20+BP!BJ20 -> 0 | BK20: =+PMGR!BK20+BP!BK20 -> 0 | BL20: =+PMGR!BL20+BP!BL20 -> 0 | ... BP20: =+PMGR!BP20+BP!BP20 -> 0 | BQ20: =+SUM(BE20:BP20) -> 0 | BS20: =+PMGR!BS20+BP!BS20 -> 0 | BT20: =+PMGR!BT20+BP!BT20 -> 0 | BU20: =+PMGR!BU20+BP!BU20 -> 0 | BV20: =+PMGR!BV20+BP!BV20 -> 0 | BW20: =+PMGR!BW20+BP!BW20 -> 0 | BX20: =+PMGR!BX20+BP!BX20 -> 0 | BY20: =+PMGR!BY20+BP!BY20 -> 0 | BZ20: =+PMGR!BZ20+BP!BZ20 -> 0 | ... CD20: =+PMGR!CD20+BP!CD20 -> 0 | CE20: =+SUM(BS20:CD20) -> 0 | CG20: =+PMGR!CG20+BP!CG20 -> 0 | CH20: =+PMGR!CH20+BP!CH20 -> 0 | CI20: =+PMGR!CI20+BP!CI20 -> 0 | CJ20: =+PMGR!CJ20+BP!CJ20 -> 0 | CK20: =+PMGR!CK20+BP!CK20 -> 0 | CL20: =+PMGR!CL20+BP!CL20 -> 0 | CM20: =+PMGR!CM20+BP!CM20 -> 0 | CN20: =+PMGR!CN20+BP!CN20 -> 0 | ... CR20: =+PMGR!CR20+BP!CR20 -> 0 | CS20: =+SUM(CG20:CR20) -> 0 | CT20: =BD20 -> Cost of goods sold - Demo Car | CU20: =+PMGR!CU20+BP!CU20 -> 0 | CV20: =+PMGR!CV20+BP!CV20 -> 0 | CW20: =+PMGR!CW20+BP!CW20 -> 0 | CX20: =+PMGR!CX20+BP!CX20 -> 0 | CY20: =+PMGR!CY20+BP!CY20 -> 0 | CZ20: =+PMGR!CZ20+BP!CZ20 -> 0 | DA20: =+PMGR!DA20+BP!DA20 -> 0 | DB20: =+PMGR!DB20+BP!DB20 -> 0 | ... DF20: =+PMGR!DF20+BP!DF20 -> 0 | DG20: =+SUM(CU20:DF20) -> 0 | DI20: =+PMGR!DI20+BP!DI20 -> 0 | DJ20: =+PMGR!DJ20+BP!DJ20 -> 0 | DK20: =+PMGR!DK20+BP!DK20 -> 0 | DL20: =+PMGR!DL20+BP!DL20 -> 0 | DM20: =+PMGR!DM20+BP!DM20 -> 0 | DN20: =+PMGR!DN20+BP!DN20 -> 0 | DO20: =+PMGR!DO20+BP!DO20 -> 0 | DP20: =+PMGR!DP20+BP!DP20 -> 0 | ... DT20: =+PMGR!DT20+BP!DT20 -> 0 | DU20: =+SUM(DI20:DT20) -> 0 | DW20: =+PMGR!DW20+BP!DW20 -> 0 | DX20: =+PMGR!DX20+BP!DX20 -> 0 | DY20: =+PMGR!DY20+BP!DY20 -> 0 | DZ20: =+PMGR!DZ20+BP!DZ20 -> 0 | EA20: =+PMGR!EA20+BP!EA20 -> 0 | EB20: =+PMGR!EB20+BP!EB20 -> 0 | EC20: =+PMGR!EC20+BP!EC20 -> 0 | ED20: =+PMGR!ED20+BP!ED20 -> 0 | ... EH20: =+PMGR!EH20+BP!EH20 -> 0 | EI20: =+SUM(DW20:EH20) -> 0 | EJ20: =CT20 -> Cost of goods sold - Demo Car | EK20: =+PMGR!EK20+BP!EK20 -> 0 | EL20: =+PMGR!EL20+BP!EL20 -> 0 | EM20: =+PMGR!EM20+BP!EM20 -> 0 | EN20: =+PMGR!EN20+BP!EN20 -> 0 | EO20: =+PMGR!EO20+BP!EO20 -> 0 | EP20: =+PMGR!EP20+BP!EP20 -> 0 | EQ20: =+PMGR!EQ20+BP!EQ20 -> 0 | ER20: =+PMGR!ER20+BP!ER20 -> 0 | ... EV20: =+PMGR!EV20+BP!EV20 -> 0 | EW20: =+SUM(EK20:EV20) -> 0 | EY20: =+PMGR!EY20+BP!EY20 -> 0 | EZ20: =+PMGR!EZ20+BP!EZ20 -> 0 | FA20: =+PMGR!FA20+BP!FA20 -> 0 | FB20: =+PMGR!FB20+BP!FB20 -> 0 | FC20: =+PMGR!FC20+BP!FC20 -> 0 | FD20: =+PMGR!FD20+BP!FD20 -> 0 | FE20: =+PMGR!FE20+BP!FE20 -> 0 | FF20: =+PMGR!FF20+BP!FF20 -> 0 | ... FJ20: =+PMGR!FJ20+BP!FJ20 -> 0 | FK20: =+SUM(EY20:FJ20) -> 0
A21: =+AQ21+CG21+DW21 -> 0 | B21: =+AR21+CH21+DX21 -> 0 | C21: =+AS21+CI21+DY21 -> 0 | D21: =+AT21+CJ21+DZ21 -> 0 | E21: =+AU21+CK21+EA21 -> 0 | F21: =+AV21+CL21+EB21 -> 0 | G21: =+AW21+CM21+EC21 -> 0 | H21: =+AX21+CN21+ED21 -> 0 | ... L21: =+BB21+CR21+EH21 -> 0 | M21: =+SUM(A21:L21) -> 0 | N21: Trade Discount | O21: =+BE21+CU21+EK21 -> 0 | P21: =+BF21+CV21+EL21 -> 0 | Q21: =+BG21+CW21+EM21 -> 0 | R21: =+BH21+CX21+EN21 -> 0 | S21: =+BI21+CY21+EO21 -> 0 | T21: =+BJ21+CZ21+EP21 -> 0 | U21: =+BK21+DA21+EQ21 -> 0 | V21: =+BL21+DB21+ER21 -> 0 | ... Z21: =+BP21+DF21+EV21 -> 0 | AA21: =+SUM(O21:Z21) -> 0 | AC21: =+BS21+DI21+EY21 -> 0 | AD21: =+BT21+DJ21+EZ21 -> 0 | AE21: =+BU21+DK21+FA21 -> 0 | AF21: =+BV21+DL21+FB21 -> 0 | AG21: =+BW21+DM21+FC21 -> 0 | AH21: =+BX21+DN21+FD21 -> 0 | AI21: =+BY21+DO21+FE21 -> 0 | AJ21: =+BZ21+DP21+FF21 -> 0 | ... AN21: =+CD21+DT21+FJ21 -> 0 | AO21: =+SUM(AC21:AN21) -> 0 | AQ21: =+PMGR!AQ21+BP!AQ21 -> 0 | AR21: =+PMGR!AR21+BP!AR21 -> 0 | AS21: =+PMGR!AS21+BP!AS21 -> 0 | AT21: =+PMGR!AT21+BP!AT21 -> 0 | AU21: =+PMGR!AU21+BP!AU21 -> 0 | AV21: =+PMGR!AV21+BP!AV21 -> 0 | AW21: =+PMGR!AW21+BP!AW21 -> 0 | AX21: =+PMGR!AX21+BP!AX21 -> 0 | ... BB21: =+PMGR!BB21+BP!BB21 -> 0 | BC21: =+SUM(AQ21:BB21) -> 0 | BD21: =N21 -> Trade Discount | BE21: =+PMGR!BE21+BP!BE21 -> 0 | BF21: =+PMGR!BF21+BP!BF21 -> 0 | BG21: =+PMGR!BG21+BP!BG21 -> 0 | BH21: =+PMGR!BH21+BP!BH21 -> 0 | BI21: =+PMGR!BI21+BP!BI21 -> 0 | BJ21: =+PMGR!BJ21+BP!BJ21 -> 0 | BK21: =+PMGR!BK21+BP!BK21 -> 0 | BL21: =+PMGR!BL21+BP!BL21 -> 0 | ... BP21: =+PMGR!BP21+BP!BP21 -> 0 | BQ21: =+SUM(BE21:BP21) -> 0 | BS21: =+PMGR!BS21+BP!BS21 -> 0 | BT21: =+PMGR!BT21+BP!BT21 -> 0 | BU21: =+PMGR!BU21+BP!BU21 -> 0 | BV21: =+PMGR!BV21+BP!BV21 -> 0 | BW21: =+PMGR!BW21+BP!BW21 -> 0 | BX21: =+PMGR!BX21+BP!BX21 -> 0 | BY21: =+PMGR!BY21+BP!BY21 -> 0 | BZ21: =+PMGR!BZ21+BP!BZ21 -> 0 | ... CD21: =+PMGR!CD21+BP!CD21 -> 0 | CE21: =+SUM(BS21:CD21) -> 0 | CG21: =+PMGR!CG21+BP!CG21 -> 0 | CH21: =+PMGR!CH21+BP!CH21 -> 0 | CI21: =+PMGR!CI21+BP!CI21 -> 0 | CJ21: =+PMGR!CJ21+BP!CJ21 -> 0 | CK21: =+PMGR!CK21+BP!CK21 -> 0 | CL21: =+PMGR!CL21+BP!CL21 -> 0 | CM21: =+PMGR!CM21+BP!CM21 -> 0 | CN21: =+PMGR!CN21+BP!CN21 -> 0 | ... CR21: =+PMGR!CR21+BP!CR21 -> 0 | CS21: =+SUM(CG21:CR21) -> 0 | CT21: =BD21 -> Trade Discount | CU21: =+PMGR!CU21+BP!CU21 -> 0 | CV21: =+PMGR!CV21+BP!CV21 -> 0 | CW21: =+PMGR!CW21+BP!CW21 -> 0 | CX21: =+PMGR!CX21+BP!CX21 -> 0 | CY21: =+PMGR!CY21+BP!CY21 -> 0 | CZ21: =+PMGR!CZ21+BP!CZ21 -> 0 | DA21: =+PMGR!DA21+BP!DA21 -> 0 | DB21: =+PMGR!DB21+BP!DB21 -> 0 | ... DF21: =+PMGR!DF21+BP!DF21 -> 0 | DG21: =+SUM(CU21:DF21) -> 0 | DI21: =+PMGR!DI21+BP!DI21 -> 0 | DJ21: =+PMGR!DJ21+BP!DJ21 -> 0 | DK21: =+PMGR!DK21+BP!DK21 -> 0 | DL21: =+PMGR!DL21+BP!DL21 -> 0 | DM21: =+PMGR!DM21+BP!DM21 -> 0 | DN21: =+PMGR!DN21+BP!DN21 -> 0 | DO21: =+PMGR!DO21+BP!DO21 -> 0 | DP21: =+PMGR!DP21+BP!DP21 -> 0 | ... DT21: =+PMGR!DT21+BP!DT21 -> 0 | DU21: =+SUM(DI21:DT21) -> 0 | DW21: =+PMGR!DW21+BP!DW21 -> 0 | DX21: =+PMGR!DX21+BP!DX21 -> 0 | DY21: =+PMGR!DY21+BP!DY21 -> 0 | DZ21: =+PMGR!DZ21+BP!DZ21 -> 0 | EA21: =+PMGR!EA21+BP!EA21 -> 0 | EB21: =+PMGR!EB21+BP!EB21 -> 0 | EC21: =+PMGR!EC21+BP!EC21 -> 0 | ED21: =+PMGR!ED21+BP!ED21 -> 0 | ... EH21: =+PMGR!EH21+BP!EH21 -> 0 | EI21: =+SUM(DW21:EH21) -> 0 | EJ21: =CT21 -> Trade Discount | EK21: =+PMGR!EK21+BP!EK21 -> 0 | EL21: =+PMGR!EL21+BP!EL21 -> 0 | EM21: =+PMGR!EM21+BP!EM21 -> 0 | EN21: =+PMGR!EN21+BP!EN21 -> 0 | EO21: =+PMGR!EO21+BP!EO21 -> 0 | EP21: =+PMGR!EP21+BP!EP21 -> 0 | EQ21: =+PMGR!EQ21+BP!EQ21 -> 0 | ER21: =+PMGR!ER21+BP!ER21 -> 0 | ... EV21: =+PMGR!EV21+BP!EV21 -> 0 | EW21: =+SUM(EK21:EV21) -> 0 | EY21: =+PMGR!EY21+BP!EY21 -> 0 | EZ21: =+PMGR!EZ21+BP!EZ21 -> 0 | FA21: =+PMGR!FA21+BP!FA21 -> 0 | FB21: =+PMGR!FB21+BP!FB21 -> 0 | FC21: =+PMGR!FC21+BP!FC21 -> 0 | FD21: =+PMGR!FD21+BP!FD21 -> 0 | FE21: =+PMGR!FE21+BP!FE21 -> 0 | FF21: =+PMGR!FF21+BP!FF21 -> 0 | ... FJ21: =+PMGR!FJ21+BP!FJ21 -> 0 | FK21: =+SUM(EY21:FJ21) -> 0
N22: Sales Used Car | BD22: =N22 -> Sales Used Car | CT22: =BD22 -> Sales Used Car | EJ22: =CT22 -> Sales Used Car
A23: =+AQ23+CG23+DW23 -> 0 | B23: =+AR23+CH23+DX23 -> 0 | C23: =+AS23+CI23+DY23 -> 0 | D23: =+AT23+CJ23+DZ23 -> 0 | E23: =+AU23+CK23+EA23 -> 0 | F23: =+AV23+CL23+EB23 -> 0 | G23: =+AW23+CM23+EC23 -> 0 | H23: =+AX23+CN23+ED23 -> 0 | ... L23: =+BB23+CR23+EH23 -> 0 | M23: =+SUM(A23:L23) -> 0 | N23: No of Cars Sold | O23: =+BE23+CU23+EK23 -> 0 | P23: =+BF23+CV23+EL23 -> 0 | Q23: =+BG23+CW23+EM23 -> 0 | R23: =+BH23+CX23+EN23 -> 0 | S23: =+BI23+CY23+EO23 -> 0 | T23: =+BJ23+CZ23+EP23 -> 0 | U23: =+BK23+DA23+EQ23 -> 0 | V23: =+BL23+DB23+ER23 -> 0 | ... Z23: =+BP23+DF23+EV23 -> 0 | AA23: =+SUM(O23:Z23) -> 0 | AC23: =+BS23+DI23+EY23 -> 0 | AD23: =+BT23+DJ23+EZ23 -> 0 | AE23: =+BU23+DK23+FA23 -> 0 | AF23: =+BV23+DL23+FB23 -> 0 | AG23: =+BW23+DM23+FC23 -> 0 | AH23: =+BX23+DN23+FD23 -> 0 | AI23: =+BY23+DO23+FE23 -> 0 | AJ23: =+BZ23+DP23+FF23 -> 0 | ... AN23: =+CD23+DT23+FJ23 -> 0 | AO23: =+SUM(AC23:AN23) -> 0 | AQ23: =+PMGR!AQ23+BP!AQ23 -> 0 | AR23: =+PMGR!AR23+BP!AR23 -> 0 | AS23: =+PMGR!AS23+BP!AS23 -> 0 | AT23: =+PMGR!AT23+BP!AT23 -> 0 | AU23: =+PMGR!AU23+BP!AU23 -> 0 | AV23: =+PMGR!AV23+BP!AV23 -> 0 | AW23: =+PMGR!AW23+BP!AW23 -> 0 | AX23: =+PMGR!AX23+BP!AX23 -> 0 | ... BB23: =+PMGR!BB23+BP!BB23 -> 0 | BC23: =+SUM(AQ23:BB23) -> 0 | BD23: =N23 -> No of Cars Sold | BE23: =+PMGR!BE23+BP!BE23 -> 0 | BF23: =+PMGR!BF23+BP!BF23 -> 0 | BG23: =+PMGR!BG23+BP!BG23 -> 0 | BH23: =+PMGR!BH23+BP!BH23 -> 0 | BI23: =+PMGR!BI23+BP!BI23 -> 0 | BJ23: =+PMGR!BJ23+BP!BJ23 -> 0 | BK23: =+PMGR!BK23+BP!BK23 -> 0 | BL23: =+PMGR!BL23+BP!BL23 -> 0 | ... BP23: =+PMGR!BP23+BP!BP23 -> 0 | BQ23: =+SUM(BE23:BP23) -> 0 | BS23: =+PMGR!BS23+BP!BS23 -> 0 | BT23: =+PMGR!BT23+BP!BT23 -> 0 | BU23: =+PMGR!BU23+BP!BU23 -> 0 | BV23: =+PMGR!BV23+BP!BV23 -> 0 | BW23: =+PMGR!BW23+BP!BW23 -> 0 | BX23: =+PMGR!BX23+BP!BX23 -> 0 | BY23: =+PMGR!BY23+BP!BY23 -> 0 | BZ23: =+PMGR!BZ23+BP!BZ23 -> 0 | ... CD23: =+PMGR!CD23+BP!CD23 -> 0 | CE23: =+SUM(BS23:CD23) -> 0 | CG23: =+PMGR!CG23+BP!CG23 -> 0 | CH23: =+PMGR!CH23+BP!CH23 -> 0 | CI23: =+PMGR!CI23+BP!CI23 -> 0 | CJ23: =+PMGR!CJ23+BP!CJ23 -> 0 | CK23: =+PMGR!CK23+BP!CK23 -> 0 | CL23: =+PMGR!CL23+BP!CL23 -> 0 | CM23: =+PMGR!CM23+BP!CM23 -> 0 | CN23: =+PMGR!CN23+BP!CN23 -> 0 | ... CR23: =+PMGR!CR23+BP!CR23 -> 0 | CS23: =+SUM(CG23:CR23) -> 0 | CT23: =BD23 -> No of Cars Sold | CU23: =+PMGR!CU23+BP!CU23 -> 0 | CV23: =+PMGR!CV23+BP!CV23 -> 0 | CW23: =+PMGR!CW23+BP!CW23 -> 0 | CX23: =+PMGR!CX23+BP!CX23 -> 0 | CY23: =+PMGR!CY23+BP!CY23 -> 0 | CZ23: =+PMGR!CZ23+BP!CZ23 -> 0 | DA23: =+PMGR!DA23+BP!DA23 -> 0 | DB23: =+PMGR!DB23+BP!DB23 -> 0 | ... DF23: =+PMGR!DF23+BP!DF23 -> 0 | DG23: =+SUM(CU23:DF23) -> 0 | DI23: =+PMGR!DI23+BP!DI23 -> 0 | DJ23: =+PMGR!DJ23+BP!DJ23 -> 0 | DK23: =+PMGR!DK23+BP!DK23 -> 0 | DL23: =+PMGR!DL23+BP!DL23 -> 0 | DM23: =+PMGR!DM23+BP!DM23 -> 0 | DN23: =+PMGR!DN23+BP!DN23 -> 0 | DO23: =+PMGR!DO23+BP!DO23 -> 0 | DP23: =+PMGR!DP23+BP!DP23 -> 0 | ... DT23: =+PMGR!DT23+BP!DT23 -> 0 | DU23: =+SUM(DI23:DT23) -> 0 | DW23: =+PMGR!DW23+BP!DW23 -> 0 | DX23: =+PMGR!DX23+BP!DX23 -> 0 | DY23: =+PMGR!DY23+BP!DY23 -> 0 | DZ23: =+PMGR!DZ23+BP!DZ23 -> 0 | EA23: =+PMGR!EA23+BP!EA23 -> 0 | EB23: =+PMGR!EB23+BP!EB23 -> 0 | EC23: =+PMGR!EC23+BP!EC23 -> 0 | ED23: =+PMGR!ED23+BP!ED23 -> 0 | ... EH23: =+PMGR!EH23+BP!EH23 -> 0 | EI23: =+SUM(DW23:EH23) -> 0 | EJ23: =CT23 -> No of Cars Sold | EK23: =+PMGR!EK23+BP!EK23 -> 0 | EL23: =+PMGR!EL23+BP!EL23 -> 0 | EM23: =+PMGR!EM23+BP!EM23 -> 0 | EN23: =+PMGR!EN23+BP!EN23 -> 0 | EO23: =+PMGR!EO23+BP!EO23 -> 0 | EP23: =+PMGR!EP23+BP!EP23 -> 0 | EQ23: =+PMGR!EQ23+BP!EQ23 -> 0 | ER23: =+PMGR!ER23+BP!ER23 -> 0 | ... EV23: =+PMGR!EV23+BP!EV23 -> 0 | EW23: =+SUM(EK23:EV23) -> 0 | EY23: =+PMGR!EY23+BP!EY23 -> 0 | EZ23: =+PMGR!EZ23+BP!EZ23 -> 0 | FA23: =+PMGR!FA23+BP!FA23 -> 0 | FB23: =+PMGR!FB23+BP!FB23 -> 0 | FC23: =+PMGR!FC23+BP!FC23 -> 0 | FD23: =+PMGR!FD23+BP!FD23 -> 0 | FE23: =+PMGR!FE23+BP!FE23 -> 0 | FF23: =+PMGR!FF23+BP!FF23 -> 0 | ... FJ23: =+PMGR!FJ23+BP!FJ23 -> 0 | FK23: =+SUM(EY23:FJ23) -> 0
A24: =+AQ24+CG24+DW24 -> 0 | B24: =+AR24+CH24+DX24 -> 0 | C24: =+AS24+CI24+DY24 -> 0 | D24: =+AT24+CJ24+DZ24 -> 0 | E24: =+AU24+CK24+EA24 -> 0 | F24: =+AV24+CL24+EB24 -> 0 | G24: =+AW24+CM24+EC24 -> 0 | H24: =+AX24+CN24+ED24 -> 0 | ... L24: =+BB24+CR24+EH24 -> 0 | M24: =+SUM(A24:L24) -> 0 | N24: Turnover, | O24: =+BE24+CU24+EK24 -> 0 | P24: =+BF24+CV24+EL24 -> 0 | Q24: =+BG24+CW24+EM24 -> 0 | R24: =+BH24+CX24+EN24 -> 0 | S24: =+BI24+CY24+EO24 -> 0 | T24: =+BJ24+CZ24+EP24 -> 0 | U24: =+BK24+DA24+EQ24 -> 0 | V24: =+BL24+DB24+ER24 -> 0 | ... Z24: =+BP24+DF24+EV24 -> 0 | AA24: =+SUM(O24:Z24) -> 0 | AC24: =+BS24+DI24+EY24 -> 0 | AD24: =+BT24+DJ24+EZ24 -> 0 | AE24: =+BU24+DK24+FA24 -> 0 | AF24: =+BV24+DL24+FB24 -> 0 | AG24: =+BW24+DM24+FC24 -> 0 | AH24: =+BX24+DN24+FD24 -> 0 | AI24: =+BY24+DO24+FE24 -> 0 | AJ24: =+BZ24+DP24+FF24 -> 0 | ... AN24: =+CD24+DT24+FJ24 -> 0 | AO24: =+SUM(AC24:AN24) -> 0 | AQ24: =+PMGR!AQ24+BP!AQ24 -> 0 | AR24: =+PMGR!AR24+BP!AR24 -> 0 | AS24: =+PMGR!AS24+BP!AS24 -> 0 | AT24: =+PMGR!AT24+BP!AT24 -> 0 | AU24: =+PMGR!AU24+BP!AU24 -> 0 | AV24: =+PMGR!AV24+BP!AV24 -> 0 | AW24: =+PMGR!AW24+BP!AW24 -> 0 | AX24: =+PMGR!AX24+BP!AX24 -> 0 | ... BB24: =+PMGR!BB24+BP!BB24 -> 0 | BC24: =+SUM(AQ24:BB24) -> 0 | BD24: =N24 -> Turnover, | BE24: =+PMGR!BE24+BP!BE24 -> 0 | BF24: =+PMGR!BF24+BP!BF24 -> 0 | BG24: =+PMGR!BG24+BP!BG24 -> 0 | BH24: =+PMGR!BH24+BP!BH24 -> 0 | BI24: =+PMGR!BI24+BP!BI24 -> 0 | BJ24: =+PMGR!BJ24+BP!BJ24 -> 0 | BK24: =+PMGR!BK24+BP!BK24 -> 0 | BL24: =+PMGR!BL24+BP!BL24 -> 0 | ... BP24: =+PMGR!BP24+BP!BP24 -> 0 | BQ24: =+SUM(BE24:BP24) -> 0 | BS24: =+PMGR!BS24+BP!BS24 -> 0 | BT24: =+PMGR!BT24+BP!BT24 -> 0 | BU24: =+PMGR!BU24+BP!BU24 -> 0 | BV24: =+PMGR!BV24+BP!BV24 -> 0 | BW24: =+PMGR!BW24+BP!BW24 -> 0 | BX24: =+PMGR!BX24+BP!BX24 -> 0 | BY24: =+PMGR!BY24+BP!BY24 -> 0 | BZ24: =+PMGR!BZ24+BP!BZ24 -> 0 | ... CD24: =+PMGR!CD24+BP!CD24 -> 0 | CE24: =+SUM(BS24:CD24) -> 0 | CG24: =+PMGR!CG24+BP!CG24 -> 0 | CH24: =+PMGR!CH24+BP!CH24 -> 0 | CI24: =+PMGR!CI24+BP!CI24 -> 0 | CJ24: =+PMGR!CJ24+BP!CJ24 -> 0 | CK24: =+PMGR!CK24+BP!CK24 -> 0 | CL24: =+PMGR!CL24+BP!CL24 -> 0 | CM24: =+PMGR!CM24+BP!CM24 -> 0 | CN24: =+PMGR!CN24+BP!CN24 -> 0 | ... CR24: =+PMGR!CR24+BP!CR24 -> 0 | CS24: =+SUM(CG24:CR24) -> 0 | CT24: =BD24 -> Turnover, | CU24: =+PMGR!CU24+BP!CU24 -> 0 | CV24: =+PMGR!CV24+BP!CV24 -> 0 | CW24: =+PMGR!CW24+BP!CW24 -> 0 | CX24: =+PMGR!CX24+BP!CX24 -> 0 | CY24: =+PMGR!CY24+BP!CY24 -> 0 | CZ24: =+PMGR!CZ24+BP!CZ24 -> 0 | DA24: =+PMGR!DA24+BP!DA24 -> 0 | DB24: =+PMGR!DB24+BP!DB24 -> 0 | ... DF24: =+PMGR!DF24+BP!DF24 -> 0 | DG24: =+SUM(CU24:DF24) -> 0 | DI24: =+PMGR!DI24+BP!DI24 -> 0 | DJ24: =+PMGR!DJ24+BP!DJ24 -> 0 | DK24: =+PMGR!DK24+BP!DK24 -> 0 | DL24: =+PMGR!DL24+BP!DL24 -> 0 | DM24: =+PMGR!DM24+BP!DM24 -> 0 | DN24: =+PMGR!DN24+BP!DN24 -> 0 | DO24: =+PMGR!DO24+BP!DO24 -> 0 | DP24: =+PMGR!DP24+BP!DP24 -> 0 | ... DT24: =+PMGR!DT24+BP!DT24 -> 0 | DU24: =+SUM(DI24:DT24) -> 0 | DW24: =+PMGR!DW24+BP!DW24 -> 0 | DX24: =+PMGR!DX24+BP!DX24 -> 0 | DY24: =+PMGR!DY24+BP!DY24 -> 0 | DZ24: =+PMGR!DZ24+BP!DZ24 -> 0 | EA24: =+PMGR!EA24+BP!EA24 -> 0 | EB24: =+PMGR!EB24+BP!EB24 -> 0 | EC24: =+PMGR!EC24+BP!EC24 -> 0 | ED24: =+PMGR!ED24+BP!ED24 -> 0 | ... EH24: =+PMGR!EH24+BP!EH24 -> 0 | EI24: =+SUM(DW24:EH24) -> 0 | EJ24: =CT24 -> Turnover, | EK24: =+PMGR!EK24+BP!EK24 -> 0 | EL24: =+PMGR!EL24+BP!EL24 -> 0 | EM24: =+PMGR!EM24+BP!EM24 -> 0 | EN24: =+PMGR!EN24+BP!EN24 -> 0 | EO24: =+PMGR!EO24+BP!EO24 -> 0 | EP24: =+PMGR!EP24+BP!EP24 -> 0 | EQ24: =+PMGR!EQ24+BP!EQ24 -> 0 | ER24: =+PMGR!ER24+BP!ER24 -> 0 | ... EV24: =+PMGR!EV24+BP!EV24 -> 0 | EW24: =+SUM(EK24:EV24) -> 0 | EY24: =+PMGR!EY24+BP!EY24 -> 0 | EZ24: =+PMGR!EZ24+BP!EZ24 -> 0 | FA24: =+PMGR!FA24+BP!FA24 -> 0 | FB24: =+PMGR!FB24+BP!FB24 -> 0 | FC24: =+PMGR!FC24+BP!FC24 -> 0 | FD24: =+PMGR!FD24+BP!FD24 -> 0 | FE24: =+PMGR!FE24+BP!FE24 -> 0 | FF24: =+PMGR!FF24+BP!FF24 -> 0 | ... FJ24: =+PMGR!FJ24+BP!FJ24 -> 0 | FK24: =+SUM(EY24:FJ24) -> 0
A25: =+AQ25+CG25+DW25 -> 0 | B25: =+AR25+CH25+DX25 -> 0 | C25: =+AS25+CI25+DY25 -> 0 | D25: =+AT25+CJ25+DZ25 -> 0 | E25: =+AU25+CK25+EA25 -> 0 | F25: =+AV25+CL25+EB25 -> 0 | G25: =+AW25+CM25+EC25 -> 0 | H25: =+AX25+CN25+ED25 -> 0 | ... L25: =+BB25+CR25+EH25 -> 0 | M25: =+SUM(A25:L25) -> 0 | N25: Cost of goods sold - Exchange | O25: =+BE25+CU25+EK25 -> 0 | P25: =+BF25+CV25+EL25 -> 0 | Q25: =+BG25+CW25+EM25 -> 0 | R25: =+BH25+CX25+EN25 -> 0 | S25: =+BI25+CY25+EO25 -> 0 | T25: =+BJ25+CZ25+EP25 -> 0 | U25: =+BK25+DA25+EQ25 -> 0 | V25: =+BL25+DB25+ER25 -> 0 | ... Z25: =+BP25+DF25+EV25 -> 0 | AA25: =+SUM(O25:Z25) -> 0 | AC25: =+BS25+DI25+EY25 -> 0 | AD25: =+BT25+DJ25+EZ25 -> 0 | AE25: =+BU25+DK25+FA25 -> 0 | AF25: =+BV25+DL25+FB25 -> 0 | AG25: =+BW25+DM25+FC25 -> 0 | AH25: =+BX25+DN25+FD25 -> 0 | AI25: =+BY25+DO25+FE25 -> 0 | AJ25: =+BZ25+DP25+FF25 -> 0 | ... AN25: =+CD25+DT25+FJ25 -> 0 | AO25: =+SUM(AC25:AN25) -> 0 | AQ25: =+PMGR!AQ25+BP!AQ25 -> 0 | AR25: =+PMGR!AR25+BP!AR25 -> 0 | AS25: =+PMGR!AS25+BP!AS25 -> 0 | AT25: =+PMGR!AT25+BP!AT25 -> 0 | AU25: =+PMGR!AU25+BP!AU25 -> 0 | AV25: =+PMGR!AV25+BP!AV25 -> 0 | AW25: =+PMGR!AW25+BP!AW25 -> 0 | AX25: =+PMGR!AX25+BP!AX25 -> 0 | ... BB25: =+PMGR!BB25+BP!BB25 -> 0 | BC25: =+SUM(AQ25:BB25) -> 0 | BD25: =N25 -> Cost of goods sold - Exchange | BE25: =+PMGR!BE25+BP!BE25 -> 0 | BF25: =+PMGR!BF25+BP!BF25 -> 0 | BG25: =+PMGR!BG25+BP!BG25 -> 0 | BH25: =+PMGR!BH25+BP!BH25 -> 0 | BI25: =+PMGR!BI25+BP!BI25 -> 0 | BJ25: =+PMGR!BJ25+BP!BJ25 -> 0 | BK25: =+PMGR!BK25+BP!BK25 -> 0 | BL25: =+PMGR!BL25+BP!BL25 -> 0 | ... BP25: =+PMGR!BP25+BP!BP25 -> 0 | BQ25: =+SUM(BE25:BP25) -> 0 | BS25: =+PMGR!BS25+BP!BS25 -> 0 | BT25: =+PMGR!BT25+BP!BT25 -> 0 | BU25: =+PMGR!BU25+BP!BU25 -> 0 | BV25: =+PMGR!BV25+BP!BV25 -> 0 | BW25: =+PMGR!BW25+BP!BW25 -> 0 | BX25: =+PMGR!BX25+BP!BX25 -> 0 | BY25: =+PMGR!BY25+BP!BY25 -> 0 | BZ25: =+PMGR!BZ25+BP!BZ25 -> 0 | ... CD25: =+PMGR!CD25+BP!CD25 -> 0 | CE25: =+SUM(BS25:CD25) -> 0 | CG25: =+PMGR!CG25+BP!CG25 -> 0 | CH25: =+PMGR!CH25+BP!CH25 -> 0 | CI25: =+PMGR!CI25+BP!CI25 -> 0 | CJ25: =+PMGR!CJ25+BP!CJ25 -> 0 | CK25: =+PMGR!CK25+BP!CK25 -> 0 | CL25: =+PMGR!CL25+BP!CL25 -> 0 | CM25: =+PMGR!CM25+BP!CM25 -> 0 | CN25: =+PMGR!CN25+BP!CN25 -> 0 | ... CR25: =+PMGR!CR25+BP!CR25 -> 0 | CS25: =+SUM(CG25:CR25) -> 0 | CT25: =BD25 -> Cost of goods sold - Exchange | CU25: =+PMGR!CU25+BP!CU25 -> 0 | CV25: =+PMGR!CV25+BP!CV25 -> 0 | CW25: =+PMGR!CW25+BP!CW25 -> 0 | CX25: =+PMGR!CX25+BP!CX25 -> 0 | CY25: =+PMGR!CY25+BP!CY25 -> 0 | CZ25: =+PMGR!CZ25+BP!CZ25 -> 0 | DA25: =+PMGR!DA25+BP!DA25 -> 0 | DB25: =+PMGR!DB25+BP!DB25 -> 0 | ... DF25: =+PMGR!DF25+BP!DF25 -> 0 | DG25: =+SUM(CU25:DF25) -> 0 | DI25: =+PMGR!DI25+BP!DI25 -> 0 | DJ25: =+PMGR!DJ25+BP!DJ25 -> 0 | DK25: =+PMGR!DK25+BP!DK25 -> 0 | DL25: =+PMGR!DL25+BP!DL25 -> 0 | DM25: =+PMGR!DM25+BP!DM25 -> 0 | DN25: =+PMGR!DN25+BP!DN25 -> 0 | DO25: =+PMGR!DO25+BP!DO25 -> 0 | DP25: =+PMGR!DP25+BP!DP25 -> 0 | ... DT25: =+PMGR!DT25+BP!DT25 -> 0 | DU25: =+SUM(DI25:DT25) -> 0 | DW25: =+PMGR!DW25+BP!DW25 -> 0 | DX25: =+PMGR!DX25+BP!DX25 -> 0 | DY25: =+PMGR!DY25+BP!DY25 -> 0 | DZ25: =+PMGR!DZ25+BP!DZ25 -> 0 | EA25: =+PMGR!EA25+BP!EA25 -> 0 | EB25: =+PMGR!EB25+BP!EB25 -> 0 | EC25: =+PMGR!EC25+BP!EC25 -> 0 | ED25: =+PMGR!ED25+BP!ED25 -> 0 | ... EH25: =+PMGR!EH25+BP!EH25 -> 0 | EI25: =+SUM(DW25:EH25) -> 0 | EJ25: =CT25 -> Cost of goods sold - Exchange | EK25: =+PMGR!EK25+BP!EK25 -> 0 | EL25: =+PMGR!EL25+BP!EL25 -> 0 | EM25: =+PMGR!EM25+BP!EM25 -> 0 | EN25: =+PMGR!EN25+BP!EN25 -> 0 | EO25: =+PMGR!EO25+BP!EO25 -> 0 | EP25: =+PMGR!EP25+BP!EP25 -> 0 | EQ25: =+PMGR!EQ25+BP!EQ25 -> 0 | ER25: =+PMGR!ER25+BP!ER25 -> 0 | ... EV25: =+PMGR!EV25+BP!EV25 -> 0 | EW25: =+SUM(EK25:EV25) -> 0 | EY25: =+PMGR!EY25+BP!EY25 -> 0 | EZ25: =+PMGR!EZ25+BP!EZ25 -> 0 | FA25: =+PMGR!FA25+BP!FA25 -> 0 | FB25: =+PMGR!FB25+BP!FB25 -> 0 | FC25: =+PMGR!FC25+BP!FC25 -> 0 | FD25: =+PMGR!FD25+BP!FD25 -> 0 | FE25: =+PMGR!FE25+BP!FE25 -> 0 | FF25: =+PMGR!FF25+BP!FF25 -> 0 | ... FJ25: =+PMGR!FJ25+BP!FJ25 -> 0 | FK25: =+SUM(EY25:FJ25) -> 0
A26: =+AQ26+CG26+DW26 -> 0 | B26: =+AR26+CH26+DX26 -> 0 | C26: =+AS26+CI26+DY26 -> 0 | D26: =+AT26+CJ26+DZ26 -> 0 | E26: =+AU26+CK26+EA26 -> 0 | F26: =+AV26+CL26+EB26 -> 0 | G26: =+AW26+CM26+EC26 -> 0 | H26: =+AX26+CN26+ED26 -> 0 | ... L26: =+BB26+CR26+EH26 -> 0 | M26: =+SUM(A26:L26) -> 0 | N26: Refurbishment expenses | O26: =+BE26+CU26+EK26 -> 0 | P26: =+BF26+CV26+EL26 -> 0 | Q26: =+BG26+CW26+EM26 -> 0 | R26: =+BH26+CX26+EN26 -> 0 | S26: =+BI26+CY26+EO26 -> 0 | T26: =+BJ26+CZ26+EP26 -> 0 | U26: =+BK26+DA26+EQ26 -> 0 | V26: =+BL26+DB26+ER26 -> 0 | ... Z26: =+BP26+DF26+EV26 -> 0 | AA26: =+SUM(O26:Z26) -> 0 | AC26: =+BS26+DI26+EY26 -> 0 | AD26: =+BT26+DJ26+EZ26 -> 0 | AE26: =+BU26+DK26+FA26 -> 0 | AF26: =+BV26+DL26+FB26 -> 0 | AG26: =+BW26+DM26+FC26 -> 0 | AH26: =+BX26+DN26+FD26 -> 0 | AI26: =+BY26+DO26+FE26 -> 0 | AJ26: =+BZ26+DP26+FF26 -> 0 | ... AN26: =+CD26+DT26+FJ26 -> 0 | AO26: =+SUM(AC26:AN26) -> 0 | AQ26: =+PMGR!AQ26+BP!AQ26 -> 0 | AR26: =+PMGR!AR26+BP!AR26 -> 0 | AS26: =+PMGR!AS26+BP!AS26 -> 0 | AT26: =+PMGR!AT26+BP!AT26 -> 0 | AU26: =+PMGR!AU26+BP!AU26 -> 0 | AV26: =+PMGR!AV26+BP!AV26 -> 0 | AW26: =+PMGR!AW26+BP!AW26 -> 0 | AX26: =+PMGR!AX26+BP!AX26 -> 0 | ... BB26: =+PMGR!BB26+BP!BB26 -> 0 | BC26: =+SUM(AQ26:BB26) -> 0 | BD26: =N26 -> Refurbishment expenses | BE26: =+PMGR!BE26+BP!BE26 -> 0 | BF26: =+PMGR!BF26+BP!BF26 -> 0 | BG26: =+PMGR!BG26+BP!BG26 -> 0 | BH26: =+PMGR!BH26+BP!BH26 -> 0 | BI26: =+PMGR!BI26+BP!BI26 -> 0 | BJ26: =+PMGR!BJ26+BP!BJ26 -> 0 | BK26: =+PMGR!BK26+BP!BK26 -> 0 | BL26: =+PMGR!BL26+BP!BL26 -> 0 | ... BP26: =+PMGR!BP26+BP!BP26 -> 0 | BQ26: =+SUM(BE26:BP26) -> 0 | BS26: =+PMGR!BS26+BP!BS26 -> 0 | BT26: =+PMGR!BT26+BP!BT26 -> 0 | BU26: =+PMGR!BU26+BP!BU26 -> 0 | BV26: =+PMGR!BV26+BP!BV26 -> 0 | BW26: =+PMGR!BW26+BP!BW26 -> 0 | BX26: =+PMGR!BX26+BP!BX26 -> 0 | BY26: =+PMGR!BY26+BP!BY26 -> 0 | BZ26: =+PMGR!BZ26+BP!BZ26 -> 0 | ... CD26: =+PMGR!CD26+BP!CD26 -> 0 | CE26: =+SUM(BS26:CD26) -> 0 | CG26: =+PMGR!CG26+BP!CG26 -> 0 | CH26: =+PMGR!CH26+BP!CH26 -> 0 | CI26: =+PMGR!CI26+BP!CI26 -> 0 | CJ26: =+PMGR!CJ26+BP!CJ26 -> 0 | CK26: =+PMGR!CK26+BP!CK26 -> 0 | CL26: =+PMGR!CL26+BP!CL26 -> 0 | CM26: =+PMGR!CM26+BP!CM26 -> 0 | CN26: =+PMGR!CN26+BP!CN26 -> 0 | ... CR26: =+PMGR!CR26+BP!CR26 -> 0 | CS26: =+SUM(CG26:CR26) -> 0 | CT26: =BD26 -> Refurbishment expenses | CU26: =+PMGR!CU26+BP!CU26 -> 0 | CV26: =+PMGR!CV26+BP!CV26 -> 0 | CW26: =+PMGR!CW26+BP!CW26 -> 0 | CX26: =+PMGR!CX26+BP!CX26 -> 0 | CY26: =+PMGR!CY26+BP!CY26 -> 0 | CZ26: =+PMGR!CZ26+BP!CZ26 -> 0 | DA26: =+PMGR!DA26+BP!DA26 -> 0 | DB26: =+PMGR!DB26+BP!DB26 -> 0 | ... DF26: =+PMGR!DF26+BP!DF26 -> 0 | DG26: =+SUM(CU26:DF26) -> 0 | DI26: =+PMGR!DI26+BP!DI26 -> 0 | DJ26: =+PMGR!DJ26+BP!DJ26 -> 0 | DK26: =+PMGR!DK26+BP!DK26 -> 0 | DL26: =+PMGR!DL26+BP!DL26 -> 0 | DM26: =+PMGR!DM26+BP!DM26 -> 0 | DN26: =+PMGR!DN26+BP!DN26 -> 0 | DO26: =+PMGR!DO26+BP!DO26 -> 0 | DP26: =+PMGR!DP26+BP!DP26 -> 0 | ... DT26: =+PMGR!DT26+BP!DT26 -> 0 | DU26: =+SUM(DI26:DT26) -> 0 | DW26: =+PMGR!DW26+BP!DW26 -> 0 | DX26: =+PMGR!DX26+BP!DX26 -> 0 | DY26: =+PMGR!DY26+BP!DY26 -> 0 | DZ26: =+PMGR!DZ26+BP!DZ26 -> 0 | EA26: =+PMGR!EA26+BP!EA26 -> 0 | EB26: =+PMGR!EB26+BP!EB26 -> 0 | EC26: =+PMGR!EC26+BP!EC26 -> 0 | ED26: =+PMGR!ED26+BP!ED26 -> 0 | ... EH26: =+PMGR!EH26+BP!EH26 -> 0 | EI26: =+SUM(DW26:EH26) -> 0 | EJ26: =CT26 -> Refurbishment expenses | EK26: =+PMGR!EK26+BP!EK26 -> 0 | EL26: =+PMGR!EL26+BP!EL26 -> 0 | EM26: =+PMGR!EM26+BP!EM26 -> 0 | EN26: =+PMGR!EN26+BP!EN26 -> 0 | EO26: =+PMGR!EO26+BP!EO26 -> 0 | EP26: =+PMGR!EP26+BP!EP26 -> 0 | EQ26: =+PMGR!EQ26+BP!EQ26 -> 0 | ER26: =+PMGR!ER26+BP!ER26 -> 0 | ... EV26: =+PMGR!EV26+BP!EV26 -> 0 | EW26: =+SUM(EK26:EV26) -> 0 | EY26: =+PMGR!EY26+BP!EY26 -> 0 | EZ26: =+PMGR!EZ26+BP!EZ26 -> 0 | FA26: =+PMGR!FA26+BP!FA26 -> 0 | FB26: =+PMGR!FB26+BP!FB26 -> 0 | FC26: =+PMGR!FC26+BP!FC26 -> 0 | FD26: =+PMGR!FD26+BP!FD26 -> 0 | FE26: =+PMGR!FE26+BP!FE26 -> 0 | FF26: =+PMGR!FF26+BP!FF26 -> 0 | ... FJ26: =+PMGR!FJ26+BP!FJ26 -> 0 | FK26: =+SUM(EY26:FJ26) -> 0
A27: =+A24-A25-A26 -> 0 | B27: =+B24-B25-B26 -> 0 | C27: =+C24-C25-C26 -> 0 | D27: =+D24-D25-D26 -> 0 | E27: =+E24-E25-E26 -> 0 | F27: =+F24-F25-F26 -> 0 | G27: =+G24-G25-G26 -> 0 | H27: =+H24-H25-H26 -> 0 | ... M27: =+M24-M25-M26 -> 0 | N27: Gross Profit | O27: =+O24-O25-O26 -> 0 | P27: =+P24-P25-P26 -> 0 | Q27: =+Q24-Q25-Q26 -> 0 | R27: =+R24-R25-R26 -> 0 | S27: =+S24-S25-S26 -> 0 | T27: =+T24-T25-T26 -> 0 | U27: =+U24-U25-U26 -> 0 | V27: =+V24-V25-V26 -> 0 | ... AA27: =+AA24-AA25-AA26 -> 0 | AC27: =+AC24-AC25-AC26 -> 0 | AD27: =+AD24-AD25-AD26 -> 0 | AE27: =+AE24-AE25-AE26 -> 0 | AF27: =+AF24-AF25-AF26 -> 0 | AG27: =+AG24-AG25-AG26 -> 0 | AH27: =+AH24-AH25-AH26 -> 0 | AI27: =+AI24-AI25-AI26 -> 0 | AJ27: =+AJ24-AJ25-AJ26 -> 0 | ... AO27: =+AO24-AO25-AO26 -> 0 | AQ27: =+AQ24-AQ25-AQ26 -> 0 | AR27: =+AR24-AR25-AR26 -> 0 | AS27: =+AS24-AS25-AS26 -> 0 | AT27: =+AT24-AT25-AT26 -> 0 | AU27: =+AU24-AU25-AU26 -> 0 | AV27: =+AV24-AV25-AV26 -> 0 | AW27: =+AW24-AW25-AW26 -> 0 | AX27: =+AX24-AX25-AX26 -> 0 | ... BC27: =+BC24-BC25-BC26 -> 0 | BD27: =N27 -> Gross Profit | BE27: =+BE24-BE25-BE26 -> 0 | BF27: =+BF24-BF25-BF26 -> 0 | BG27: =+BG24-BG25-BG26 -> 0 | BH27: =+BH24-BH25-BH26 -> 0 | BI27: =+BI24-BI25-BI26 -> 0 | BJ27: =+BJ24-BJ25-BJ26 -> 0 | BK27: =+BK24-BK25-BK26 -> 0 | BL27: =+BL24-BL25-BL26 -> 0 | ... BQ27: =+BQ24-BQ25-BQ26 -> 0 | BS27: =+BS24-BS25-BS26 -> 0 | BT27: =+BT24-BT25-BT26 -> 0 | BU27: =+BU24-BU25-BU26 -> 0 | BV27: =+BV24-BV25-BV26 -> 0 | BW27: =+BW24-BW25-BW26 -> 0 | BX27: =+BX24-BX25-BX26 -> 0 | BY27: =+BY24-BY25-BY26 -> 0 | BZ27: =+BZ24-BZ25-BZ26 -> 0 | ... CE27: =+CE24-CE25-CE26 -> 0 | CG27: =+CG24-CG25-CG26 -> 0 | CH27: =+CH24-CH25-CH26 -> 0 | CI27: =+CI24-CI25-CI26 -> 0 | CJ27: =+CJ24-CJ25-CJ26 -> 0 | CK27: =+CK24-CK25-CK26 -> 0 | CL27: =+CL24-CL25-CL26 -> 0 | CM27: =+CM24-CM25-CM26 -> 0 | CN27: =+CN24-CN25-CN26 -> 0 | ... CS27: =+CS24-CS25-CS26 -> 0 | CT27: =BD27 -> Gross Profit | CU27: =+CU24-CU25-CU26 -> 0 | CV27: =+CV24-CV25-CV26 -> 0 | CW27: =+CW24-CW25-CW26 -> 0 | CX27: =+CX24-CX25-CX26 -> 0 | CY27: =+CY24-CY25-CY26 -> 0 | CZ27: =+CZ24-CZ25-CZ26 -> 0 | DA27: =+DA24-DA25-DA26 -> 0 | DB27: =+DB24-DB25-DB26 -> 0 | ... DG27: =+DG24-DG25-DG26 -> 0 | DI27: =+DI24-DI25-DI26 -> 0 | DJ27: =+DJ24-DJ25-DJ26 -> 0 | DK27: =+DK24-DK25-DK26 -> 0 | DL27: =+DL24-DL25-DL26 -> 0 | DM27: =+DM24-DM25-DM26 -> 0 | DN27: =+DN24-DN25-DN26 -> 0 | DO27: =+DO24-DO25-DO26 -> 0 | DP27: =+DP24-DP25-DP26 -> 0 | ... DU27: =+DU24-DU25-DU26 -> 0 | DW27: =+DW24-DW25-DW26 -> 0 | DX27: =+DX24-DX25-DX26 -> 0 | DY27: =+DY24-DY25-DY26 -> 0 | DZ27: =+DZ24-DZ25-DZ26 -> 0 | EA27: =+EA24-EA25-EA26 -> 0 | EB27: =+EB24-EB25-EB26 -> 0 | EC27: =+EC24-EC25-EC26 -> 0 | ED27: =+ED24-ED25-ED26 -> 0 | ... EI27: =+EI24-EI25-EI26 -> 0 | EJ27: =CT27 -> Gross Profit | EK27: =+EK24-EK25-EK26 -> 0 | EL27: =+EL24-EL25-EL26 -> 0 | EM27: =+EM24-EM25-EM26 -> 0 | EN27: =+EN24-EN25-EN26 -> 0 | EO27: =+EO24-EO25-EO26 -> 0 | EP27: =+EP24-EP25-EP26 -> 0 | EQ27: =+EQ24-EQ25-EQ26 -> 0 | ER27: =+ER24-ER25-ER26 -> 0 | ... EW27: =+EW24-EW25-EW26 -> 0 | EY27: =+EY24-EY25-EY26 -> 0 | EZ27: =+EZ24-EZ25-EZ26 -> 0 | FA27: =+FA24-FA25-FA26 -> 0 | FB27: =+FB24-FB25-FB26 -> 0 | FC27: =+FC24-FC25-FC26 -> 0 | FD27: =+FD24-FD25-FD26 -> 0 | FE27: =+FE24-FE25-FE26 -> 0 | FF27: =+FF24-FF25-FF26 -> 0 | ... FK27: =+FK24-FK25-FK26 -> 0
BD28: =N28 -> 0 | CT28: =BD28 -> 0 | EJ28: =CT28 -> 0
A29: =+SUM(A31:A37) -> 32712449 | B29: =+SUM(B31:B37) -> 41690514 | C29: =+SUM(C31:C37) -> 30097326 | D29: =+SUM(D31:D37) -> 27036522 | E29: =+SUM(E31:E37) -> 30530528 | F29: =+SUM(F31:F37) -> 34507886 | G29: =+SUM(G31:G37) -> 34186451 | H29: =+SUM(H31:H37) -> 39880082 | ... M29: =+SUM(M31:M37) -> 4.2617904e+08 | N29: Service | O29: =+SUM(O31:O37) -> 33689541 | P29: =+SUM(P31:P37) -> 30209173 | Q29: =+SUM(Q31:Q37) -> 45373709 | R29: =+SUM(R31:R37) -> 37420970 | S29: =+SUM(S31:S37) -> 50647749 | T29: =+SUM(T31:T37) -> 37247192 | U29: =+SUM(U31:U37) -> 45528757 | V29: =+SUM(V31:V37) -> 45087700 | ... AA29: =+SUM(AA31:AA37) -> 4.0975452e+08 | AC29: =+SUM(AC31:AC37) -> 44168918 | AD29: =+SUM(AD31:AD37) -> 43170397 | AE29: =+SUM(AE31:AE37) -> 43875552 | AF29: =+SUM(AF31:AF37) -> 37255657 | AG29: =+SUM(AG31:AG37) -> 42632013 | AH29: =+SUM(AH31:AH37) -> 44599368 | AI29: =+SUM(AI31:AI37) -> 46299928 | AJ29: =+SUM(AJ31:AJ37) -> 47435270 | ... AO29: =+SUM(AO31:AO37) -> 5.1903737e+08 | AQ29: =+SUM(AQ31:AQ37) -> 18341376 | AR29: =+SUM(AR31:AR37) -> 26419966 | AS29: =+SUM(AS31:AS37) -> 19142831 | AT29: =+SUM(AT31:AT37) -> 19360737 | AU29: =+SUM(AU31:AU37) -> 14722600 | AV29: =+SUM(AV31:AV37) -> 19319600 | AW29: =+SUM(AW31:AW37) -> 21705118 | AX29: =+SUM(AX31:AX37) -> 26035904 | ... BC29: =+SUM(BC31:BC37) -> 2.6618298e+08 | BD29: =N29 -> Service | BE29: =+SUM(BE31:BE37) -> 19119343 | BF29: =+SUM(BF31:BF37) -> 17560892 | BG29: =+SUM(BG31:BG37) -> 29947615 | BH29: =+SUM(BH31:BH37) -> 25660411 | BI29: =+SUM(BI31:BI37) -> 32618196 | BJ29: =+SUM(BJ31:BJ37) -> 21514408 | BK29: =+SUM(BK31:BK37) -> 27545435 | BL29: =+SUM(BL31:BL37) -> 26420259 | ... BQ29: =+SUM(BQ31:BQ37) -> 2.5161432e+08 | BS29: =+SUM(BS31:BS37) -> 23670492 | BT29: =+SUM(BT31:BT37) -> 23112944 | BU29: =+SUM(BU31:BU37) -> 21440298 | BV29: =+SUM(BV31:BV37) -> 20068696 | BW29: =+SUM(BW31:BW37) -> 22142515 | BX29: =+SUM(BX31:BX37) -> 22933406 | BY29: =+SUM(BY31:BY37) -> 23484510 | BZ29: =+SUM(BZ31:BZ37) -> 24512139 | ... CE29: =+SUM(CE31:CE37) -> 2.7237852e+08 | CG29: =+SUM(CG31:CG37) -> 14371074 | CH29: =+SUM(CH31:CH37) -> 15270547 | CI29: =+SUM(CI31:CI37) -> 10954495 | CJ29: =+SUM(CJ31:CJ37) -> 7675785.2 | CK29: =+SUM(CK31:CK37) -> 15807927 | CL29: =+SUM(CL31:CL37) -> 15188286 | CM29: =+SUM(CM31:CM37) -> 12481333 | CN29: =+SUM(CN31:CN37) -> 13844178 | ... CS29: =+SUM(CS31:CS37) -> 1.5999606e+08 | CT29: =BD29 -> Service | CU29: =+SUM(CU31:CU37) -> 11984106 | CV29: =+SUM(CV31:CV37) -> 8548458.8 | CW29: =+SUM(CW31:CW37) -> 12392486 | CX29: =+SUM(CX31:CX37) -> 9431339.9 | CY29: =+SUM(CY31:CY37) -> 14296493 | CZ29: =+SUM(CZ31:CZ37) -> 10170736 | DA29: =+SUM(DA31:DA37) -> 13586205 | DB29: =+SUM(DB31:DB37) -> 13373026 | ... DG29: =+SUM(DG31:DG37) -> 1.1816689e+08 | DI29: =+SUM(DI31:DI37) -> 15156870 | DJ29: =+SUM(DJ31:DJ37) -> 15072001 | DK29: =+SUM(DK31:DK37) -> 16871133 | DL29: =+SUM(DL31:DL37) -> 12201509 | DM29: =+SUM(DM31:DM37) -> 14554436 | DN29: =+SUM(DN31:DN37) -> 15730900 | DO29: =+SUM(DO31:DO37) -> 16138473 | DP29: =+SUM(DP31:DP37) -> 16493480 | ... DU29: =+SUM(DU31:DU37) -> 1.8115386e+08 | DW29: =+SUM(DW31:DW37) -> 0 | DX29: =+SUM(DX31:DX37) -> 0 | DY29: =+SUM(DY31:DY37) -> 0 | DZ29: =+SUM(DZ31:DZ37) -> 0 | EA29: =+SUM(EA31:EA37) -> 0 | EB29: =+SUM(EB31:EB37) -> 0 | EC29: =+SUM(EC31:EC37) -> 0 | ED29: =+SUM(ED31:ED37) -> 0 | ... EI29: =+SUM(EI31:EI37) -> 0 | EJ29: =CT29 -> Service | EK29: =+SUM(EK31:EK37) -> 2586092 | EL29: =+SUM(EL31:EL37) -> 4099822.4 | EM29: =+SUM(EM31:EM37) -> 3033607.5 | EN29: =+SUM(EN31:EN37) -> 2329219.2 | EO29: =+SUM(EO31:EO37) -> 3733059.6 | EP29: =+SUM(EP31:EP37) -> 5562047.8 | EQ29: =+SUM(EQ31:EQ37) -> 4397116.2 | ER29: =+SUM(ER31:ER37) -> 5294415.6 | ... EW29: =+SUM(EW31:EW37) -> 39973313 | EY29: =+SUM(EY31:EY37) -> 5341555.8 | EZ29: =+SUM(EZ31:EZ37) -> 4985452.1 | FA29: =+SUM(FA31:FA37) -> 5564120.6 | FB29: =+SUM(FB31:FB37) -> 4985452.1 | FC29: =+SUM(FC31:FC37) -> 5935062 | FD29: =+SUM(FD31:FD37) -> 5935062 | FE29: =+SUM(FE31:FE37) -> 6676944.8 | FF29: =+SUM(FF31:FF37) -> 6429650.5 | ... FK29: =+SUM(FK31:FK37) -> 65504988
A30: =+AQ30+CG30+DW30 -> 525 | B30: =+AR30+CH30+DX30 -> 493 | C30: =+AS30+CI30+DY30 -> 453 | D30: =+AT30+CJ30+DZ30 -> 466 | E30: =+AU30+CK30+EA30 -> 590 | F30: =+AV30+CL30+EB30 -> 501 | G30: =+AW30+CM30+EC30 -> 639 | H30: =+AX30+CN30+ED30 -> 668 | ... L30: =+BB30+CR30+EH30 -> 757 | M30: =+SUM(A30:L30) -> 6926 | N30: Throughputs | O30: =+BE30+CU30+EK30 -> 997 | P30: =+BF30+CV30+EL30 -> 767 | Q30: =+BG30+CW30+EM30 -> 819 | R30: =+BH30+CX30+EN30 -> 723 | S30: =+BI30+CY30+EO30 -> 894 | T30: =+BJ30+CZ30+EP30 -> 692 | U30: =+BK30+DA30+EQ30 -> 1034 | V30: =+BL30+DB30+ER30 -> 719 | ... Z30: =+BP30+DF30+EV30 -> 0 | AA30: =+SUM(O30:Z30) -> 7978 | AC30: =+BS30+DI30+EY30 -> 940.78115 | AD30: =+BT30+DJ30+EZ30 -> 932.74306 | AE30: =+BU30+DK30+FA30 -> 986.0817 | AF30: =+BV30+DL30+FB30 -> 801.13718 | AG30: =+BW30+DM30+FC30 -> 915.21572 | AH30: =+BX30+DN30+FD30 -> 974.0284 | AI30: =+BY30+DO30+FE30 -> 999.48703 | AJ30: =+BZ30+DP30+FF30 -> 1058.4305 | ... AN30: =+CD30+DT30+FJ30 -> 1014.196 | AO30: =+SUM(AC30:AN30) -> 11471.225 | AQ30: =+PMGR!AQ30+BP!AQ30 -> 506 | AR30: =+PMGR!AR30+BP!AR30 -> 465 | AS30: =+PMGR!AS30+BP!AS30 -> 434 | AT30: =+PMGR!AT30+BP!AT30 -> 444 | AU30: =+PMGR!AU30+BP!AU30 -> 555 | AV30: =+PMGR!AV30+BP!AV30 -> 479 | AW30: =+PMGR!AW30+BP!AW30 -> 613 | AX30: =+PMGR!AX30+BP!AX30 -> 634 | ... BB30: =+PMGR!BB30+BP!BB30 -> 734 | BC30: =+SUM(AQ30:BB30) -> 6607 | BD30: =N30 -> Throughputs | BE30: =+PMGR!BE30+BP!BE30 -> 457 | BF30: =+PMGR!BF30+BP!BF30 -> 429 | BG30: =+PMGR!BG30+BP!BG30 -> 435 | BH30: =+PMGR!BH30+BP!BH30 -> 399 | BI30: =+PMGR!BI30+BP!BI30 -> 500 | BJ30: =+PMGR!BJ30+BP!BJ30 -> 335 | BK30: =+PMGR!BK30+BP!BK30 -> 592 | BL30: =+PMGR!BL30+BP!BL30 -> 385 | ... BP30: =+PMGR!BP30+BP!BP30 -> 0 | BQ30: =+SUM(BE30:BP30) -> 4286 | BS30: =+PMGR!BS30+BP!BS30 -> 496.78115 | BT30: =+PMGR!BT30+BP!BT30 -> 496.91906 | BU30: =+PMGR!BU30+BP!BU30 -> 496.33279 | BV30: =+PMGR!BV30+BP!BV30 -> 402.40418 | BW30: =+PMGR!BW30+BP!BW30 -> 471.37192 | BX30: =+PMGR!BX30+BP!BX30 -> 501.5172 | BY30: =+PMGR!BY30+BP!BY30 -> 503.30048 | BZ30: =+PMGR!BZ30+BP!BZ30 -> 554.39707 | ... CD30: =+PMGR!CD30+BP!CD30 -> 508.73088 | CE30: =+SUM(BS30:CD30) -> 5883.1693 | CG30: =+PMGR!CG30+BP!CG30 -> 19 | CH30: =+PMGR!CH30+BP!CH30 -> 28 | CI30: =+PMGR!CI30+BP!CI30 -> 19 | CJ30: =+PMGR!CJ30+BP!CJ30 -> 22 | CK30: =+PMGR!CK30+BP!CK30 -> 35 | CL30: =+PMGR!CL30+BP!CL30 -> 22 | CM30: =+PMGR!CM30+BP!CM30 -> 26 | CN30: =+PMGR!CN30+BP!CN30 -> 34 | ... CR30: =+PMGR!CR30+BP!CR30 -> 23 | CS30: =+SUM(CG30:CR30) -> 319 | CT30: =BD30 -> Throughputs | CU30: =+PMGR!CU30+BP!CU30 -> 454 | CV30: =+PMGR!CV30+BP!CV30 -> 244 | CW30: =+PMGR!CW30+BP!CW30 -> 293 | CX30: =+PMGR!CX30+BP!CX30 -> 240 | CY30: =+PMGR!CY30+BP!CY30 -> 286 | CZ30: =+PMGR!CZ30+BP!CZ30 -> 253 | DA30: =+PMGR!DA30+BP!DA30 -> 336 | DB30: =+PMGR!DB30+BP!DB30 -> 247 | ... DF30: =+PMGR!DF30+BP!DF30 -> 0 | DG30: =+SUM(CU30:DF30) -> 2779 | DI30: =+PMGR!DI30+BP!DI30 -> 320 | DJ30: =+PMGR!DJ30+BP!DJ30 -> 320 | DK30: =+PMGR!DK30+BP!DK30 -> 359.87391 | DL30: =+PMGR!DL30+BP!DL30 -> 255.909 | DM30: =+PMGR!DM30+BP!DM30 -> 308.2438 | DN30: =+PMGR!DN30+BP!DN30 -> 334.9112 | DO30: =+PMGR!DO30+BP!DO30 -> 341.13655 | DP30: =+PMGR!DP30+BP!DP30 -> 354.13345 | ... DT30: =+PMGR!DT30+BP!DT30 -> 325.78508 | DU30: =+SUM(DI30:DT30) -> 3847.2269 | DW30: =+PMGR!DW30+BP!DW30 -> 0 | DX30: =+PMGR!DX30+BP!DX30 -> 0 | DY30: =+PMGR!DY30+BP!DY30 -> 0 | DZ30: =+PMGR!DZ30+BP!DZ30 -> 0 | EA30: =+PMGR!EA30+BP!EA30 -> 0 | EB30: =+PMGR!EB30+BP!EB30 -> 0 | EC30: =+PMGR!EC30+BP!EC30 -> 0 | ED30: =+PMGR!ED30+BP!ED30 -> 0 | ... EH30: =+PMGR!EH30+BP!EH30 -> 0 | EI30: =+SUM(DW30:EH30) -> 0 | EJ30: =CT30 -> Throughputs | EK30: =+PMGR!EK30+BP!EK30 -> 86 | EL30: =+PMGR!EL30+BP!EL30 -> 94 | EM30: =+PMGR!EM30+BP!EM30 -> 91 | EN30: =+PMGR!EN30+BP!EN30 -> 84 | EO30: =+PMGR!EO30+BP!EO30 -> 108 | EP30: =+PMGR!EP30+BP!EP30 -> 104 | EQ30: =+PMGR!EQ30+BP!EQ30 -> 106 | ER30: =+PMGR!ER30+BP!ER30 -> 87 | ... EV30: =+PMGR!EV30+BP!EV30 -> 0 | EW30: =+SUM(EK30:EV30) -> 913 | EY30: =+PMGR!EY30+BP!EY30 -> 124 | EZ30: =+PMGR!EZ30+BP!EZ30 -> 115.824 | FA30: =+PMGR!FA30+BP!FA30 -> 129.875 | FB30: =+PMGR!FB30+BP!FB30 -> 142.824 | FC30: =+PMGR!FC30+BP!FC30 -> 135.6 | FD30: =+PMGR!FD30+BP!FD30 -> 137.6 | FE30: =+PMGR!FE30+BP!FE30 -> 155.05 | FF30: =+PMGR!FF30+BP!FF30 -> 149.9 | ... FJ30: =+PMGR!FJ30+BP!FJ30 -> 179.68 | FK30: =+SUM(EY30:FJ30) -> 1740.829
A31: =+AQ31+CG31+DW31 -> 21038050 | B31: =+AR31+CH31+DX31 -> 27967305 | C31: =+AS31+CI31+DY31 -> 17711562 | D31: =+AT31+CJ31+DZ31 -> 16734424 | E31: =+AU31+CK31+EA31 -> 19707195 | F31: =+AV31+CL31+EB31 -> 21145089 | G31: =+AW31+CM31+EC31 -> 21503979 | H31: =+AX31+CN31+ED31 -> 26950573 | ... L31: =+BB31+CR31+EH31 -> 26631355 | M31: =+SUM(A31:L31) -> 2.6754463e+08 | N31: Parts Revenue | O31: =+BE31+CU31+EK31 -> 19791647 | P31: =+BF31+CV31+EL31 -> 17943373 | Q31: =+BG31+CW31+EM31 -> 24255737 | R31: =+BH31+CX31+EN31 -> 21266704 | S31: =+BI31+CY31+EO31 -> 28782983 | T31: =+BJ31+CZ31+EP31 -> 23215059 | U31: =+BK31+DA31+EQ31 -> 28958177 | V31: =+BL31+DB31+ER31 -> 28842793 | ... Z31: =+BP31+DF31+EV31 -> 0 | AA31: =+SUM(O31:Z31) -> 2.4499753e+08 | AC31: =+BS31+DI31+EY31 -> 31475162 | AD31: =+BT31+DJ31+EZ31 -> 30755438 | AE31: =+BU31+DK31+FA31 -> 31251380 | AF31: =+BV31+DL31+FB31 -> 26576261 | AG31: =+BW31+DM31+FC31 -> 30432412 | AH31: =+BX31+DN31+FD31 -> 31816472 | AI31: =+BY31+DO31+FE31 -> 33050040 | AJ31: =+BZ31+DP31+FF31 -> 33884800 | ... AN31: =+CD31+DT31+FJ31 -> 31309902 | AO31: =+SUM(AC31:AN31) -> 3.6977923e+08 | AQ31: =+PMGR!AQ31+BP!AQ31 -> 11330189 | AR31: =+PMGR!AR31+BP!AR31 -> 18552474 | AS31: =+PMGR!AS31+BP!AS31 -> 10924470 | AT31: =+PMGR!AT31+BP!AT31 -> 12368520 | AU31: =+PMGR!AU31+BP!AU31 -> 8979975.5 | AV31: =+PMGR!AV31+BP!AV31 -> 12849069 | AW31: =+PMGR!AW31+BP!AW31 -> 13646605 | AX31: =+PMGR!AX31+BP!AX31 -> 17620947 | ... BB31: =+PMGR!BB31+BP!BB31 -> 17264190 | BC31: =+SUM(AQ31:BB31) -> 1.6345376e+08 | BD31: =N31 -> Parts Revenue | BE31: =+PMGR!BE31+BP!BE31 -> 11227308 | BF31: =+PMGR!BF31+BP!BF31 -> 8888250.2 | BG31: =+PMGR!BG31+BP!BG31 -> 13478074 | BH31: =+PMGR!BH31+BP!BH31 -> 14616580 | BI31: =+PMGR!BI31+BP!BI31 -> 18028660 | BJ31: =+PMGR!BJ31+BP!BJ31 -> 13066496 | BK31: =+PMGR!BK31+BP!BK31 -> 16956250 | BL31: =+PMGR!BL31+BP!BL31 -> 16142394 | ... BP31: =+PMGR!BP31+BP!BP31 -> 0 | BQ31: =+SUM(BE31:BP31) -> 1.4254862e+08 | BS31: =+PMGR!BS31+BP!BS31 -> 16819787 | BT31: =+PMGR!BT31+BP!BT31 -> 16410411 | BU31: =+PMGR!BU31+BP!BU31 -> 15182284 | BV31: =+PMGR!BV31+BP!BV31 -> 14281289 | BW31: =+PMGR!BW31+BP!BW31 -> 15726472 | BX31: =+PMGR!BX31+BP!BX31 -> 16272727 | BY31: =+PMGR!BY31+BP!BY31 -> 16675235 | BZ31: =+PMGR!BZ31+BP!BZ31 -> 17372427 | ... CD31: =+PMGR!CD31+BP!CD31 -> 17091158 | CE31: =+SUM(BS31:CD31) -> 1.9335477e+08 | CG31: =+PMGR!CG31+BP!CG31 -> 9707860.9 | CH31: =+PMGR!CH31+BP!CH31 -> 9414830.5 | CI31: =+PMGR!CI31+BP!CI31 -> 6787092 | CJ31: =+PMGR!CJ31+BP!CJ31 -> 4365903.9 | CK31: =+PMGR!CK31+BP!CK31 -> 10727220 | CL31: =+PMGR!CL31+BP!CL31 -> 8296020.7 | CM31: =+PMGR!CM31+BP!CM31 -> 7857374.1 | CN31: =+PMGR!CN31+BP!CN31 -> 9329625.8 | ... CR31: =+PMGR!CR31+BP!CR31 -> 9367165.7 | CS31: =+SUM(CG31:CR31) -> 1.0409087e+08 | CT31: =BD31 -> Parts Revenue | CU31: =+PMGR!CU31+BP!CU31 -> 6979476.6 | CV31: =+PMGR!CV31+BP!CV31 -> 5912109 | CW31: =+PMGR!CW31+BP!CW31 -> 8784681.7 | CX31: =+PMGR!CX31+BP!CX31 -> 5639542.9 | CY31: =+PMGR!CY31+BP!CY31 -> 8294231.7 | CZ31: =+PMGR!CZ31+BP!CZ31 -> 6072540.4 | DA31: =+PMGR!DA31+BP!DA31 -> 8900010.4 | DB31: =+PMGR!DB31+BP!DB31 -> 9178956 | ... DF31: =+PMGR!DF31+BP!DF31 -> 0 | DG31: =+SUM(CU31:DF31) -> 75716370 | DI31: =+PMGR!DI31+BP!DI31 -> 10518975 | DJ31: =+PMGR!DJ31+BP!DJ31 -> 10484386 | DK31: =+PMGR!DK31+BP!DK31 -> 11760346 | DL31: =+PMGR!DL31+BP!DL31 -> 8434331.6 | DM31: =+PMGR!DM31+BP!DM31 -> 10109940 | DN31: =+PMGR!DN31+BP!DN31 -> 10947745 | DO31: =+PMGR!DO31+BP!DO31 -> 11204306 | DP31: =+PMGR!DP31+BP!DP31 -> 11533373 | ... DT31: =+PMGR!DT31+BP!DT31 -> 10699781 | DU31: =+SUM(DI31:DT31) -> 126014260 | DW31: =+PMGR!DW31+BP!DW31 -> 0 | DX31: =+PMGR!DX31+BP!DX31 -> 0 | DY31: =+PMGR!DY31+BP!DY31 -> 0 | DZ31: =+PMGR!DZ31+BP!DZ31 -> 0 | EA31: =+PMGR!EA31+BP!EA31 -> 0 | EB31: =+PMGR!EB31+BP!EB31 -> 0 | EC31: =+PMGR!EC31+BP!EC31 -> 0 | ED31: =+PMGR!ED31+BP!ED31 -> 0 | ... EH31: =+PMGR!EH31+BP!EH31 -> 0 | EI31: =+SUM(DW31:EH31) -> 0 | EJ31: =CT31 -> Parts Revenue | EK31: =+PMGR!EK31+BP!EK31 -> 1584862.4 | EL31: =+PMGR!EL31+BP!EL31 -> 3143013.9 | EM31: =+PMGR!EM31+BP!EM31 -> 1992981.2 | EN31: =+PMGR!EN31+BP!EN31 -> 1010581 | EO31: =+PMGR!EO31+BP!EO31 -> 2460090.8 | EP31: =+PMGR!EP31+BP!EP31 -> 4076023 | EQ31: =+PMGR!EQ31+BP!EQ31 -> 3101916.8 | ER31: =+PMGR!ER31+BP!ER31 -> 3521443.5 | ... EV31: =+PMGR!EV31+BP!EV31 -> 0 | EW31: =+SUM(EK31:EV31) -> 26732539 | EY31: =+PMGR!EY31+BP!EY31 -> 4136400 | EZ31: =+PMGR!EZ31+BP!EZ31 -> 3860640 | FA31: =+PMGR!FA31+BP!FA31 -> 4308750 | FB31: =+PMGR!FB31+BP!FB31 -> 3860640 | FC31: =+PMGR!FC31+BP!FC31 -> 4596000 | FD31: =+PMGR!FD31+BP!FD31 -> 4596000 | FE31: =+PMGR!FE31+BP!FE31 -> 5170500 | FF31: =+PMGR!FF31+BP!FF31 -> 4979000 | ... FJ31: =+PMGR!FJ31+BP!FJ31 -> 3518963.2 | FK31: =+SUM(EY31:FJ31) -> 50410205
A32: =+AQ32+CG32+DW32 -> 6533384 | B32: =+AR32+CH32+DX32 -> 6877912.6 | C32: =+AS32+CI32+DY32 -> 4644464.5 | D32: =+AT32+CJ32+DZ32 -> 5397449.6 | E32: =+AU32+CK32+EA32 -> 5664848.6 | F32: =+AV32+CL32+EB32 -> 5466635.4 | G32: =+AW32+CM32+EC32 -> 6570390.2 | H32: =+AX32+CN32+ED32 -> 6511380.4 | ... L32: =+BB32+CR32+EH32 -> 6757257 | M32: =+SUM(A32:L32) -> 73181676 | N32: Labour Revenue | O32: =+BE32+CU32+EK32 -> 6742748.2 | P32: =+BF32+CV32+EL32 -> 5467131.8 | Q32: =+BG32+CW32+EM32 -> 6925399.1 | R32: =+BH32+CX32+EN32 -> 5828733.7 | S32: =+BI32+CY32+EO32 -> 8672548.4 | T32: =+BJ32+CZ32+EP32 -> 6976122.3 | U32: =+BK32+DA32+EQ32 -> 8705674.4 | V32: =+BL32+DB32+ER32 -> 8324101.7 | ... Z32: =+BP32+DF32+EV32 -> 0 | AA32: =+SUM(O32:Z32) -> 73116323 | AC32: =+BS32+DI32+EY32 -> 9441936.8 | AD32: =+BT32+DJ32+EZ32 -> 9236846.7 | AE32: =+BU32+DK32+FA32 -> 9425724.9 | AF32: =+BV32+DL32+FB32 -> 7952653.3 | AG32: =+BW32+DM32+FC32 -> 9130180.8 | AH32: =+BX32+DN32+FD32 -> 9560766.8 | AI32: =+BY32+DO32+FE32 -> 9921564.2 | AJ32: =+BZ32+DP32+FF32 -> 10189446 | ... AN32: =+CD32+DT32+FJ32 -> 9546131.4 | AO32: =+SUM(AC32:AN32) -> 1.1147019e+08 | AQ32: =+PMGR!AQ32+BP!AQ32 -> 3920902.4 | AR32: =+PMGR!AR32+BP!AR32 -> 4293005.4 | AS32: =+PMGR!AS32+BP!AS32 -> 2636039.7 | AT32: =+PMGR!AT32+BP!AT32 -> 3710824.4 | AU32: =+PMGR!AU32+BP!AU32 -> 2687682.7 | AV32: =+PMGR!AV32+BP!AV32 -> 2949083.4 | AW32: =+PMGR!AW32+BP!AW32 -> 3925919.3 | AX32: =+PMGR!AX32+BP!AX32 -> 3757423.6 | ... BB32: =+PMGR!BB32+BP!BB32 -> 4210696.9 | BC32: =+SUM(AQ32:BB32) -> 43309180 | BD32: =N32 -> Labour Revenue | BE32: =+PMGR!BE32+BP!BE32 -> 3603435.4 | BF32: =+PMGR!BF32+BP!BF32 -> 3109730.6 | BG32: =+PMGR!BG32+BP!BG32 -> 3999000.2 | BH32: =+PMGR!BH32+BP!BH32 -> 3675527.1 | BI32: =+PMGR!BI32+BP!BI32 -> 5201298.9 | BJ32: =+PMGR!BJ32+BP!BJ32 -> 3783780.6 | BK32: =+PMGR!BK32+BP!BK32 -> 5225356.2 | BL32: =+PMGR!BL32+BP!BL32 -> 4340422.5 | ... BP32: =+PMGR!BP32+BP!BP32 -> 0 | BQ32: =+SUM(BE32:BP32) -> 41402685 | BS32: =+PMGR!BS32+BP!BS32 -> 5021842.4 | BT32: =+PMGR!BT32+BP!BT32 -> 4913464.9 | BU32: =+PMGR!BU32+BP!BU32 -> 4588332.1 | BV32: =+PMGR!BV32+BP!BV32 -> 4242024 | BW32: =+PMGR!BW32+BP!BW32 -> 4703354.7 | BX32: =+PMGR!BX32+BP!BX32 -> 4882967.1 | BY32: =+PMGR!BY32+BP!BY32 -> 4991697.3 | BZ32: =+PMGR!BZ32+BP!BZ32 -> 5234518.7 | ... CD32: =+PMGR!CD32+BP!CD32 -> 5107043.2 | CE32: =+SUM(BS32:CD32) -> 57931064 | CG32: =+PMGR!CG32+BP!CG32 -> 2612481.5 | CH32: =+PMGR!CH32+BP!CH32 -> 2584907.2 | CI32: =+PMGR!CI32+BP!CI32 -> 2008424.9 | CJ32: =+PMGR!CJ32+BP!CJ32 -> 1686625.2 | CK32: =+PMGR!CK32+BP!CK32 -> 2977165.9 | CL32: =+PMGR!CL32+BP!CL32 -> 2517552 | CM32: =+PMGR!CM32+BP!CM32 -> 2644471 | CN32: =+PMGR!CN32+BP!CN32 -> 2753956.8 | ... CR32: =+PMGR!CR32+BP!CR32 -> 2546560.1 | CS32: =+SUM(CG32:CR32) -> 29872496 | CT32: =BD32 -> Labour Revenue | CU32: =+PMGR!CU32+BP!CU32 -> 2498719 | CV32: =+PMGR!CV32+BP!CV32 -> 1671025.6 | CW32: =+PMGR!CW32+BP!CW32 -> 2234045.2 | CX32: =+PMGR!CX32+BP!CX32 -> 1739259.5 | CY32: =+PMGR!CY32+BP!CY32 -> 2672222.9 | CZ32: =+PMGR!CZ32+BP!CZ32 -> 2140620.8 | DA32: =+PMGR!DA32+BP!DA32 -> 2712379.4 | DB32: =+PMGR!DB32+BP!DB32 -> 2881628.3 | ... DF32: =+PMGR!DF32+BP!DF32 -> 0 | DG32: =+SUM(CU32:DF32) -> 23601626 | DI32: =+PMGR!DI32+BP!DI32 -> 3214938.5 | DJ32: =+PMGR!DJ32+BP!DJ32 -> 3198569.8 | DK32: =+PMGR!DK32+BP!DK32 -> 3582022.2 | DL32: =+PMGR!DL32+BP!DL32 -> 2585817.3 | DM32: =+PMGR!DM32+BP!DM32 -> 3087764.2 | DN32: =+PMGR!DN32+BP!DN32 -> 3338737.6 | DO32: =+PMGR!DO32+BP!DO32 -> 3423422.1 | DP32: =+PMGR!DP32+BP!DP32 -> 3504276.5 | ... DT32: =+PMGR!DT32+BP!DT32 -> 3268010.6 | DU32: =+SUM(DI32:DT32) -> 38444348 | DW32: =+PMGR!DW32+BP!DW32 -> 0 | DX32: =+PMGR!DX32+BP!DX32 -> 0 | DY32: =+PMGR!DY32+BP!DY32 -> 0 | DZ32: =+PMGR!DZ32+BP!DZ32 -> 0 | EA32: =+PMGR!EA32+BP!EA32 -> 0 | EB32: =+PMGR!EB32+BP!EB32 -> 0 | EC32: =+PMGR!EC32+BP!EC32 -> 0 | ED32: =+PMGR!ED32+BP!ED32 -> 0 | ... EH32: =+PMGR!EH32+BP!EH32 -> 0 | EI32: =+SUM(DW32:EH32) -> 0 | EJ32: =CT32 -> Labour Revenue | EK32: =+PMGR!EK32+BP!EK32 -> 640593.85 | EL32: =+PMGR!EL32+BP!EL32 -> 686375.51 | EM32: =+PMGR!EM32+BP!EM32 -> 692353.7 | EN32: =+PMGR!EN32+BP!EN32 -> 413947.1 | EO32: =+PMGR!EO32+BP!EO32 -> 799026.6 | EP32: =+PMGR!EP32+BP!EP32 -> 1051720.9 | EQ32: =+PMGR!EQ32+BP!EQ32 -> 767938.76 | ER32: =+PMGR!ER32+BP!ER32 -> 1102050.9 | ... EV32: =+PMGR!EV32+BP!EV32 -> 0 | EW32: =+SUM(EK32:EV32) -> 8112012.3 | EY32: =+PMGR!EY32+BP!EY32 -> 1205155.8 | EZ32: =+PMGR!EZ32+BP!EZ32 -> 1124812.1 | FA32: =+PMGR!FA32+BP!FA32 -> 1255370.6 | FB32: =+PMGR!FB32+BP!FB32 -> 1124812.1 | FC32: =+PMGR!FC32+BP!FC32 -> 1339062 | FD32: =+PMGR!FD32+BP!FD32 -> 1339062 | FE32: =+PMGR!FE32+BP!FE32 -> 1506444.8 | FF32: =+PMGR!FF32+BP!FF32 -> 1450650.5 | ... FJ32: =+PMGR!FJ32+BP!FJ32 -> 1171077.7 | FK32: =+SUM(EY32:FJ32) -> 15094783
A33: =+AQ33+CG33+DW33 -> 2358067.4 | B33: =+AR33+CH33+DX33 -> 3107710 | C33: =+AS33+CI33+DY33 -> 3767254.8 | D33: =+AT33+CJ33+DZ33 -> 1544498 | E33: =+AU33+CK33+EA33 -> 2343547.7 | F33: =+AV33+CL33+EB33 -> 4896443.5 | G33: =+AW33+CM33+EC33 -> 3119333.8 | H33: =+AX33+CN33+ED33 -> 3617154.5 | ... L33: =+BB33+CR33+EH33 -> 3795582.6 | M33: =+SUM(A33:L33) -> 45256817 | N33: Warranty Parts | O33: =+BE33+CU33+EK33 -> 4076459.7 | P33: =+BF33+CV33+EL33 -> 4192321 | Q33: =+BG33+CW33+EM33 -> 9964813.5 | R33: =+BH33+CX33+EN33 -> 5876565 | S33: =+BI33+CY33+EO33 -> 6626650.9 | T33: =+BJ33+CZ33+EP33 -> 3459252 | U33: =+BK33+DA33+EQ33 -> 3722684.8 | V33: =+BL33+DB33+ER33 -> 4436778.3 | ... Z33: =+BP33+DF33+EV33 -> 0 | AA33: =+SUM(O33:Z33) -> 51435616 | AC33: =+BS33+DI33+EY33 -> 2787273.2 | AD33: =+BT33+DJ33+EZ33 -> 2724096.9 | AE33: =+BU33+DK33+FA33 -> 2741526.7 | AF33: =+BV33+DL33+FB33 -> 2337208 | AG33: =+BW33+DM33+FC33 -> 2630931.9 | AH33: =+BX33+DN33+FD33 -> 2761825.3 | AI33: =+BY33+DO33+FE33 -> 2852848.7 | AJ33: =+BZ33+DP33+FF33 -> 2880877.4 | ... AN33: =+CD33+DT33+FJ33 -> 2825293.1 | AO33: =+SUM(AC33:AN33) -> 32389663 | AQ33: =+PMGR!AQ33+BP!AQ33 -> 1297444 | AR33: =+PMGR!AR33+BP!AR33 -> 1465654.2 | AS33: =+PMGR!AS33+BP!AS33 -> 3137334.1 | AT33: =+PMGR!AT33+BP!AT33 -> 993269 | AU33: =+PMGR!AU33+BP!AU33 -> 1486260.9 | AV33: =+PMGR!AV33+BP!AV33 -> 1707649.3 | AW33: =+PMGR!AW33+BP!AW33 -> 2123853.1 | AX33: =+PMGR!AX33+BP!AX33 -> 2401313.5 | ... BB33: =+PMGR!BB33+BP!BB33 -> 2920345.1 | BC33: =+SUM(AQ33:BB33) -> 32049999 | BD33: =N33 -> Warranty Parts | BE33: =+PMGR!BE33+BP!BE33 -> 2558615.2 | BF33: =+PMGR!BF33+BP!BF33 -> 3755948 | BG33: =+PMGR!BG33+BP!BG33 -> 9018030.6 | BH33: =+PMGR!BH33+BP!BH33 -> 4867079 | BI33: =+PMGR!BI33+BP!BI33 -> 3560311.5 | BJ33: =+PMGR!BJ33+BP!BJ33 -> 1843594.8 | BK33: =+PMGR!BK33+BP!BK33 -> 2497832.1 | BL33: =+PMGR!BL33+BP!BL33 -> 3439648.8 | ... BP33: =+PMGR!BP33+BP!BP33 -> 0 | BQ33: =+SUM(BE33:BP33) -> 38162627 | BS33: =+PMGR!BS33+BP!BS33 -> 1567596.7 | BT33: =+PMGR!BT33+BP!BT33 -> 1533486.6 | BU33: =+PMGR!BU33+BP!BU33 -> 1431156.5 | BV33: =+PMGR!BV33+BP!BV33 -> 1324613.8 | BW33: =+PMGR!BW33+BP!BW33 -> 1468018.7 | BX33: =+PMGR!BX33+BP!BX33 -> 1523752.6 | BY33: =+PMGR!BY33+BP!BY33 -> 1557924.2 | BZ33: =+PMGR!BZ33+BP!BZ33 -> 1633023 | ... CD33: =+PMGR!CD33+BP!CD33 -> 1594108.3 | CE33: =+SUM(BS33:CD33) -> 18079444 | CG33: =+PMGR!CG33+BP!CG33 -> 1060623.3 | CH33: =+PMGR!CH33+BP!CH33 -> 1642055.8 | CI33: =+PMGR!CI33+BP!CI33 -> 629920.69 | CJ33: =+PMGR!CJ33+BP!CJ33 -> 551229.04 | CK33: =+PMGR!CK33+BP!CK33 -> 857286.78 | CL33: =+PMGR!CL33+BP!CL33 -> 3188794.3 | CM33: =+PMGR!CM33+BP!CM33 -> 995480.76 | CN33: =+PMGR!CN33+BP!CN33 -> 1215841 | ... CR33: =+PMGR!CR33+BP!CR33 -> 875237.48 | CS33: =+SUM(CG33:CR33) -> 13206818 | CT33: =BD33 -> Warranty Parts | CU33: =+PMGR!CU33+BP!CU33 -> 1274652.6 | CV33: =+PMGR!CV33+BP!CV33 -> 337392.2 | CW33: =+PMGR!CW33+BP!CW33 -> 624996.3 | CX33: =+PMGR!CX33+BP!CX33 -> 890704.14 | CY33: =+PMGR!CY33+BP!CY33 -> 2707176.4 | CZ33: =+PMGR!CZ33+BP!CZ33 -> 1444507 | DA33: =+PMGR!DA33+BP!DA33 -> 855358.04 | DB33: =+PMGR!DB33+BP!DB33 -> 516392.99 | ... DF33: =+PMGR!DF33+BP!DF33 -> 0 | DG33: =+SUM(CU33:DF33) -> 10471335 | DI33: =+PMGR!DI33+BP!DI33 -> 1219676.5 | DJ33: =+PMGR!DJ33+BP!DJ33 -> 1190610.2 | DK33: =+PMGR!DK33+BP!DK33 -> 1310370.2 | DL33: =+PMGR!DL33+BP!DL33 -> 1012594.1 | DM33: =+PMGR!DM33+BP!DM33 -> 1162913.2 | DN33: =+PMGR!DN33+BP!DN33 -> 1238072.7 | DO33: =+PMGR!DO33+BP!DO33 -> 1294924.6 | DP33: =+PMGR!DP33+BP!DP33 -> 1247854.4 | ... DT33: =+PMGR!DT33+BP!DT33 -> 1231184.8 | DU33: =+SUM(DI33:DT33) -> 14310219 | DW33: =+PMGR!DW33+BP!DW33 -> 0 | DX33: =+PMGR!DX33+BP!DX33 -> 0 | DY33: =+PMGR!DY33+BP!DY33 -> 0 | DZ33: =+PMGR!DZ33+BP!DZ33 -> 0 | EA33: =+PMGR!EA33+BP!EA33 -> 0 | EB33: =+PMGR!EB33+BP!EB33 -> 0 | EC33: =+PMGR!EC33+BP!EC33 -> 0 | ED33: =+PMGR!ED33+BP!ED33 -> 0 | ... EH33: =+PMGR!EH33+BP!EH33 -> 0 | EI33: =+SUM(DW33:EH33) -> 0 | EJ33: =CT33 -> Warranty Parts | EK33: =+PMGR!EK33+BP!EK33 -> 243192 | EL33: =+PMGR!EL33+BP!EL33 -> 98980.78 | EM33: =+PMGR!EM33+BP!EM33 -> 321786.64 | EN33: =+PMGR!EN33+BP!EN33 -> 118781.86 | EO33: =+PMGR!EO33+BP!EO33 -> 359162.93 | EP33: =+PMGR!EP33+BP!EP33 -> 171150.17 | EQ33: =+PMGR!EQ33+BP!EQ33 -> 369494.62 | ER33: =+PMGR!ER33+BP!ER33 -> 480736.59 | ... EV33: =+PMGR!EV33+BP!EV33 -> 0 | EW33: =+SUM(EK33:EV33) -> 2801653.4 | EY33: =+PMGR!EY33+BP!EY33 -> 0 | EZ33: =+PMGR!EZ33+BP!EZ33 -> 0 | FA33: =+PMGR!FA33+BP!FA33 -> 0 | FB33: =+PMGR!FB33+BP!FB33 -> 0 | FC33: =+PMGR!FC33+BP!FC33 -> 0 | FD33: =+PMGR!FD33+BP!FD33 -> 0 | FE33: =+PMGR!FE33+BP!FE33 -> 0 | FF33: =+PMGR!FF33+BP!FF33 -> 0 | ... FJ33: =+PMGR!FJ33+BP!FJ33 -> 0 | FK33: =+SUM(EY33:FJ33) -> 0
A34: =+AQ34+CG34+DW34 -> 116704.8 | B34: =+AR34+CH34+DX34 -> 621355.5 | C34: =+AS34+CI34+DY34 -> 485198.7 | D34: =+AT34+CJ34+DZ34 -> 300793.5 | E34: =+AU34+CK34+EA34 -> 404654.7 | F34: =+AV34+CL34+EB34 -> 427433.03 | G34: =+AW34+CM34+EC34 -> 407081.1 | H34: =+AX34+CN34+ED34 -> 254504.1 | ... L34: =+BB34+CR34+EH34 -> 320163.6 | M34: =+SUM(A34:L34) -> 4712473.4 | N34: Warranty Labour | O34: =+BE34+CU34+EK34 -> 740246.4 | P34: =+BF34+CV34+EL34 -> 57217.2 | Q34: =+BG34+CW34+EM34 -> 1482770.6 | R34: =+BH34+CX34+EN34 -> 1638210.4 | S34: =+BI34+CY34+EO34 -> 2978382.3 | T34: =+BJ34+CZ34+EP34 -> 599895.5 | U34: =+BK34+DA34+EQ34 -> 382592.4 | V34: =+BL34+DB34+ER34 -> 497054.5 | ... Z34: =+BP34+DF34+EV34 -> 0 | AA34: =+SUM(O34:Z34) -> 9630284.7 | AC34: =+BS34+DI34+EY34 -> 464545.53 | AD34: =+BT34+DJ34+EZ34 -> 454016.14 | AE34: =+BU34+DK34+FA34 -> 456921.11 | AF34: =+BV34+DL34+FB34 -> 389534.66 | AG34: =+BW34+DM34+FC34 -> 438488.65 | AH34: =+BX34+DN34+FD34 -> 460304.21 | AI34: =+BY34+DO34+FE34 -> 475474.79 | AJ34: =+BZ34+DP34+FF34 -> 480146.23 | ... AN34: =+CD34+DT34+FJ34 -> 470882.18 | AO34: =+SUM(AC34:AN34) -> 5398277.2 | AQ34: =+PMGR!AQ34+BP!AQ34 -> 85780.8 | AR34: =+PMGR!AR34+BP!AR34 -> 348451.2 | AS34: =+PMGR!AS34+BP!AS34 -> 320013 | AT34: =+PMGR!AT34+BP!AT34 -> 222710.4 | AU34: =+PMGR!AU34+BP!AU34 -> 211122 | AV34: =+PMGR!AV34+BP!AV34 -> 241824.6 | AW34: =+PMGR!AW34+BP!AW34 -> 210456 | AX34: =+PMGR!AX34+BP!AX34 -> 186213.6 | ... BB34: =+PMGR!BB34+BP!BB34 -> 263469.6 | BC34: =+SUM(AQ34:BB34) -> 3066930 | BD34: =N34 -> Warranty Labour | BE34: =+PMGR!BE34+BP!BE34 -> 548517.6 | BF34: =+PMGR!BF34+BP!BF34 -> 39693.6 | BG34: =+PMGR!BG34+BP!BG34 -> 1358809.6 | BH34: =+PMGR!BH34+BP!BH34 -> 867111.6 | BI34: =+PMGR!BI34+BP!BI34 -> 2725840 | BJ34: =+PMGR!BJ34+BP!BJ34 -> 394619 | BK34: =+PMGR!BK34+BP!BK34 -> 220260.6 | BL34: =+PMGR!BL34+BP!BL34 -> 336657 | ... BP34: =+PMGR!BP34+BP!BP34 -> 0 | BQ34: =+SUM(BE34:BP34) -> 7429606.9 | BS34: =+PMGR!BS34+BP!BS34 -> 261266.12 | BT34: =+PMGR!BT34+BP!BT34 -> 255581.11 | BU34: =+PMGR!BU34+BP!BU34 -> 238526.08 | BV34: =+PMGR!BV34+BP!BV34 -> 220768.97 | BW34: =+PMGR!BW34+BP!BW34 -> 244669.79 | BX34: =+PMGR!BX34+BP!BX34 -> 253958.76 | BY34: =+PMGR!BY34+BP!BY34 -> 259654.03 | BZ34: =+PMGR!BZ34+BP!BZ34 -> 272170.5 | ... CD34: =+PMGR!CD34+BP!CD34 -> 265684.72 | CE34: =+SUM(BS34:CD34) -> 3013240.7 | CG34: =+PMGR!CG34+BP!CG34 -> 30924 | CH34: =+PMGR!CH34+BP!CH34 -> 272904.3 | CI34: =+PMGR!CI34+BP!CI34 -> 165185.7 | CJ34: =+PMGR!CJ34+BP!CJ34 -> 78083.1 | CK34: =+PMGR!CK34+BP!CK34 -> 193532.7 | CL34: =+PMGR!CL34+BP!CL34 -> 185608.43 | CM34: =+PMGR!CM34+BP!CM34 -> 196625.1 | CN34: =+PMGR!CN34+BP!CN34 -> 68290.5 | ... CR34: =+PMGR!CR34+BP!CR34 -> 56694 | CS34: =+SUM(CG34:CR34) -> 1645543.4 | CT34: =BD34 -> Warranty Labour | CU34: =+PMGR!CU34+BP!CU34 -> 191728.8 | CV34: =+PMGR!CV34+BP!CV34 -> 17523.6 | CW34: =+PMGR!CW34+BP!CW34 -> 97475.03 | CX34: =+PMGR!CX34+BP!CX34 -> 115042.8 | CY34: =+PMGR!CY34+BP!CY34 -> 177929.3 | CZ34: =+PMGR!CZ34+BP!CZ34 -> 151981.5 | DA34: =+PMGR!DA34+BP!DA34 -> 72214.8 | DB34: =+PMGR!DB34+BP!DB34 -> 100642.5 | ... DF34: =+PMGR!DF34+BP!DF34 -> 0 | DG34: =+SUM(CU34:DF34) -> 1122137.8 | DI34: =+PMGR!DI34+BP!DI34 -> 203279.42 | DJ34: =+PMGR!DJ34+BP!DJ34 -> 198435.04 | DK34: =+PMGR!DK34+BP!DK34 -> 218395.03 | DL34: =+PMGR!DL34+BP!DL34 -> 168765.69 | DM34: =+PMGR!DM34+BP!DM34 -> 193818.87 | DN34: =+PMGR!DN34+BP!DN34 -> 206345.45 | DO34: =+PMGR!DO34+BP!DO34 -> 215820.76 | DP34: =+PMGR!DP34+BP!DP34 -> 207975.73 | ... DT34: =+PMGR!DT34+BP!DT34 -> 205197.47 | DU34: =+SUM(DI34:DT34) -> 2385036.5 | DW34: =+PMGR!DW34+BP!DW34 -> 0 | DX34: =+PMGR!DX34+BP!DX34 -> 0 | DY34: =+PMGR!DY34+BP!DY34 -> 0 | DZ34: =+PMGR!DZ34+BP!DZ34 -> 0 | EA34: =+PMGR!EA34+BP!EA34 -> 0 | EB34: =+PMGR!EB34+BP!EB34 -> 0 | EC34: =+PMGR!EC34+BP!EC34 -> 0 | ED34: =+PMGR!ED34+BP!ED34 -> 0 | ... EH34: =+PMGR!EH34+BP!EH34 -> 0 | EI34: =+SUM(DW34:EH34) -> 0 | EJ34: =CT34 -> Warranty Labour | EK34: =+PMGR!EK34+BP!EK34 -> 0 | EL34: =+PMGR!EL34+BP!EL34 -> 0 | EM34: =+PMGR!EM34+BP!EM34 -> 26486 | EN34: =+PMGR!EN34+BP!EN34 -> 656056 | EO34: =+PMGR!EO34+BP!EO34 -> 74613 | EP34: =+PMGR!EP34+BP!EP34 -> 53295 | EQ34: =+PMGR!EQ34+BP!EQ34 -> 90117 | ER34: =+PMGR!ER34+BP!ER34 -> 59755 | ... EV34: =+PMGR!EV34+BP!EV34 -> 0 | EW34: =+SUM(EK34:EV34) -> 1078540 | EY34: =+PMGR!EY34+BP!EY34 -> 0 | EZ34: =+PMGR!EZ34+BP!EZ34 -> 0 | FA34: =+PMGR!FA34+BP!FA34 -> 0 | FB34: =+PMGR!FB34+BP!FB34 -> 0 | FC34: =+PMGR!FC34+BP!FC34 -> 0 | FD34: =+PMGR!FD34+BP!FD34 -> 0 | FE34: =+PMGR!FE34+BP!FE34 -> 0 | FF34: =+PMGR!FF34+BP!FF34 -> 0 | ... FJ34: =+PMGR!FJ34+BP!FJ34 -> 0 | FK34: =+SUM(EY34:FJ34) -> 0
A35: =+AQ35+CG35+DW35 -> 475961.28 | B35: =+AR35+CH35+DX35 -> 580892.85 | C35: =+AS35+CI35+DY35 -> 756699.17 | D35: =+AT35+CJ35+DZ35 -> 768157.28 | E35: =+AU35+CK35+EA35 -> 540240.48 | F35: =+AV35+CL35+EB35 -> 680318.35 | G35: =+AW35+CM35+EC35 -> 463228.73 | H35: =+AX35+CN35+ED35 -> 502265.5 | ... L35: =+BB35+CR35+EH35 -> 496696.42 | M35: =+SUM(A35:L35) -> 7693043.9 | N35: Internal Sales | O35: =+BE35+CU35+EK35 -> 211620.97 | P35: =+BF35+CV35+EL35 -> 402740.79 | Q35: =+BG35+CW35+EM35 -> 668858.42 | R35: =+BH35+CX35+EN35 -> 798064.67 | S35: =+BI35+CY35+EO35 -> 1097659.5 | T35: =+BJ35+CZ35+EP35 -> 651985.43 | U35: =+BK35+DA35+EQ35 -> 998684.53 | V35: =+BL35+DB35+ER35 -> 507049.1 | ... Z35: =+BP35+DF35+EV35 -> 0 | AA35: =+SUM(O35:Z35) -> 7526593.8 | AC35: =+BS35+DI35+EY35 -> 0 | AD35: =+BT35+DJ35+EZ35 -> 0 | AE35: =+BU35+DK35+FA35 -> 0 | AF35: =+BV35+DL35+FB35 -> 0 | AG35: =+BW35+DM35+FC35 -> 0 | AH35: =+BX35+DN35+FD35 -> 0 | AI35: =+BY35+DO35+FE35 -> 0 | AJ35: =+BZ35+DP35+FF35 -> 0 | ... AN35: =+CD35+DT35+FJ35 -> 0 | AO35: =+SUM(AC35:AN35) -> 0 | AQ35: =+PMGR!AQ35+BP!AQ35 -> 405435.71 | AR35: =+PMGR!AR35+BP!AR35 -> 312776.72 | AS35: =+PMGR!AS35+BP!AS35 -> 445611.32 | AT35: =+PMGR!AT35+BP!AT35 -> 727204.92 | AU35: =+PMGR!AU35+BP!AU35 -> 215353.95 | AV35: =+PMGR!AV35+BP!AV35 -> 347874.12 | AW35: =+PMGR!AW35+BP!AW35 -> 261126.2 | AX35: =+PMGR!AX35+BP!AX35 -> 399862.92 | ... BB35: =+PMGR!BB35+BP!BB35 -> 371935.99 | BC35: =+SUM(AQ35:BB35) -> 5004954.4 | BD35: =N35 -> Internal Sales | BE35: =+PMGR!BE35+BP!BE35 -> 50334.85 | BF35: =+PMGR!BF35+BP!BF35 -> 265017.98 | BG35: =+PMGR!BG35+BP!BG35 -> 639641.8 | BH35: =+PMGR!BH35+BP!BH35 -> 157190.56 | BI35: =+PMGR!BI35+BP!BI35 -> 891498.91 | BJ35: =+PMGR!BJ35+BP!BJ35 -> 468490.17 | BK35: =+PMGR!BK35+BP!BK35 -> 604172.04 | BL35: =+PMGR!BL35+BP!BL35 -> 353757 | ... BP35: =+PMGR!BP35+BP!BP35 -> 0 | BQ35: =+SUM(BE35:BP35) -> 4991863.4 | BS35: =+PMGR!BS35+BP!BS35 -> 0 | BT35: =+PMGR!BT35+BP!BT35 -> 0 | BU35: =+PMGR!BU35+BP!BU35 -> 0 | BV35: =+PMGR!BV35+BP!BV35 -> 0 | BW35: =+PMGR!BW35+BP!BW35 -> 0 | BX35: =+PMGR!BX35+BP!BX35 -> 0 | BY35: =+PMGR!BY35+BP!BY35 -> 0 | BZ35: =+PMGR!BZ35+BP!BZ35 -> 0 | ... CD35: =+PMGR!CD35+BP!CD35 -> 0 | CE35: =+SUM(BS35:CD35) -> 0 | CG35: =+PMGR!CG35+BP!CG35 -> 70525.57 | CH35: =+PMGR!CH35+BP!CH35 -> 268116.13 | CI35: =+PMGR!CI35+BP!CI35 -> 311087.85 | CJ35: =+PMGR!CJ35+BP!CJ35 -> 40952.36 | CK35: =+PMGR!CK35+BP!CK35 -> 324886.53 | CL35: =+PMGR!CL35+BP!CL35 -> 332444.23 | CM35: =+PMGR!CM35+BP!CM35 -> 202102.53 | CN35: =+PMGR!CN35+BP!CN35 -> 102402.58 | ... CR35: =+PMGR!CR35+BP!CR35 -> 124760.43 | CS35: =+SUM(CG35:CR35) -> 2688089.5 | CT35: =BD35 -> Internal Sales | CU35: =+PMGR!CU35+BP!CU35 -> 159413.56 | CV35: =+PMGR!CV35+BP!CV35 -> 133546.54 | CW35: =+PMGR!CW35+BP!CW35 -> 29216.62 | CX35: =+PMGR!CX35+BP!CX35 -> 511020.84 | CY35: =+PMGR!CY35+BP!CY35 -> 165994.36 | CZ35: =+PMGR!CZ35+BP!CZ35 -> 51500.99 | DA35: =+PMGR!DA35+BP!DA35 -> 326863.47 | DB35: =+PMGR!DB35+BP!DB35 -> 22862.6 | ... DF35: =+PMGR!DF35+BP!DF35 -> 0 | DG35: =+SUM(CU35:DF35) -> 1799054.4 | DI35: =+PMGR!DI35+BP!DI35 -> 0 | DJ35: =+PMGR!DJ35+BP!DJ35 -> 0 | DK35: =+PMGR!DK35+BP!DK35 -> 0 | DL35: =+PMGR!DL35+BP!DL35 -> 0 | DM35: =+PMGR!DM35+BP!DM35 -> 0 | DN35: =+PMGR!DN35+BP!DN35 -> 0 | DO35: =+PMGR!DO35+BP!DO35 -> 0 | DP35: =+PMGR!DP35+BP!DP35 -> 0 | ... DT35: =+PMGR!DT35+BP!DT35 -> 0 | DU35: =+SUM(DI35:DT35) -> 0 | DW35: =+PMGR!DW35+BP!DW35 -> 0 | DX35: =+PMGR!DX35+BP!DX35 -> 0 | DY35: =+PMGR!DY35+BP!DY35 -> 0 | DZ35: =+PMGR!DZ35+BP!DZ35 -> 0 | EA35: =+PMGR!EA35+BP!EA35 -> 0 | EB35: =+PMGR!EB35+BP!EB35 -> 0 | EC35: =+PMGR!EC35+BP!EC35 -> 0 | ED35: =+PMGR!ED35+BP!ED35 -> 0 | ... EH35: =+PMGR!EH35+BP!EH35 -> 0 | EI35: =+SUM(DW35:EH35) -> 0 | EJ35: =CT35 -> Internal Sales | EK35: =+PMGR!EK35+BP!EK35 -> 1872.56 | EL35: =+PMGR!EL35+BP!EL35 -> 4176.27 | EM35: =+PMGR!EM35+BP!EM35 -> 0 | EN35: =+PMGR!EN35+BP!EN35 -> 129853.27 | EO35: =+PMGR!EO35+BP!EO35 -> 40166.27 | EP35: =+PMGR!EP35+BP!EP35 -> 131994.27 | EQ35: =+PMGR!EQ35+BP!EQ35 -> 67649.02 | ER35: =+PMGR!ER35+BP!ER35 -> 130429.5 | ... EV35: =+PMGR!EV35+BP!EV35 -> 0 | EW35: =+SUM(EK35:EV35) -> 735676.07 | EY35: =+PMGR!EY35+BP!EY35 -> 0 | EZ35: =+PMGR!EZ35+BP!EZ35 -> 0 | FA35: =+PMGR!FA35+BP!FA35 -> 0 | FB35: =+PMGR!FB35+BP!FB35 -> 0 | FC35: =+PMGR!FC35+BP!FC35 -> 0 | FD35: =+PMGR!FD35+BP!FD35 -> 0 | FE35: =+PMGR!FE35+BP!FE35 -> 0 | FF35: =+PMGR!FF35+BP!FF35 -> 0 | ... FJ35: =+PMGR!FJ35+BP!FJ35 -> 0 | FK35: =+SUM(EY35:FJ35) -> 0
A36: =+AQ36+CG36+DW36 -> 2011629.6 | B36: =+AR36+CH36+DX36 -> 2366818.1 | C36: =+AS36+CI36+DY36 -> 2459466.9 | D36: =+AT36+CJ36+DZ36 -> 2184377 | E36: =+AU36+CK36+EA36 -> 1775208.7 | F36: =+AV36+CL36+EB36 -> 1714035.9 | G36: =+AW36+CM36+EC36 -> 1849420.5 | H36: =+AX36+CN36+ED36 -> 1881207.1 | ... L36: =+BB36+CR36+EH36 -> 1816696.5 | M36: =+SUM(A36:L36) -> 24116390 | N36: Starease Sales | O36: =+BE36+CU36+EK36 -> 1953531.6 | P36: =+BF36+CV36+EL36 -> 2028960.2 | Q36: =+BG36+CW36+EM36 -> 1847315.6 | R36: =+BH36+CX36+EN36 -> 1919821.6 | S36: =+BI36+CY36+EO36 -> 1988266.3 | T36: =+BJ36+CZ36+EP36 -> 1887437.4 | U36: =+BK36+DA36+EQ36 -> 2210241.6 | V36: =+BL36+DB36+ER36 -> 2043928.9 | ... Z36: =+BP36+DF36+EV36 -> 0 | AA36: =+SUM(O36:Z36) -> 20025848 | AC36: =+BS36+DI36+EY36 -> 0 | AD36: =+BT36+DJ36+EZ36 -> 0 | AE36: =+BU36+DK36+FA36 -> 0 | AF36: =+BV36+DL36+FB36 -> 0 | AG36: =+BW36+DM36+FC36 -> 0 | AH36: =+BX36+DN36+FD36 -> 0 | AI36: =+BY36+DO36+FE36 -> 0 | AJ36: =+BZ36+DP36+FF36 -> 0 | ... AN36: =+CD36+DT36+FJ36 -> 0 | AO36: =+SUM(AC36:AN36) -> 0 | AQ36: =+PMGR!AQ36+BP!AQ36 -> 1122971.4 | AR36: =+PMGR!AR36+BP!AR36 -> 1279084.7 | AS36: =+PMGR!AS36+BP!AS36 -> 1406683.5 | AT36: =+PMGR!AT36+BP!AT36 -> 1231385.4 | AU36: =+PMGR!AU36+BP!AU36 -> 1047373.1 | AV36: =+PMGR!AV36+BP!AV36 -> 1046169.7 | AW36: =+PMGR!AW36+BP!AW36 -> 1264140.6 | AX36: =+PMGR!AX36+BP!AX36 -> 1507145.9 | ... BB36: =+PMGR!BB36+BP!BB36 -> 1476654 | BC36: =+SUM(AQ36:BB36) -> 15624143 | BD36: =N36 -> Starease Sales | BE36: =+PMGR!BE36+BP!BE36 -> 957844.49 | BF36: =+PMGR!BF36+BP!BF36 -> 1384822.3 | BG36: =+PMGR!BG36+BP!BG36 -> 1225244.4 | BH36: =+PMGR!BH36+BP!BH36 -> 1384051.8 | BI36: =+PMGR!BI36+BP!BI36 -> 1709327.7 | BJ36: =+PMGR!BJ36+BP!BJ36 -> 1499988 | BK36: =+PMGR!BK36+BP!BK36 -> 1490862.4 | BL36: =+PMGR!BL36+BP!BL36 -> 1371385.7 | ... BP36: =+PMGR!BP36+BP!BP36 -> 0 | BQ36: =+SUM(BE36:BP36) -> 14056593 | BS36: =+PMGR!BS36+BP!BS36 -> 0 | BT36: =+PMGR!BT36+BP!BT36 -> 0 | BU36: =+PMGR!BU36+BP!BU36 -> 0 | BV36: =+PMGR!BV36+BP!BV36 -> 0 | BW36: =+PMGR!BW36+BP!BW36 -> 0 | BX36: =+PMGR!BX36+BP!BX36 -> 0 | BY36: =+PMGR!BY36+BP!BY36 -> 0 | BZ36: =+PMGR!BZ36+BP!BZ36 -> 0 | ... CD36: =+PMGR!CD36+BP!CD36 -> 0 | CE36: =+SUM(BS36:CD36) -> 0 | CG36: =+PMGR!CG36+BP!CG36 -> 888658.25 | CH36: =+PMGR!CH36+BP!CH36 -> 1087733.5 | CI36: =+PMGR!CI36+BP!CI36 -> 1052783.4 | CJ36: =+PMGR!CJ36+BP!CJ36 -> 952991.62 | CK36: =+PMGR!CK36+BP!CK36 -> 727835.57 | CL36: =+PMGR!CL36+BP!CL36 -> 667866.15 | CM36: =+PMGR!CM36+BP!CM36 -> 585279.87 | CN36: =+PMGR!CN36+BP!CN36 -> 374061.22 | ... CR36: =+PMGR!CR36+BP!CR36 -> 340042.52 | CS36: =+SUM(CG36:CR36) -> 8492247 | CT36: =BD36 -> Starease Sales | CU36: =+PMGR!CU36+BP!CU36 -> 880115.9 | CV36: =+PMGR!CV36+BP!CV36 -> 476861.93 | CW36: =+PMGR!CW36+BP!CW36 -> 622071.29 | CX36: =+PMGR!CX36+BP!CX36 -> 535769.79 | CY36: =+PMGR!CY36+BP!CY36 -> 278938.62 | CZ36: =+PMGR!CZ36+BP!CZ36 -> 309585.07 | DA36: =+PMGR!DA36+BP!DA36 -> 719379.17 | DB36: =+PMGR!DB36+BP!DB36 -> 672543.14 | ... DF36: =+PMGR!DF36+BP!DF36 -> 0 | DG36: =+SUM(CU36:DF36) -> 5456362.5 | DI36: =+PMGR!DI36+BP!DI36 -> 0 | DJ36: =+PMGR!DJ36+BP!DJ36 -> 0 | DK36: =+PMGR!DK36+BP!DK36 -> 0 | DL36: =+PMGR!DL36+BP!DL36 -> 0 | DM36: =+PMGR!DM36+BP!DM36 -> 0 | DN36: =+PMGR!DN36+BP!DN36 -> 0 | DO36: =+PMGR!DO36+BP!DO36 -> 0 | DP36: =+PMGR!DP36+BP!DP36 -> 0 | ... DT36: =+PMGR!DT36+BP!DT36 -> 0 | DU36: =+SUM(DI36:DT36) -> 0 | DW36: =+PMGR!DW36+BP!DW36 -> 0 | DX36: =+PMGR!DX36+BP!DX36 -> 0 | DY36: =+PMGR!DY36+BP!DY36 -> 0 | DZ36: =+PMGR!DZ36+BP!DZ36 -> 0 | EA36: =+PMGR!EA36+BP!EA36 -> 0 | EB36: =+PMGR!EB36+BP!EB36 -> 0 | EC36: =+PMGR!EC36+BP!EC36 -> 0 | ED36: =+PMGR!ED36+BP!ED36 -> 0 | ... EH36: =+PMGR!EH36+BP!EH36 -> 0 | EI36: =+SUM(DW36:EH36) -> 0 | EJ36: =CT36 -> Starease Sales | EK36: =+PMGR!EK36+BP!EK36 -> 115571.18 | EL36: =+PMGR!EL36+BP!EL36 -> 167275.95 | EM36: =+PMGR!EM36+BP!EM36 -> 0 | EN36: =+PMGR!EN36+BP!EN36 -> 0 | EO36: =+PMGR!EO36+BP!EO36 -> 0 | EP36: =+PMGR!EP36+BP!EP36 -> 77864.353 | EQ36: =+PMGR!EQ36+BP!EQ36 -> 0 | ER36: =+PMGR!ER36+BP!ER36 -> 0 | ... EV36: =+PMGR!EV36+BP!EV36 -> 0 | EW36: =+SUM(EK36:EV36) -> 512892.28 | EY36: =+PMGR!EY36+BP!EY36 -> 0 | EZ36: =+PMGR!EZ36+BP!EZ36 -> 0 | FA36: =+PMGR!FA36+BP!FA36 -> 0 | FB36: =+PMGR!FB36+BP!FB36 -> 0 | FC36: =+PMGR!FC36+BP!FC36 -> 0 | FD36: =+PMGR!FD36+BP!FD36 -> 0 | FE36: =+PMGR!FE36+BP!FE36 -> 0 | FF36: =+PMGR!FF36+BP!FF36 -> 0 | ... FJ36: =+PMGR!FJ36+BP!FJ36 -> 0 | FK36: =+SUM(EY36:FJ36) -> 0
A37: =+AQ37+CG37+DW37 -> 178652.71 | B37: =+AR37+CH37+DX37 -> 168519.85 | C37: =+AS37+CI37+DY37 -> 272679.86 | D37: =+AT37+CJ37+DZ37 -> 106822.07 | E37: =+AU37+CK37+EA37 -> 94832.22 | F37: =+AV37+CL37+EB37 -> 177930.33 | G37: =+AW37+CM37+EC37 -> 273017.48 | H37: =+AX37+CN37+ED37 -> 162996.84 | ... L37: =+BB37+CR37+EH37 -> 1881087.3 | M37: =+SUM(A37:L37) -> 3674011.3 | N37: Other star package | O37: =+BE37+CU37+EK37 -> 173286.69 | P37: =+BF37+CV37+EL37 -> 117429.45 | Q37: =+BG37+CW37+EM37 -> 228814.42 | R37: =+BH37+CX37+EN37 -> 92870.41 | S37: =+BI37+CY37+EO37 -> 501259.42 | T37: =+BJ37+CZ37+EP37 -> 457440.04 | U37: =+BK37+DA37+EQ37 -> 550702.57 | V37: =+BL37+DB37+ER37 -> 435994.19 | ... Z37: =+BP37+DF37+EV37 -> 0 | AA37: =+SUM(O37:Z37) -> 3022322.9 | AC37: =+BS37+DI37+EY37 -> 0 | AD37: =+BT37+DJ37+EZ37 -> 0 | AE37: =+BU37+DK37+FA37 -> 0 | AF37: =+BV37+DL37+FB37 -> 0 | AG37: =+BW37+DM37+FC37 -> 0 | AH37: =+BX37+DN37+FD37 -> 0 | AI37: =+BY37+DO37+FE37 -> 0 | AJ37: =+BZ37+DP37+FF37 -> 0 | ... AN37: =+CD37+DT37+FJ37 -> 0 | AO37: =+SUM(AC37:AN37) -> 0 | AQ37: =+PMGR!AQ37+BP!AQ37 -> 178652.71 | AR37: =+PMGR!AR37+BP!AR37 -> 168519.85 | AS37: =+PMGR!AS37+BP!AS37 -> 272679.86 | AT37: =+PMGR!AT37+BP!AT37 -> 106822.07 | AU37: =+PMGR!AU37+BP!AU37 -> 94832.22 | AV37: =+PMGR!AV37+BP!AV37 -> 177930.33 | AW37: =+PMGR!AW37+BP!AW37 -> 273017.48 | AX37: =+PMGR!AX37+BP!AX37 -> 162996.84 | ... BB37: =+PMGR!BB37+BP!BB37 -> 1881087.3 | BC37: =+SUM(AQ37:BB37) -> 3674011.3 | BD37: Other star package | BE37: =+PMGR!BE37+BP!BE37 -> 173286.69 | BF37: =+PMGR!BF37+BP!BF37 -> 117429.45 | BG37: =+PMGR!BG37+BP!BG37 -> 228814.42 | BH37: =+PMGR!BH37+BP!BH37 -> 92870.41 | BI37: =+PMGR!BI37+BP!BI37 -> 501259.42 | BJ37: =+PMGR!BJ37+BP!BJ37 -> 457440.04 | BK37: =+PMGR!BK37+BP!BK37 -> 550702.57 | BL37: =+PMGR!BL37+BP!BL37 -> 435994.19 | ... BP37: =+PMGR!BP37+BP!BP37 -> 0 | BQ37: =+SUM(BE37:BP37) -> 3022322.9 | BS37: =+PMGR!BS37+BP!BS37 -> 0 | BT37: =+PMGR!BT37+BP!BT37 -> 0 | BU37: =+PMGR!BU37+BP!BU37 -> 0 | BV37: =+PMGR!BV37+BP!BV37 -> 0 | BW37: =+PMGR!BW37+BP!BW37 -> 0 | BX37: =+PMGR!BX37+BP!BX37 -> 0 | BY37: =+PMGR!BY37+BP!BY37 -> 0 | BZ37: =+PMGR!BZ37+BP!BZ37 -> 0 | ... CD37: =+PMGR!CD37+BP!CD37 -> 0 | CE37: =+SUM(BS37:CD37) -> 0 | CG37: =+PMGR!CG37+BP!CG37 -> 0 | CH37: =+PMGR!CH37+BP!CH37 -> 0 | CI37: =+PMGR!CI37+BP!CI37 -> 0 | CJ37: =+PMGR!CJ37+BP!CJ37 -> 0 | CK37: =+PMGR!CK37+BP!CK37 -> 0 | CL37: =+PMGR!CL37+BP!CL37 -> 0 | CM37: =+PMGR!CM37+BP!CM37 -> 0 | CN37: =+PMGR!CN37+BP!CN37 -> 0 | ... CR37: =+PMGR!CR37+BP!CR37 -> 0 | CS37: =+SUM(CG37:CR37) -> 0 | CT37: =BD37 -> Other star package | CU37: =+PMGR!CU37+BP!CU37 -> 0 | CV37: =+PMGR!CV37+BP!CV37 -> 0 | CW37: =+PMGR!CW37+BP!CW37 -> 0 | CX37: =+PMGR!CX37+BP!CX37 -> 0 | CY37: =+PMGR!CY37+BP!CY37 -> 0 | CZ37: =+PMGR!CZ37+BP!CZ37 -> 0 | DA37: =+PMGR!DA37+BP!DA37 -> 0 | DB37: =+PMGR!DB37+BP!DB37 -> 0 | ... DF37: =+PMGR!DF37+BP!DF37 -> 0 | DG37: =+SUM(CU37:DF37) -> 0 | DI37: =+PMGR!DI37+BP!DI37 -> 0 | DJ37: =+PMGR!DJ37+BP!DJ37 -> 0 | DK37: =+PMGR!DK37+BP!DK37 -> 0 | DL37: =+PMGR!DL37+BP!DL37 -> 0 | DM37: =+PMGR!DM37+BP!DM37 -> 0 | DN37: =+PMGR!DN37+BP!DN37 -> 0 | DO37: =+PMGR!DO37+BP!DO37 -> 0 | DP37: =+PMGR!DP37+BP!DP37 -> 0 | ... DT37: =+PMGR!DT37+BP!DT37 -> 0 | DU37: =+SUM(DI37:DT37) -> 0 | DW37: =+PMGR!DW37+BP!DW37 -> 0 | DX37: =+PMGR!DX37+BP!DX37 -> 0 | DY37: =+PMGR!DY37+BP!DY37 -> 0 | DZ37: =+PMGR!DZ37+BP!DZ37 -> 0 | EA37: =+PMGR!EA37+BP!EA37 -> 0 | EB37: =+PMGR!EB37+BP!EB37 -> 0 | EC37: =+PMGR!EC37+BP!EC37 -> 0 | ED37: =+PMGR!ED37+BP!ED37 -> 0 | ... EH37: =+PMGR!EH37+BP!EH37 -> 0 | EI37: =+SUM(DW37:EH37) -> 0 | EJ37: =CT37 -> Other star package | EK37: =+PMGR!EK37+BP!EK37 -> 0 | EL37: =+PMGR!EL37+BP!EL37 -> 0 | EM37: =+PMGR!EM37+BP!EM37 -> 0 | EN37: =+PMGR!EN37+BP!EN37 -> 0 | EO37: =+PMGR!EO37+BP!EO37 -> 0 | EP37: =+PMGR!EP37+BP!EP37 -> 0 | EQ37: =+PMGR!EQ37+BP!EQ37 -> 0 | ER37: =+PMGR!ER37+BP!ER37 -> 0 | ... EV37: =+PMGR!EV37+BP!EV37 -> 0 | EW37: =+SUM(EK37:EV37) -> 0 | EY37: =+PMGR!EY37+BP!EY37 -> 0 | EZ37: =+PMGR!EZ37+BP!EZ37 -> 0 | FA37: =+PMGR!FA37+BP!FA37 -> 0 | FB37: =+PMGR!FB37+BP!FB37 -> 0 | FC37: =+PMGR!FC37+BP!FC37 -> 0 | FD37: =+PMGR!FD37+BP!FD37 -> 0 | FE37: =+PMGR!FE37+BP!FE37 -> 0 | FF37: =+PMGR!FF37+BP!FF37 -> 0 | ... FJ37: =+PMGR!FJ37+BP!FJ37 -> 0 | FK37: =+SUM(EY37:FJ37) -> 0
A38: =+SUM(A39:A42) -> 22218373 | B38: =+SUM(B39:B42) -> 28640183 | C38: =+SUM(C39:C42) -> 21368854 | D38: =+SUM(D39:D42) -> 17955675 | E38: =+SUM(E39:E42) -> 21666087 | F38: =+SUM(F39:F42) -> 25393403 | G38: =+SUM(G39:G42) -> 23187013 | H38: =+SUM(H39:H42) -> 28744380 | ... M38: =+SUM(M39:M42) -> 2.9724793e+08 | N38: Cost of Good sold | O38: =+SUM(O39:O42) -> 22533396 | P38: =+SUM(P39:P42) -> 22854948 | Q38: =+SUM(Q39:Q42) -> 32953502 | R38: =+SUM(R39:R42) -> 25647634 | S38: =+SUM(S39:S42) -> 34245432 | T38: =+SUM(T39:T42) -> 27025650 | U38: =+SUM(U39:U42) -> 31897189 | V38: =+SUM(V39:V42) -> 31588240 | ... AA38: =+SUM(AA39:AA42) -> 2.8910385e+08 | AC38: =+SUM(AC39:AC42) -> 30140822 | AD38: =+SUM(AD39:AD42) -> 29576836 | AE38: =+SUM(AE39:AE42) -> 29965923 | AF38: =+SUM(AF39:AF42) -> 25773387 | AG38: =+SUM(AG39:AG42) -> 29197819 | AH38: =+SUM(AH39:AH42) -> 30457527 | AI38: =+SUM(AI39:AI42) -> 31545549 | AJ38: =+SUM(AJ39:AJ42) -> 32258580 | ... AO38: =+SUM(AO39:AO42) -> 3.5492105e+08 | AQ38: =+SUM(AQ39:AQ42) -> 12571707 | AR38: =+SUM(AR39:AR42) -> 18219992 | AS38: =+SUM(AS39:AS42) -> 14063253 | AT38: =+SUM(AT39:AT42) -> 13184037 | AU38: =+SUM(AU39:AU42) -> 10894752 | AV38: =+SUM(AV39:AV42) -> 14166662 | AW38: =+SUM(AW39:AW42) -> 15095895 | AX38: =+SUM(AX39:AX42) -> 19502432 | ... BC38: =+SUM(BC39:BC42) -> 1.915933e+08 | BD38: =N38 -> Cost of Good sold | BE38: =+SUM(BE39:BE42) -> 12921062 | BF38: =+SUM(BF39:BF42) -> 13060730 | BG38: =+SUM(BG39:BG42) -> 22235523 | BH38: =+SUM(BH39:BH42) -> 18005158 | BI38: =+SUM(BI39:BI42) -> 21491396 | BJ38: =+SUM(BJ39:BJ42) -> 15954878 | BK38: =+SUM(BK39:BK42) -> 19435224 | BL38: =+SUM(BL39:BL42) -> 19344813 | ... BQ38: =+SUM(BQ39:BQ42) -> 179374214 | BS38: =+SUM(BS39:BS42) -> 16265994 | BT38: =+SUM(BT39:BT42) -> 15979388 | BU38: =+SUM(BU39:BU42) -> 14863054 | BV38: =+SUM(BV39:BV42) -> 14009544 | BW38: =+SUM(BW39:BW42) -> 15348400 | BX38: =+SUM(BX39:BX42) -> 15856144 | BY38: =+SUM(BY39:BY42) -> 16222708 | BZ38: =+SUM(BZ39:BZ42) -> 16875098 | ... CE38: =+SUM(CE39:CE42) -> 1.8839462e+08 | CG38: =+SUM(CG39:CG42) -> 9646665.8 | CH38: =+SUM(CH39:CH42) -> 10420191 | CI38: =+SUM(CI39:CI42) -> 7305600.7 | CJ38: =+SUM(CJ39:CJ42) -> 4771638.1 | CK38: =+SUM(CK39:CK42) -> 10771334 | CL38: =+SUM(CL39:CL42) -> 11226741 | CM38: =+SUM(CM39:CM42) -> 8091118.1 | CN38: =+SUM(CN39:CN42) -> 9241948.7 | ... CS38: =+SUM(CS39:CS42) -> 1.0565463e+08 | CT38: =BD38 -> Cost of Good sold | CU38: =+SUM(CU39:CU42) -> 7885073.8 | CV38: =+SUM(CV39:CV42) -> 6679582.4 | CW38: =+SUM(CW39:CW42) -> 8620311.3 | CX38: =+SUM(CX39:CX42) -> 6299706.4 | CY38: =+SUM(CY39:CY42) -> 9889412.6 | CZ38: =+SUM(CZ39:CZ42) -> 7019204.6 | DA38: =+SUM(DA39:DA42) -> 9191513.4 | DB38: =+SUM(DB39:DB42) -> 8487305.8 | ... DG38: =+SUM(DG39:DG42) -> 81293666 | DI38: =+SUM(DI39:DI42) -> 10350111 | DJ38: =+SUM(DJ39:DJ42) -> 10290849 | DK38: =+SUM(DK39:DK42) -> 11441830 | DL38: =+SUM(DL39:DL42) -> 8457244.4 | DM38: =+SUM(DM39:DM42) -> 9961174.1 | DN38: =+SUM(DN39:DN42) -> 10713139 | DO38: =+SUM(DO39:DO42) -> 10980187 | DP38: =+SUM(DP39:DP42) -> 11192298 | ... DU38: =+SUM(DU39:DU42) -> 1.2367638e+08 | DW38: =+SUM(DW39:DW42) -> 0 | DX38: =+SUM(DX39:DX42) -> 0 | DY38: =+SUM(DY39:DY42) -> 0 | DZ38: =+SUM(DZ39:DZ42) -> 0 | EA38: =+SUM(EA39:EA42) -> 0 | EB38: =+SUM(EB39:EB42) -> 0 | EC38: =+SUM(EC39:EC42) -> 0 | ED38: =+SUM(ED39:ED42) -> 0 | ... EI38: =+SUM(EI39:EI42) -> 0 | EJ38: =CT38 -> Cost of Good sold | EK38: =+SUM(EK39:EK42) -> 1727260.4 | EL38: =+SUM(EL39:EL42) -> 3114635.6 | EM38: =+SUM(EM39:EM42) -> 2097667.7 | EN38: =+SUM(EN39:EN42) -> 1342769.6 | EO38: =+SUM(EO39:EO42) -> 2864623.4 | EP38: =+SUM(EP39:EP42) -> 4051567.6 | EQ38: =+SUM(EQ39:EQ42) -> 3270452.3 | ER38: =+SUM(ER39:ER42) -> 3756121.9 | ... EW38: =+SUM(EW39:EW42) -> 28435975 | EY38: =+SUM(EY39:EY42) -> 3524716.2 | EZ38: =+SUM(EZ39:EZ42) -> 3306599.4 | FA38: =+SUM(FA39:FA42) -> 3661039.2 | FB38: =+SUM(FB39:FB42) -> 3306599.4 | FC38: =+SUM(FC39:FC42) -> 3888244.2 | FD38: =+SUM(FD39:FD42) -> 3888244.2 | FE38: =+SUM(FE39:FE42) -> 4342654.2 | FF38: =+SUM(FF39:FF42) -> 4191184.2 | ... FK38: =+SUM(FK39:FK42) -> 42850049
A39: =+AQ39+CG39+DW39 -> 20552879 | B39: =+AR39+CH39+DX39 -> 27001118 | C39: =+AS39+CI39+DY39 -> 19683887 | D39: =+AT39+CJ39+DZ39 -> 16329059 | E39: =+AU39+CK39+EA39 -> 19733935 | F39: =+AV39+CL39+EB39 -> 23759785 | G39: =+AW39+CM39+EC39 -> 21664572 | H39: =+AX39+CN39+ED39 -> 27718444 | ... L39: =+BB39+CR39+EH39 -> 25536586 | M39: =+SUM(A39:L39) -> 2.7618148e+08 | N39: Cost of Goods Sold - Parts and Consumables | O39: =+BE39+CU39+EK39 -> 20360345 | P39: =+BF39+CV39+EL39 -> 20483328 | Q39: =+BG39+CW39+EM39 -> 30796561 | R39: =+BH39+CX39+EN39 -> 23516745 | S39: =+BI39+CY39+EO39 -> 31361306 | T39: =+BJ39+CZ39+EP39 -> 24320546 | U39: =+BK39+DA39+EQ39 -> 28596090 | V39: =+BL39+DB39+ER39 -> 28903313 | ... Z39: =+BP39+DF39+EV39 -> 0 | AA39: =+SUM(O39:Z39) -> 2.6369489e+08 | AC39: =+BS39+DI39+EY39 -> 26976565 | AD39: =+BT39+DJ39+EZ39 -> 26442363 | AE39: =+BU39+DK39+FA39 -> 26813617 | AF39: =+BV39+DL39+FB39 -> 22835411 | AG39: =+BW39+DM39+FC39 -> 26087180 | AH39: =+BX39+DN39+FD39 -> 27281896 | AI39: =+BY39+DO39+FE39 -> 28319707 | AJ39: =+BZ39+DP39+FF39 -> 28988732 | ... AN39: =+CD39+DT39+FJ39 -> 26963019 | AO39: =+SUM(AC39:AN39) -> 3.1732375e+08 | AQ39: =+PMGR!AQ39+BP!AQ39 -> 11352503 | AR39: =+PMGR!AR39+BP!AR39 -> 17309654 | AS39: =+PMGR!AS39+BP!AS39 -> 12937654 | AT39: =+PMGR!AT39+BP!AT39 -> 11987553 | AU39: =+PMGR!AU39+BP!AU39 -> 9576385.7 | AV39: =+PMGR!AV39+BP!AV39 -> 13086560 | AW39: =+PMGR!AW39+BP!AW39 -> 14017596 | AX39: =+PMGR!AX39+BP!AX39 -> 18708917 | ... BB39: =+PMGR!BB39+BP!BB39 -> 17138140 | BC39: =+SUM(AQ39:BB39) -> 1.7686628e+08 | BD39: =N39 -> Cost of Goods Sold - Parts and Consumables | BE39: =+PMGR!BE39+BP!BE39 -> 11533610 | BF39: =+PMGR!BF39+BP!BF39 -> 11693239 | BG39: =+PMGR!BG39+BP!BG39 -> 20862355 | BH39: =+PMGR!BH39+BP!BH39 -> 16940072 | BI39: =+PMGR!BI39+BP!BI39 -> 19427897 | BJ39: =+PMGR!BJ39+BP!BJ39 -> 14141556 | BK39: =+PMGR!BK39+BP!BK39 -> 17315041 | BL39: =+PMGR!BL39+BP!BL39 -> 17521861 | ... BP39: =+PMGR!BP39+BP!BP39 -> 0 | BQ39: =+SUM(BE39:BP39) -> 1.6330556e+08 | BS39: =+PMGR!BS39+BP!BS39 -> 14594837 | BT39: =+PMGR!BT39+BP!BT39 -> 14327499 | BU39: =+PMGR!BU39+BP!BU39 -> 13268967 | BV39: =+PMGR!BV39+BP!BV39 -> 12457682 | BW39: =+PMGR!BW39+BP!BW39 -> 13728652 | BX39: =+PMGR!BX39+BP!BX39 -> 14210745 | BY39: =+PMGR!BY39+BP!BY39 -> 14558368 | BZ39: =+PMGR!BZ39+BP!BZ39 -> 15178043 | ... CD39: =+PMGR!CD39+BP!CD39 -> 14918542 | CE39: =+SUM(BS39:CD39) -> 1.6873984e+08 | CG39: =+PMGR!CG39+BP!CG39 -> 9200375.8 | CH39: =+PMGR!CH39+BP!CH39 -> 9691463.4 | CI39: =+PMGR!CI39+BP!CI39 -> 6746232.2 | CJ39: =+PMGR!CJ39+BP!CJ39 -> 4341506.4 | CK39: =+PMGR!CK39+BP!CK39 -> 10157550 | CL39: =+PMGR!CL39+BP!CL39 -> 10673225 | CM39: =+PMGR!CM39+BP!CM39 -> 7646976.5 | CN39: =+PMGR!CN39+BP!CN39 -> 9009526.2 | ... CR39: =+PMGR!CR39+BP!CR39 -> 8398445.4 | CS39: =+SUM(CG39:CR39) -> 99315200 | CT39: =BD39 -> Cost of Goods Sold - Parts and Consumables | CU39: =+PMGR!CU39+BP!CU39 -> 7269861.8 | CV39: =+PMGR!CV39+BP!CV39 -> 6019767.4 | CW39: =+PMGR!CW39+BP!CW39 -> 8025339.2 | CX39: =+PMGR!CX39+BP!CX39 -> 5623076.3 | CY39: =+PMGR!CY39+BP!CY39 -> 9378242.5 | CZ39: =+PMGR!CZ39+BP!CZ39 -> 6451811.6 | DA39: =+PMGR!DA39+BP!DA39 -> 8375285.1 | DB39: =+PMGR!DB39+BP!DB39 -> 8004114 | ... DF39: =+PMGR!DF39+BP!DF39 -> 0 | DG39: =+SUM(CU39:DF39) -> 74983945 | DI39: =+PMGR!DI39+BP!DI39 -> 9256747.5 | DJ39: =+PMGR!DJ39+BP!DJ39 -> 9198216.4 | DK39: =+PMGR!DK39+BP!DK39 -> 10289462 | DL39: =+PMGR!DL39+BP!DL39 -> 7461081.5 | DM39: =+PMGR!DM39+BP!DM39 -> 8886327.5 | DN39: =+PMGR!DN39+BP!DN39 -> 9598950.6 | DO39: =+PMGR!DO39+BP!DO39 -> 9855114.3 | DP39: =+PMGR!DP39+BP!DP39 -> 10049139 | ... DT39: =+PMGR!DT39+BP!DT39 -> 9405254.7 | DU39: =+SUM(DI39:DT39) -> 1.1055549e+08 | DW39: =+PMGR!DW39+BP!DW39 -> 0 | DX39: =+PMGR!DX39+BP!DX39 -> 0 | DY39: =+PMGR!DY39+BP!DY39 -> 0 | DZ39: =+PMGR!DZ39+BP!DZ39 -> 0 | EA39: =+PMGR!EA39+BP!EA39 -> 0 | EB39: =+PMGR!EB39+BP!EB39 -> 0 | EC39: =+PMGR!EC39+BP!EC39 -> 0 | ED39: =+PMGR!ED39+BP!ED39 -> 0 | ... EH39: =+PMGR!EH39+BP!EH39 -> 0 | EI39: =+SUM(DW39:EH39) -> 0 | EJ39: =CT39 -> Cost of Goods Sold - Parts and Consumables | EK39: =+PMGR!EK39+BP!EK39 -> 1556873.4 | EL39: =+PMGR!EL39+BP!EL39 -> 2770321.7 | EM39: =+PMGR!EM39+BP!EM39 -> 1908866.2 | EN39: =+PMGR!EN39+BP!EN39 -> 953597.53 | EO39: =+PMGR!EO39+BP!EO39 -> 2555166.6 | EP39: =+PMGR!EP39+BP!EP39 -> 3727178.8 | EQ39: =+PMGR!EQ39+BP!EQ39 -> 2905764.6 | ER39: =+PMGR!ER39+BP!ER39 -> 3377338.7 | ... EV39: =+PMGR!EV39+BP!EV39 -> 0 | EW39: =+SUM(EK39:EV39) -> 25405384 | EY39: =+PMGR!EY39+BP!EY39 -> 3124980 | EZ39: =+PMGR!EZ39+BP!EZ39 -> 2916648 | FA39: =+PMGR!FA39+BP!FA39 -> 3255187.5 | FB39: =+PMGR!FB39+BP!FB39 -> 2916648 | FC39: =+PMGR!FC39+BP!FC39 -> 3472200 | FD39: =+PMGR!FD39+BP!FD39 -> 3472200 | FE39: =+PMGR!FE39+BP!FE39 -> 3906225 | FF39: =+PMGR!FF39+BP!FF39 -> 3761550 | ... FJ39: =+PMGR!FJ39+BP!FJ39 -> 2639222.4 | FK39: =+SUM(EY39:FJ39) -> 38028427
A40: =+AQ40+CG40+DW40 -> 1005198 | B40: =+AR40+CH40+DX40 -> 984825.9 | C40: =+AS40+CI40+DY40 -> 987294 | D40: =+AT40+CJ40+DZ40 -> 983968 | E40: =+AU40+CK40+EA40 -> 1046181 | F40: =+AV40+CL40+EB40 -> 1096266 | G40: =+AW40+CM40+EC40 -> 1062341.7 | H40: =+AX40+CN40+ED40 -> 560937 | ... L40: =+BB40+CR40+EH40 -> 1105494 | M40: =+SUM(A40:L40) -> 12018424 | N40: Labour Cost | O40: =+BE40+CU40+EK40 -> 1275874 | P40: =+BF40+CV40+EL40 -> 1434676.6 | Q40: =+BG40+CW40+EM40 -> 1203479 | R40: =+BH40+CX40+EN40 -> 1424608 | S40: =+BI40+CY40+EO40 -> 1411556 | T40: =+BJ40+CZ40+EP40 -> 1345293 | U40: =+BK40+DA40+EQ40 -> 1384583 | V40: =+BL40+DB40+ER40 -> 1452550 | ... Z40: =+BP40+DF40+EV40 -> 0 | AA40: =+SUM(O40:Z40) -> 13774069 | AC40: =+BS40+DI40+EY40 -> 1742347.1 | AD40: =+BT40+DJ40+EZ40 -> 1742347.1 | AE40: =+BU40+DK40+FA40 -> 1742347.1 | AF40: =+BV40+DL40+FB40 -> 1742347.1 | AG40: =+BW40+DM40+FC40 -> 1742347.1 | AH40: =+BX40+DN40+FD40 -> 1742347.1 | AI40: =+BY40+DO40+FE40 -> 1742347.1 | AJ40: =+BZ40+DP40+FF40 -> 1742347.1 | ... AN40: =+CD40+DT40+FJ40 -> 1742347.1 | AO40: =+SUM(AC40:AN40) -> 20908165 | AQ40: =+PMGR!AQ40+BP!AQ40 -> 625660 | AR40: =+PMGR!AR40+BP!AR40 -> 605287.9 | AS40: =+PMGR!AS40+BP!AS40 -> 611294 | AT40: =+PMGR!AT40+BP!AT40 -> 626634 | AU40: =+PMGR!AU40+BP!AU40 -> 652245 | AV40: =+PMGR!AV40+BP!AV40 -> 696667 | AW40: =+PMGR!AW40+BP!AW40 -> 655842 | AX40: =+PMGR!AX40+BP!AX40 -> 368731 | ... BB40: =+PMGR!BB40+BP!BB40 -> 739783 | BC40: =+SUM(AQ40:BB40) -> 7686676.5 | BD40: =N40 -> Labour Cost | BE40: =+PMGR!BE40+BP!BE40 -> 702712 | BF40: =+PMGR!BF40+BP!BF40 -> 728100 | BG40: =+PMGR!BG40+BP!BG40 -> 665206 | BH40: =+PMGR!BH40+BP!BH40 -> 847800 | BI40: =+PMGR!BI40+BP!BI40 -> 821923 | BJ40: =+PMGR!BJ40+BP!BJ40 -> 772739 | BK40: =+PMGR!BK40+BP!BK40 -> 818146 | BL40: =+PMGR!BL40+BP!BL40 -> 816309 | ... BP40: =+PMGR!BP40+BP!BP40 -> 0 | BQ40: =+SUM(BE40:BP40) -> 7744554 | BS40: =+PMGR!BS40+BP!BS40 -> 880480.35 | BT40: =+PMGR!BT40+BP!BT40 -> 880480.35 | BU40: =+PMGR!BU40+BP!BU40 -> 880480.35 | BV40: =+PMGR!BV40+BP!BV40 -> 880480.35 | BW40: =+PMGR!BW40+BP!BW40 -> 880480.35 | BX40: =+PMGR!BX40+BP!BX40 -> 880480.35 | BY40: =+PMGR!BY40+BP!BY40 -> 880480.35 | BZ40: =+PMGR!BZ40+BP!BZ40 -> 880480.35 | ... CD40: =+PMGR!CD40+BP!CD40 -> 880480.35 | CE40: =+SUM(BS40:CD40) -> 10565764 | CG40: =+PMGR!CG40+BP!CG40 -> 379538 | CH40: =+PMGR!CH40+BP!CH40 -> 379538 | CI40: =+PMGR!CI40+BP!CI40 -> 376000 | CJ40: =+PMGR!CJ40+BP!CJ40 -> 357334 | CK40: =+PMGR!CK40+BP!CK40 -> 393936 | CL40: =+PMGR!CL40+BP!CL40 -> 399599 | CM40: =+PMGR!CM40+BP!CM40 -> 406499.68 | CN40: =+PMGR!CN40+BP!CN40 -> 192206 | ... CR40: =+PMGR!CR40+BP!CR40 -> 365711 | CS40: =+SUM(CG40:CR40) -> 4331747.3 | CT40: =BD40 -> Labour Cost | CU40: =+PMGR!CU40+BP!CU40 -> 402775 | CV40: =+PMGR!CV40+BP!CV40 -> 525576.57 | CW40: =+PMGR!CW40+BP!CW40 -> 389473 | CX40: =+PMGR!CX40+BP!CX40 -> 340808 | CY40: =+PMGR!CY40+BP!CY40 -> 353633 | CZ40: =+PMGR!CZ40+BP!CZ40 -> 336954 | DA40: =+PMGR!DA40+BP!DA40 -> 331223 | DB40: =+PMGR!DB40+BP!DB40 -> 409145 | ... DF40: =+PMGR!DF40+BP!DF40 -> 0 | DG40: =+SUM(CU40:DF40) -> 3969379.6 | DI40: =+PMGR!DI40+BP!DI40 -> 608902.57 | DJ40: =+PMGR!DJ40+BP!DJ40 -> 608902.57 | DK40: =+PMGR!DK40+BP!DK40 -> 608902.57 | DL40: =+PMGR!DL40+BP!DL40 -> 608902.57 | DM40: =+PMGR!DM40+BP!DM40 -> 608902.57 | DN40: =+PMGR!DN40+BP!DN40 -> 608902.57 | DO40: =+PMGR!DO40+BP!DO40 -> 608902.57 | DP40: =+PMGR!DP40+BP!DP40 -> 608902.57 | ... DT40: =+PMGR!DT40+BP!DT40 -> 608902.57 | DU40: =+SUM(DI40:DT40) -> 7306830.8 | DW40: =+PMGR!DW40+BP!DW40 -> 0 | DX40: =+PMGR!DX40+BP!DX40 -> 0 | DY40: =+PMGR!DY40+BP!DY40 -> 0 | DZ40: =+PMGR!DZ40+BP!DZ40 -> 0 | EA40: =+PMGR!EA40+BP!EA40 -> 0 | EB40: =+PMGR!EB40+BP!EB40 -> 0 | EC40: =+PMGR!EC40+BP!EC40 -> 0 | ED40: =+PMGR!ED40+BP!ED40 -> 0 | ... EH40: =+PMGR!EH40+BP!EH40 -> 0 | EI40: =+SUM(DW40:EH40) -> 0 | EJ40: =CT40 -> Labour Cost | EK40: =+PMGR!EK40+BP!EK40 -> 170387 | EL40: =+PMGR!EL40+BP!EL40 -> 181000 | EM40: =+PMGR!EM40+BP!EM40 -> 148800 | EN40: =+PMGR!EN40+BP!EN40 -> 236000 | EO40: =+PMGR!EO40+BP!EO40 -> 236000 | EP40: =+PMGR!EP40+BP!EP40 -> 235600 | EQ40: =+PMGR!EQ40+BP!EQ40 -> 235214 | ER40: =+PMGR!ER40+BP!ER40 -> 227096 | ... EV40: =+PMGR!EV40+BP!EV40 -> 0 | EW40: =+SUM(EK40:EV40) -> 2060135 | EY40: =+PMGR!EY40+BP!EY40 -> 252964.17 | EZ40: =+PMGR!EZ40+BP!EZ40 -> 252964.17 | FA40: =+PMGR!FA40+BP!FA40 -> 252964.17 | FB40: =+PMGR!FB40+BP!FB40 -> 252964.17 | FC40: =+PMGR!FC40+BP!FC40 -> 252964.17 | FD40: =+PMGR!FD40+BP!FD40 -> 252964.17 | FE40: =+PMGR!FE40+BP!FE40 -> 252964.17 | FF40: =+PMGR!FF40+BP!FF40 -> 252964.17 | ... FJ40: =+PMGR!FJ40+BP!FJ40 -> 252964.17 | FK40: =+SUM(EY40:FJ40) -> 3035570
A41: =+AQ41+CG41+DW41 -> 491269.84 | B41: =+AR41+CH41+DX41 -> 404842.92 | C41: =+AS41+CI41+DY41 -> 492906.05 | D41: =+AT41+CJ41+DZ41 -> 453301.81 | E41: =+AU41+CK41+EA41 -> 493756.29 | F41: =+AV41+CL41+EB41 -> 122309.68 | G41: =+AW41+CM41+EC41 -> 114582.71 | H41: =+AX41+CN41+ED41 -> 32205.46 | ... L41: =+BB41+CR41+EH41 -> 285207.95 | M41: =+SUM(A41:L41) -> 4496643.2 | N41: Consumables | O41: =+BE41+CU41+EK41 -> 0 | P41: =+BF41+CV41+EL41 -> 138851.18 | Q41: =+BG41+CW41+EM41 -> 242162.31 | R41: =+BH41+CX41+EN41 -> 479833.53 | S41: =+BI41+CY41+EO41 -> 792082.99 | T41: =+BJ41+CZ41+EP41 -> 245797.24 | U41: =+BK41+DA41+EQ41 -> 658964.84 | V41: =+BL41+DB41+ER41 -> 304732.1 | ... Z41: =+BP41+DF41+EV41 -> 0 | AA41: =+SUM(O41:Z41) -> 3862392.2 | AC41: =+BS41+DI41+EY41 -> 1142073.7 | AD41: =+BT41+DJ41+EZ41 -> 1118514.2 | AE41: =+BU41+DK41+FA41 -> 1134482.1 | AF41: =+BV41+DL41+FB41 -> 961140.5 | AG41: =+BW41+DM41+FC41 -> 1104109.7 | AH41: =+BX41+DN41+FD41 -> 1155860.2 | AI41: =+BY41+DO41+FE41 -> 1197062.2 | AJ41: =+BZ41+DP41+FF41 -> 1237843 | ... AN41: =+CD41+DT41+FJ41 -> 1136675 | AO41: =+SUM(AC41:AN41) -> 13435881 | AQ41: =+PMGR!AQ41+BP!AQ41 -> 465219.84 | AR41: =+PMGR!AR41+BP!AR41 -> 98953.62 | AS41: =+PMGR!AS41+BP!AS41 -> 317937.5 | AT41: =+PMGR!AT41+BP!AT41 -> 400644.28 | AU41: =+PMGR!AU41+BP!AU41 -> 470997.71 | AV41: =+PMGR!AV41+BP!AV41 -> 95041.98 | AW41: =+PMGR!AW41+BP!AW41 -> 95793.82 | AX41: =+PMGR!AX41+BP!AX41 -> 0 | ... BB41: =+PMGR!BB41+BP!BB41 -> 199675.35 | BC41: =+SUM(AQ41:BB41) -> 3471881.9 | BD41: =N41 -> Consumables | BE41: =+PMGR!BE41+BP!BE41 -> 0 | BF41: =+PMGR!BF41+BP!BF41 -> 27285.85 | BG41: =+PMGR!BG41+BP!BG41 -> 135615.72 | BH41: =+PMGR!BH41+BP!BH41 -> 18003.3 | BI41: =+PMGR!BI41+BP!BI41 -> 663892.07 | BJ41: =+PMGR!BJ41+BP!BJ41 -> 193886.4 | BK41: =+PMGR!BK41+BP!BK41 -> 320707.92 | BL41: =+PMGR!BL41+BP!BL41 -> 236026.15 | ... BP41: =+PMGR!BP41+BP!BP41 -> 0 | BQ41: =+SUM(BE41:BP41) -> 2141604.9 | BS41: =+PMGR!BS41+BP!BS41 -> 631976.46 | BT41: =+PMGR!BT41+BP!BT41 -> 616055.68 | BU41: =+PMGR!BU41+BP!BU41 -> 568293.32 | BV41: =+PMGR!BV41+BP!BV41 -> 537449.27 | BW41: =+PMGR!BW41+BP!BW41 -> 590587.76 | BX41: =+PMGR!BX41+BP!BX41 -> 610469.35 | BY41: =+PMGR!BY41+BP!BY41 -> 626038.5 | BZ41: =+PMGR!BZ41+BP!BZ41 -> 650884.94 | ... CD41: =+PMGR!CD41+BP!CD41 -> 642010.15 | CE41: =+SUM(BS41:CD41) -> 7257145.8 | CG41: =+PMGR!CG41+BP!CG41 -> 26050 | CH41: =+PMGR!CH41+BP!CH41 -> 305889.3 | CI41: =+PMGR!CI41+BP!CI41 -> 174968.55 | CJ41: =+PMGR!CJ41+BP!CJ41 -> 52657.53 | CK41: =+PMGR!CK41+BP!CK41 -> 22758.58 | CL41: =+PMGR!CL41+BP!CL41 -> 27267.7 | CM41: =+PMGR!CM41+BP!CM41 -> 18788.89 | CN41: =+PMGR!CN41+BP!CN41 -> 32205.46 | ... CR41: =+PMGR!CR41+BP!CR41 -> 85532.6 | CS41: =+SUM(CG41:CR41) -> 1024761.2 | CT41: =BD41 -> Consumables | CU41: =+PMGR!CU41+BP!CU41 -> 0 | CV41: =+PMGR!CV41+BP!CV41 -> 15051.415 | CW41: =+PMGR!CW41+BP!CW41 -> 89095.04 | CX41: =+PMGR!CX41+BP!CX41 -> 308658.13 | CY41: =+PMGR!CY41+BP!CY41 -> 54734.13 | CZ41: =+PMGR!CZ41+BP!CZ41 -> 1502 | DA41: =+PMGR!DA41+BP!DA41 -> 271113.25 | DB41: =+PMGR!DB41+BP!DB41 -> 15498.76 | ... DF41: =+PMGR!DF41+BP!DF41 -> 0 | DG41: =+SUM(CU41:DF41) -> 1071151.1 | DI41: =+PMGR!DI41+BP!DI41 -> 363325.22 | DJ41: =+PMGR!DJ41+BP!DJ41 -> 365471.29 | DK41: =+PMGR!DK41+BP!DK41 -> 413301.27 | DL41: =+PMGR!DL41+BP!DL41 -> 286704.03 | DM41: =+PMGR!DM41+BP!DM41 -> 350441.92 | DN41: =+PMGR!DN41+BP!DN41 -> 382310.86 | DO41: =+PMGR!DO41+BP!DO41 -> 387558.67 | DP41: =+PMGR!DP41+BP!DP41 -> 410288.08 | ... DT41: =+PMGR!DT41+BP!DT41 -> 370831.06 | DU41: =+SUM(DI41:DT41) -> 4392683.8 | DW41: =+PMGR!DW41+BP!DW41 -> 0 | DX41: =+PMGR!DX41+BP!DX41 -> 0 | DY41: =+PMGR!DY41+BP!DY41 -> 0 | DZ41: =+PMGR!DZ41+BP!DZ41 -> 0 | EA41: =+PMGR!EA41+BP!EA41 -> 0 | EB41: =+PMGR!EB41+BP!EB41 -> 0 | EC41: =+PMGR!EC41+BP!EC41 -> 0 | ED41: =+PMGR!ED41+BP!ED41 -> 0 | ... EH41: =+PMGR!EH41+BP!EH41 -> 0 | EI41: =+SUM(DW41:EH41) -> 0 | EJ41: =CT41 -> Consumables | EK41: =+PMGR!EK41+BP!EK41 -> 0 | EL41: =+PMGR!EL41+BP!EL41 -> 96513.92 | EM41: =+PMGR!EM41+BP!EM41 -> 17451.55 | EN41: =+PMGR!EN41+BP!EN41 -> 153172.1 | EO41: =+PMGR!EO41+BP!EO41 -> 73456.79 | EP41: =+PMGR!EP41+BP!EP41 -> 50408.84 | EQ41: =+PMGR!EQ41+BP!EQ41 -> 67143.67 | ER41: =+PMGR!ER41+BP!ER41 -> 53207.19 | ... EV41: =+PMGR!EV41+BP!EV41 -> 0 | EW41: =+SUM(EK41:EV41) -> 649636.2 | EY41: =+PMGR!EY41+BP!EY41 -> 146772 | EZ41: =+PMGR!EZ41+BP!EZ41 -> 136987.2 | FA41: =+PMGR!FA41+BP!FA41 -> 152887.5 | FB41: =+PMGR!FB41+BP!FB41 -> 136987.2 | FC41: =+PMGR!FC41+BP!FC41 -> 163080 | FD41: =+PMGR!FD41+BP!FD41 -> 163080 | FE41: =+PMGR!FE41+BP!FE41 -> 183465 | FF41: =+PMGR!FF41+BP!FF41 -> 176670 | ... FJ41: =+PMGR!FJ41+BP!FJ41 -> 123833.78 | FK41: =+SUM(EY41:FJ41) -> 1786051.6
A42: =+AQ42+CG42+DW42 -> 169026.33 | B42: =+AR42+CH42+DX42 -> 249396.17 | C42: =+AS42+CI42+DY42 -> 204767 | D42: =+AT42+CJ42+DZ42 -> 189346.52 | E42: =+AU42+CK42+EA42 -> 392214 | F42: =+AV42+CL42+EB42 -> 415042.72 | G42: =+AW42+CM42+EC42 -> 345516.54 | H42: =+AX42+CN42+ED42 -> 432794.32 | ... L42: =+BB42+CR42+EH42 -> 308198 | M42: =+SUM(A42:L42) -> 4551381.9 | N42: Direct Expenses [Sub contract other than Access] | O42: =+BE42+CU42+EK42 -> 897177.12 | P42: =+BF42+CV42+EL42 -> 798092.05 | Q42: =+BG42+CW42+EM42 -> 711300.35 | R42: =+BH42+CX42+EN42 -> 226447.33 | S42: =+BI42+CY42+EO42 -> 680487.14 | T42: =+BJ42+CZ42+EP42 -> 1114013.6 | U42: =+BK42+DA42+EQ42 -> 1257551.1 | V42: =+BL42+DB42+ER42 -> 927644.75 | ... Z42: =+BP42+DF42+EV42 -> 0 | AA42: =+SUM(O42:Z42) -> 7772504.3 | AC42: =+BS42+DI42+EY42 -> 279835.98 | AD42: =+BT42+DJ42+EZ42 -> 273611.7 | AE42: =+BU42+DK42+FA42 -> 275476.23 | AF42: =+BV42+DL42+FB42 -> 234488.66 | AG42: =+BW42+DM42+FC42 -> 264181.81 | AH42: =+BX42+DN42+FD42 -> 277424.03 | AI42: =+BY42+DO42+FE42 -> 286431.87 | AJ42: =+BZ42+DP42+FF42 -> 289657.85 | ... AN42: =+CD42+DT42+FJ42 -> 283698.57 | AO42: =+SUM(AC42:AN42) -> 3253248.4 | AQ42: =+PMGR!AQ42+BP!AQ42 -> 128324.33 | AR42: =+PMGR!AR42+BP!AR42 -> 206096.17 | AS42: =+PMGR!AS42+BP!AS42 -> 196367 | AT42: =+PMGR!AT42+BP!AT42 -> 169206.37 | AU42: =+PMGR!AU42+BP!AU42 -> 195124 | AV42: =+PMGR!AV42+BP!AV42 -> 288392.72 | AW42: =+PMGR!AW42+BP!AW42 -> 326663.54 | AX42: =+PMGR!AX42+BP!AX42 -> 424783.32 | ... BB42: =+PMGR!BB42+BP!BB42 -> 85070 | BC42: =+SUM(AQ42:BB42) -> 3568456.8 | BD42: =N42 -> Direct Expenses [Sub contract other than Access] | BE42: =+PMGR!BE42+BP!BE42 -> 684740.12 | BF42: =+PMGR!BF42+BP!BF42 -> 612105.05 | BG42: =+PMGR!BG42+BP!BG42 -> 572346.35 | BH42: =+PMGR!BH42+BP!BH42 -> 199283.33 | BI42: =+PMGR!BI42+BP!BI42 -> 577684.14 | BJ42: =+PMGR!BJ42+BP!BJ42 -> 846696.59 | BK42: =+PMGR!BK42+BP!BK42 -> 981329.1 | BL42: =+PMGR!BL42+BP!BL42 -> 770616.75 | ... BP42: =+PMGR!BP42+BP!BP42 -> 0 | BQ42: =+SUM(BE42:BP42) -> 6182494.3 | BS42: =+PMGR!BS42+BP!BS42 -> 158699.77 | BT42: =+PMGR!BT42+BP!BT42 -> 155353 | BU42: =+PMGR!BU42+BP!BU42 -> 145312.7 | BV42: =+PMGR!BV42+BP!BV42 -> 133932.37 | BW42: =+PMGR!BW42+BP!BW42 -> 148679.77 | BX42: =+PMGR!BX42+BP!BX42 -> 154449.11 | BY42: =+PMGR!BY42+BP!BY42 -> 157820.58 | BZ42: =+PMGR!BZ42+BP!BZ42 -> 165689.86 | ... CD42: =+PMGR!CD42+BP!CD42 -> 161415.86 | CE42: =+SUM(BS42:CD42) -> 1831869.8 | CG42: =+PMGR!CG42+BP!CG42 -> 40702 | CH42: =+PMGR!CH42+BP!CH42 -> 43300 | CI42: =+PMGR!CI42+BP!CI42 -> 8400 | CJ42: =+PMGR!CJ42+BP!CJ42 -> 20140.15 | CK42: =+PMGR!CK42+BP!CK42 -> 197090 | CL42: =+PMGR!CL42+BP!CL42 -> 126650 | CM42: =+PMGR!CM42+BP!CM42 -> 18853 | CN42: =+PMGR!CN42+BP!CN42 -> 8011 | ... CR42: =+PMGR!CR42+BP!CR42 -> 223128 | CS42: =+SUM(CG42:CR42) -> 982925.15 | CT42: =BD42 -> Direct Expenses [Sub contract other than Access] | CU42: =+PMGR!CU42+BP!CU42 -> 212437 | CV42: =+PMGR!CV42+BP!CV42 -> 119187 | CW42: =+PMGR!CW42+BP!CW42 -> 116404 | CX42: =+PMGR!CX42+BP!CX42 -> 27164 | CY42: =+PMGR!CY42+BP!CY42 -> 102803 | CZ42: =+PMGR!CZ42+BP!CZ42 -> 228937 | DA42: =+PMGR!DA42+BP!DA42 -> 213892 | DB42: =+PMGR!DB42+BP!DB42 -> 58548 | ... DF42: =+PMGR!DF42+BP!DF42 -> 0 | DG42: =+SUM(CU42:DF42) -> 1269190 | DI42: =+PMGR!DI42+BP!DI42 -> 121136.22 | DJ42: =+PMGR!DJ42+BP!DJ42 -> 118258.7 | DK42: =+PMGR!DK42+BP!DK42 -> 130163.53 | DL42: =+PMGR!DL42+BP!DL42 -> 100556.29 | DM42: =+PMGR!DM42+BP!DM42 -> 115502.04 | DN42: =+PMGR!DN42+BP!DN42 -> 122974.92 | DO42: =+PMGR!DO42+BP!DO42 -> 128611.29 | DP42: =+PMGR!DP42+BP!DP42 -> 123968 | ... DT42: =+PMGR!DT42+BP!DT42 -> 122282.71 | DU42: =+SUM(DI42:DT42) -> 1421378.6 | DW42: =+PMGR!DW42+BP!DW42 -> 0 | DX42: =+PMGR!DX42+BP!DX42 -> 0 | DY42: =+PMGR!DY42+BP!DY42 -> 0 | DZ42: =+PMGR!DZ42+BP!DZ42 -> 0 | EA42: =+PMGR!EA42+BP!EA42 -> 0 | EB42: =+PMGR!EB42+BP!EB42 -> 0 | EC42: =+PMGR!EC42+BP!EC42 -> 0 | ED42: =+PMGR!ED42+BP!ED42 -> 0 | ... EH42: =+PMGR!EH42+BP!EH42 -> 0 | EI42: =+SUM(DW42:EH42) -> 0 | EJ42: =CT42 -> Direct Expenses [Sub contract other than Access] | EK42: =+PMGR!EK42+BP!EK42 -> 0 | EL42: =+PMGR!EL42+BP!EL42 -> 66800 | EM42: =+PMGR!EM42+BP!EM42 -> 22550 | EN42: =+PMGR!EN42+BP!EN42 -> 0 | EO42: =+PMGR!EO42+BP!EO42 -> 0 | EP42: =+PMGR!EP42+BP!EP42 -> 38380 | EQ42: =+PMGR!EQ42+BP!EQ42 -> 62330 | ER42: =+PMGR!ER42+BP!ER42 -> 98480 | ... EV42: =+PMGR!EV42+BP!EV42 -> 0 | EW42: =+SUM(EK42:EV42) -> 320820 | EY42: =+PMGR!EY42+BP!EY42 -> 0 | EZ42: =+PMGR!EZ42+BP!EZ42 -> 0 | FA42: =+PMGR!FA42+BP!FA42 -> 0 | FB42: =+PMGR!FB42+BP!FB42 -> 0 | FC42: =+PMGR!FC42+BP!FC42 -> 0 | FD42: =+PMGR!FD42+BP!FD42 -> 0 | FE42: =+PMGR!FE42+BP!FE42 -> 0 | FF42: =+PMGR!FF42+BP!FF42 -> 0 | ... FJ42: =+PMGR!FJ42+BP!FJ42 -> 0 | FK42: =+SUM(EY42:FJ42) -> 0
A43: =+A29-A38 -> 10494076 | B43: =+B29-B38 -> 13050331 | C43: =+C29-C38 -> 8728471.9 | D43: =+D29-D38 -> 9080846.4 | E43: =+E29-E38 -> 8864440.9 | F43: =+F29-F38 -> 9114482.5 | G43: =+G29-G38 -> 10999438 | H43: =+H29-H38 -> 11135701 | ... M43: =+M29-M38 -> 1.2893111e+08 | N43: Gross Profit | O43: =+O29-O38 -> 11156145 | P43: =+P29-P38 -> 7354225.4 | Q43: =+Q29-Q38 -> 12420207 | R43: =+R29-R38 -> 11773336 | S43: =+S29-S38 -> 16402317 | T43: =+T29-T38 -> 10221542 | U43: =+U29-U38 -> 13631568 | V43: =+V29-V38 -> 13499460 | ... AA43: =+AA29-AA38 -> 1.2065067e+08 | AC43: =+AC29-AC38 -> 14028096 | AD43: =+AD29-AD38 -> 13593561 | AE43: =+AE29-AE38 -> 13909630 | AF43: =+AF29-AF38 -> 11482269 | AG43: =+AG29-AG38 -> 13434195 | AH43: =+AH29-AH38 -> 14141841 | AI43: =+AI29-AI38 -> 14754379 | AJ43: =+AJ29-AJ38 -> 15176690 | ... AO43: =+AO29-AO38 -> 1.6411632e+08 | AQ43: =+AQ29-AQ38 -> 5769668.7 | AR43: =+AR29-AR38 -> 8199974 | AS43: =+AS29-AS38 -> 5079578.2 | AT43: =+AT29-AT38 -> 6176699.2 | AU43: =+AU29-AU38 -> 3827848 | AV43: =+AV29-AV38 -> 5152938.1 | AW43: =+AW29-AW38 -> 6609222.6 | AX43: =+AX29-AX38 -> 6533472 | ... BC43: =+BC29-BC38 -> 74589683 | BD43: =N43 -> Gross Profit | BE43: =+BE29-BE38 -> 6198280.5 | BF43: =+BF29-BF38 -> 4500162 | BG43: =+BG29-BG38 -> 7712092 | BH43: =+BH29-BH38 -> 7655252.4 | BI43: =+BI29-BI38 -> 11126800 | BJ43: =+BJ29-BJ38 -> 5559530.8 | BK43: =+BK29-BK38 -> 8110211.7 | BL43: =+BL29-BL38 -> 7075446.2 | ... BQ43: =+BQ29-BQ38 -> 72240109 | BS43: =+BS29-BS38 -> 7404498.3 | BT43: =+BT29-BT38 -> 7133555.9 | BU43: =+BU29-BU38 -> 6577244.6 | BV43: =+BV29-BV38 -> 6059152.1 | BW43: =+BW29-BW38 -> 6794114.7 | BX43: =+BX29-BX38 -> 7077261.7 | BY43: =+BY29-BY38 -> 7261802.5 | BZ43: =+BZ29-BZ38 -> 7637041.4 | ... CE43: =+CE29-CE38 -> 83983897 | CG43: =+CG29-CG38 -> 4724407.8 | CH43: =+CH29-CH38 -> 4850356.8 | CI43: =+CI29-CI38 -> 3648893.8 | CJ43: =+CJ29-CJ38 -> 2904147.2 | CK43: =+CK29-CK38 -> 5036592.8 | CL43: =+CL29-CL38 -> 3961544.4 | CM43: =+CM29-CM38 -> 4390215.3 | CN43: =+CN29-CN38 -> 4602229.2 | ... CS43: =+CS29-CS38 -> 54341428 | CT43: =BD43 -> Gross Profit | CU43: =+CU29-CU38 -> 4099032.6 | CV43: =+CV29-CV38 -> 1868876.5 | CW43: =+CW29-CW38 -> 3772174.9 | CX43: =+CX29-CX38 -> 3131633.5 | CY43: =+CY29-CY38 -> 4407080.8 | CZ43: =+CZ29-CZ38 -> 3151531.2 | DA43: =+DA29-DA38 -> 4394691.9 | DB43: =+DB29-DB38 -> 4885719.8 | ... DG43: =+DG29-DG38 -> 36873220 | DI43: =+DI29-DI38 -> 4806758.1 | DJ43: =+DJ29-DJ38 -> 4781152.4 | DK43: =+DK29-DK38 -> 5429303.6 | DL43: =+DL29-DL38 -> 3744264.3 | DM43: =+DM29-DM38 -> 4593262.4 | DN43: =+DN29-DN38 -> 5017761.4 | DO43: =+DO29-DO38 -> 5158286.2 | DP43: =+DP29-DP38 -> 5301181.9 | ... DU43: =+DU29-DU38 -> 57477484 | DW43: =+DW29-DW38 -> 0 | DX43: =+DX29-DX38 -> 0 | DY43: =+DY29-DY38 -> 0 | DZ43: =+DZ29-DZ38 -> 0 | EA43: =+EA29-EA38 -> 0 | EB43: =+EB29-EB38 -> 0 | EC43: =+EC29-EC38 -> 0 | ED43: =+ED29-ED38 -> 0 | ... EI43: =+EI29-EI38 -> 0 | EJ43: =CT43 -> Gross Profit | EK43: =+EK29-EK38 -> 858831.67 | EL43: =+EL29-EL38 -> 985186.84 | EM43: =+EM29-EM38 -> 935939.81 | EN43: =+EN29-EN38 -> 986449.6 | EO43: =+EO29-EO38 -> 868436.2 | EP43: =+EP29-EP38 -> 1510480.1 | EQ43: =+EQ29-EQ38 -> 1126663.9 | ER43: =+ER29-ER38 -> 1538293.7 | ... EW43: =+EW29-EW38 -> 11537338 | EY43: =+EY29-EY38 -> 1816839.6 | EZ43: =+EZ29-EZ38 -> 1678852.7 | FA43: =+FA29-FA38 -> 1903081.5 | FB43: =+FB29-FB38 -> 1678852.7 | FC43: =+FC29-FC38 -> 2046817.8 | FD43: =+FD29-FD38 -> 2046817.8 | FE43: =+FE29-FE38 -> 2334290.6 | FF43: =+FF29-FF38 -> 2238466.3 | ... FK43: =+FK29-FK38 -> 22654939
A44: =+AQ44+CG44+DW44 -> 1159231.2 | B44: =+AR44+CH44+DX44 -> 1159231.2 | C44: =+AS44+CI44+DY44 -> 621838.19 | D44: =+AT44+CJ44+DZ44 -> 351279.09 | E44: =+AU44+CK44+EA44 -> 429792.69 | F44: =+AV44+CL44+EB44 -> 349775.44 | G44: =+AW44+CM44+EC44 -> 845907 | H44: =+AX44+CN44+ED44 -> 791776 | ... L44: =+BB44+CR44+EH44 -> 547440.78 | M44: =+SUM(A44:L44) -> 8296601.9 | N44: Monthly Target Incentive | O44: =+BE44+CU44+EK44 -> 0 | P44: =+BF44+CV44+EL44 -> 937661.97 | Q44: =+BG44+CW44+EM44 -> 632909.4 | R44: =+BH44+CX44+EN44 -> 467948.69 | S44: =+BI44+CY44+EO44 -> 682759.28 | T44: =+BJ44+CZ44+EP44 -> 1144469.3 | U44: =+BK44+DA44+EQ44 -> 949666.91 | V44: =+BL44+DB44+ER44 -> 912922 | ... Z44: =+BP44+DF44+EV44 -> 0 | AA44: =+SUM(O44:Z44) -> 7138999.2 | AC44: =+BS44+DI44+EY44 -> 796055.5 | AD44: =+BT44+DJ44+EZ44 -> 815711.2 | AE44: =+BU44+DK44+FA44 -> 845194.73 | AF44: =+BV44+DL44+FB44 -> 687949.2 | AG44: =+BW44+DM44+FC44 -> 825539.04 | AH44: =+BX44+DN44+FD44 -> 845194.73 | AI44: =+BY44+DO44+FE44 -> 913989.65 | AJ44: =+BZ44+DP44+FF44 -> 894333.96 | ... AN44: =+CD44+DT44+FJ44 -> 825539.04 | AO44: =+SUM(AC44:AN44) -> 9827845.7 | AQ44: =+PMGR!AQ44+BP!AQ44 -> 625984.83 | AR44: =+PMGR!AR44+BP!AR44 -> 625984.83 | AS44: =+PMGR!AS44+BP!AS44 -> 397976.44 | AT44: =+PMGR!AT44+BP!AT44 -> 210767.45 | AU44: =+PMGR!AU44+BP!AU44 -> 206300.49 | AV44: =+PMGR!AV44+BP!AV44 -> 195874.25 | AW44: =+PMGR!AW44+BP!AW44 -> 510555.82 | AX44: =+PMGR!AX44+BP!AX44 -> 491753.16 | ... BB44: =+PMGR!BB44+BP!BB44 -> 391722.47 | BC44: =+SUM(AQ44:BB44) -> 5042170.2 | BD44: =N44 -> Monthly Target Incentive | BE44: =+PMGR!BE44+BP!BE44 -> 0 | BF44: =+PMGR!BF44+BP!BF44 -> 427357.22 | BG44: =+PMGR!BG44+BP!BG44 -> 287840.23 | BH44: =+PMGR!BH44+BP!BH44 -> 267248.39 | BI44: =+PMGR!BI44+BP!BI44 -> 385113.73 | BJ44: =+PMGR!BJ44+BP!BJ44 -> 594691.02 | BK44: =+PMGR!BK44+BP!BK44 -> 535753.3 | BL44: =+PMGR!BL44+BP!BL44 -> 534430.56 | ... BP44: =+PMGR!BP44+BP!BP44 -> 0 | BQ44: =+SUM(BE44:BP44) -> 3867171.1 | BS44: =+PMGR!BS44+BP!BS44 -> 437830.53 | BT44: =+PMGR!BT44+BP!BT44 -> 448641.16 | BU44: =+PMGR!BU44+BP!BU44 -> 464857.1 | BV44: =+PMGR!BV44+BP!BV44 -> 378372.06 | BW44: =+PMGR!BW44+BP!BW44 -> 454046.47 | BX44: =+PMGR!BX44+BP!BX44 -> 464857.1 | BY44: =+PMGR!BY44+BP!BY44 -> 502694.31 | BZ44: =+PMGR!BZ44+BP!BZ44 -> 491883.68 | ... CD44: =+PMGR!CD44+BP!CD44 -> 454046.47 | CE44: =+SUM(BS44:CD44) -> 5405315.1 | CG44: =+PMGR!CG44+BP!CG44 -> 533246.33 | CH44: =+PMGR!CH44+BP!CH44 -> 533246.33 | CI44: =+PMGR!CI44+BP!CI44 -> 223861.75 | CJ44: =+PMGR!CJ44+BP!CJ44 -> 140511.64 | CK44: =+PMGR!CK44+BP!CK44 -> 223492.2 | CL44: =+PMGR!CL44+BP!CL44 -> 153901.19 | CM44: =+PMGR!CM44+BP!CM44 -> 335351.18 | CN44: =+PMGR!CN44+BP!CN44 -> 300022.84 | ... CR44: =+PMGR!CR44+BP!CR44 -> 155718.31 | CS44: =+SUM(CG44:CR44) -> 3254431.7 | CT44: =BD44 -> Monthly Target Incentive | CU44: =+PMGR!CU44+BP!CU44 -> 0 | CV44: =+PMGR!CV44+BP!CV44 -> 332462.98 | CW44: =+PMGR!CW44+BP!CW44 -> 279777.48 | CX44: =+PMGR!CX44+BP!CX44 -> 166159.92 | CY44: =+PMGR!CY44+BP!CY44 -> 214540.39 | CZ44: =+PMGR!CZ44+BP!CZ44 -> 380717.08 | DA44: =+PMGR!DA44+BP!DA44 -> 307764.46 | DB44: =+PMGR!DB44+BP!DB44 -> 274054.75 | ... DF44: =+PMGR!DF44+BP!DF44 -> 0 | DG44: =+SUM(CU44:DF44) -> 2364845.5 | DI44: =+PMGR!DI44+BP!DI44 -> 278619.43 | DJ44: =+PMGR!DJ44+BP!DJ44 -> 285498.92 | DK44: =+PMGR!DK44+BP!DK44 -> 295818.16 | DL44: =+PMGR!DL44+BP!DL44 -> 240782.22 | DM44: =+PMGR!DM44+BP!DM44 -> 288938.66 | DN44: =+PMGR!DN44+BP!DN44 -> 295818.16 | DO44: =+PMGR!DO44+BP!DO44 -> 319896.38 | DP44: =+PMGR!DP44+BP!DP44 -> 313016.89 | ... DT44: =+PMGR!DT44+BP!DT44 -> 288938.66 | DU44: =+SUM(DI44:DT44) -> 3439746 | DW44: =+PMGR!DW44+BP!DW44 -> 0 | DX44: =+PMGR!DX44+BP!DX44 -> 0 | DY44: =+PMGR!DY44+BP!DY44 -> 0 | DZ44: =+PMGR!DZ44+BP!DZ44 -> 0 | EA44: =+PMGR!EA44+BP!EA44 -> 0 | EB44: =+PMGR!EB44+BP!EB44 -> 0 | EC44: =+PMGR!EC44+BP!EC44 -> 0 | ED44: =+PMGR!ED44+BP!ED44 -> 0 | ... EH44: =+PMGR!EH44+BP!EH44 -> 0 | EI44: =+SUM(DW44:EH44) -> 0 | EJ44: =CT44 -> Monthly Target Incentive | EK44: =+PMGR!EK44+BP!EK44 -> 0 | EL44: =+PMGR!EL44+BP!EL44 -> 177841.76 | EM44: =+PMGR!EM44+BP!EM44 -> 65291.691 | EN44: =+PMGR!EN44+BP!EN44 -> 34540.382 | EO44: =+PMGR!EO44+BP!EO44 -> 83105.161 | EP44: =+PMGR!EP44+BP!EP44 -> 169061.18 | EQ44: =+PMGR!EQ44+BP!EQ44 -> 106149.14 | ER44: =+PMGR!ER44+BP!ER44 -> 104436.69 | ... EV44: =+PMGR!EV44+BP!EV44 -> 0 | EW44: =+SUM(EK44:EV44) -> 906982.63 | EY44: =+PMGR!EY44+BP!EY44 -> 79605.55 | EZ44: =+PMGR!EZ44+BP!EZ44 -> 81571.12 | FA44: =+PMGR!FA44+BP!FA44 -> 84519.473 | FB44: =+PMGR!FB44+BP!FB44 -> 68794.92 | FC44: =+PMGR!FC44+BP!FC44 -> 82553.904 | FD44: =+PMGR!FD44+BP!FD44 -> 84519.473 | FE44: =+PMGR!FE44+BP!FE44 -> 91398.965 | FF44: =+PMGR!FF44+BP!FF44 -> 89433.396 | ... FJ44: =+PMGR!FJ44+BP!FJ44 -> 82553.904 | FK44: =+SUM(EY44:FJ44) -> 982784.57
A45: =+AQ45+CG45+DW45 -> 0 | B45: =+AR45+CH45+DX45 -> 0 | C45: =+AS45+CI45+DY45 -> 2930221.9 | D45: =+AT45+CJ45+DZ45 -> 0 | E45: =+AU45+CK45+EA45 -> 0 | F45: =+AV45+CL45+EB45 -> 991070.36 | G45: =+AW45+CM45+EC45 -> 0 | H45: =+AX45+CN45+ED45 -> 0 | ... L45: =+BB45+CR45+EH45 -> 2152924.8 | M45: =+SUM(A45:L45) -> 7872343.8 | N45: Quarterly Target Incentive | O45: =+BE45+CU45+EK45 -> 0 | P45: =+BF45+CV45+EL45 -> 0 | Q45: =+BG45+CW45+EM45 -> 1381933.4 | R45: =+BH45+CX45+EN45 -> 0 | S45: =+BI45+CY45+EO45 -> 0 | T45: =+BJ45+CZ45+EP45 -> 2284394.3 | U45: =+BK45+DA45+EQ45 -> 0 | V45: =+BL45+DB45+ER45 -> 0 | ... Z45: =+BP45+DF45+EV45 -> 0 | AA45: =+SUM(O45:Z45) -> 6345299.9 | AC45: =+BS45+DI45+EY45 -> 0 | AD45: =+BT45+DJ45+EZ45 -> 0 | AE45: =+BU45+DK45+FA45 -> 1720272.5 | AF45: =+BV45+DL45+FB45 -> 0 | AG45: =+BW45+DM45+FC45 -> 0 | AH45: =+BX45+DN45+FD45 -> 1625446.6 | AI45: =+BY45+DO45+FE45 -> 0 | AJ45: =+BZ45+DP45+FF45 -> 0 | ... AN45: =+CD45+DT45+FJ45 -> 1691484.5 | AO45: =+SUM(AC45:AN45) -> 6800601 | AQ45: =+PMGR!AQ45+BP!AQ45 -> 0 | AR45: =+PMGR!AR45+BP!AR45 -> 0 | AS45: =+PMGR!AS45+BP!AS45 -> 1787435.3 | AT45: =+PMGR!AT45+BP!AT45 -> 0 | AU45: =+PMGR!AU45+BP!AU45 -> 0 | AV45: =+PMGR!AV45+BP!AV45 -> 594642.21 | AW45: =+PMGR!AW45+BP!AW45 -> 0 | AX45: =+PMGR!AX45+BP!AX45 -> 0 | ... BB45: =+PMGR!BB45+BP!BB45 -> 1291754.9 | BC45: =+SUM(AQ45:BB45) -> 4752708.5 | BD45: =N45 -> Quarterly Target Incentive | BE45: =+PMGR!BE45+BP!BE45 -> 0 | BF45: =+PMGR!BF45+BP!BF45 -> 0 | BG45: =+PMGR!BG45+BP!BG45 -> 690966.68 | BH45: =+PMGR!BH45+BP!BH45 -> 0 | BI45: =+PMGR!BI45+BP!BI45 -> 0 | BJ45: =+PMGR!BJ45+BP!BJ45 -> 1142197.2 | BK45: =+PMGR!BK45+BP!BK45 -> 0 | BL45: =+PMGR!BL45+BP!BL45 -> 0 | ... BP45: =+PMGR!BP45+BP!BP45 -> 0 | BQ45: =+SUM(BE45:BP45) -> 3172650 | BS45: =+PMGR!BS45+BP!BS45 -> 0 | BT45: =+PMGR!BT45+BP!BT45 -> 0 | BU45: =+PMGR!BU45+BP!BU45 -> 946149.86 | BV45: =+PMGR!BV45+BP!BV45 -> 0 | BW45: =+PMGR!BW45+BP!BW45 -> 0 | BX45: =+PMGR!BX45+BP!BX45 -> 893995.65 | BY45: =+PMGR!BY45+BP!BY45 -> 0 | BZ45: =+PMGR!BZ45+BP!BZ45 -> 0 | ... CD45: =+PMGR!CD45+BP!CD45 -> 930316.47 | CE45: =+SUM(BS45:CD45) -> 3740330.6 | CG45: =+PMGR!CG45+BP!CG45 -> 0 | CH45: =+PMGR!CH45+BP!CH45 -> 0 | CI45: =+PMGR!CI45+BP!CI45 -> 1142786.5 | CJ45: =+PMGR!CJ45+BP!CJ45 -> 0 | CK45: =+PMGR!CK45+BP!CK45 -> 0 | CL45: =+PMGR!CL45+BP!CL45 -> 396428.14 | CM45: =+PMGR!CM45+BP!CM45 -> 0 | CN45: =+PMGR!CN45+BP!CN45 -> 0 | ... CR45: =+PMGR!CR45+BP!CR45 -> 861169.93 | CS45: =+SUM(CG45:CR45) -> 3119635.3 | CT45: =BD45 -> Quarterly Target Incentive | CU45: =+PMGR!CU45+BP!CU45 -> 0 | CV45: =+PMGR!CV45+BP!CV45 -> 0 | CW45: =+PMGR!CW45+BP!CW45 -> 414580.01 | CX45: =+PMGR!CX45+BP!CX45 -> 0 | CY45: =+PMGR!CY45+BP!CY45 -> 0 | CZ45: =+PMGR!CZ45+BP!CZ45 -> 685318.29 | DA45: =+PMGR!DA45+BP!DA45 -> 0 | DB45: =+PMGR!DB45+BP!DB45 -> 0 | ... DF45: =+PMGR!DF45+BP!DF45 -> 0 | DG45: =+SUM(CU45:DF45) -> 1903590 | DI45: =+PMGR!DI45+BP!DI45 -> 0 | DJ45: =+PMGR!DJ45+BP!DJ45 -> 0 | DK45: =+PMGR!DK45+BP!DK45 -> 602095.37 | DL45: =+PMGR!DL45+BP!DL45 -> 0 | DM45: =+PMGR!DM45+BP!DM45 -> 0 | DN45: =+PMGR!DN45+BP!DN45 -> 568906.32 | DO45: =+PMGR!DO45+BP!DO45 -> 0 | DP45: =+PMGR!DP45+BP!DP45 -> 0 | ... DT45: =+PMGR!DT45+BP!DT45 -> 592019.57 | DU45: =+SUM(DI45:DT45) -> 2380210.4 | DW45: =+PMGR!DW45+BP!DW45 -> 0 | DX45: =+PMGR!DX45+BP!DX45 -> 0 | DY45: =+PMGR!DY45+BP!DY45 -> 0 | DZ45: =+PMGR!DZ45+BP!DZ45 -> 0 | EA45: =+PMGR!EA45+BP!EA45 -> 0 | EB45: =+PMGR!EB45+BP!EB45 -> 0 | EC45: =+PMGR!EC45+BP!EC45 -> 0 | ED45: =+PMGR!ED45+BP!ED45 -> 0 | ... EH45: =+PMGR!EH45+BP!EH45 -> 0 | EI45: =+SUM(DW45:EH45) -> 0 | EJ45: =CT45 -> Quarterly Target Incentive | EK45: =+PMGR!EK45+BP!EK45 -> 0 | EL45: =+PMGR!EL45+BP!EL45 -> 0 | EM45: =+PMGR!EM45+BP!EM45 -> 276386.67 | EN45: =+PMGR!EN45+BP!EN45 -> 0 | EO45: =+PMGR!EO45+BP!EO45 -> 0 | EP45: =+PMGR!EP45+BP!EP45 -> 456878.86 | EQ45: =+PMGR!EQ45+BP!EQ45 -> 0 | ER45: =+PMGR!ER45+BP!ER45 -> 0 | ... EV45: =+PMGR!EV45+BP!EV45 -> 0 | EW45: =+SUM(EK45:EV45) -> 1269060 | EY45: =+PMGR!EY45+BP!EY45 -> 0 | EZ45: =+PMGR!EZ45+BP!EZ45 -> 0 | FA45: =+PMGR!FA45+BP!FA45 -> 172027.25 | FB45: =+PMGR!FB45+BP!FB45 -> 0 | FC45: =+PMGR!FC45+BP!FC45 -> 0 | FD45: =+PMGR!FD45+BP!FD45 -> 162544.66 | FE45: =+PMGR!FE45+BP!FE45 -> 0 | FF45: =+PMGR!FF45+BP!FF45 -> 0 | ... FJ45: =+PMGR!FJ45+BP!FJ45 -> 169148.45 | FK45: =+SUM(EY45:FJ45) -> 680060.1
A46: =+AQ46+CG46+DW46 -> 0 | B46: =+AR46+CH46+DX46 -> 0 | C46: =+AS46+CI46+DY46 -> 1239680 | D46: =+AT46+CJ46+DZ46 -> 0 | E46: =+AU46+CK46+EA46 -> 0 | F46: =+AV46+CL46+EB46 -> 2116850 | G46: =+AW46+CM46+EC46 -> 0 | H46: =+AX46+CN46+ED46 -> 0 | ... L46: =+BB46+CR46+EH46 -> 2918137.5 | M46: =+SUM(A46:L46) -> 8297307.5 | N46: Qualitative Quarterly Incentive | O46: =+BE46+CU46+EK46 -> 0 | P46: =+BF46+CV46+EL46 -> 0 | Q46: =+BG46+CW46+EM46 -> 2298900 | R46: =+BH46+CX46+EN46 -> 0 | S46: =+BI46+CY46+EO46 -> 0 | T46: =+BJ46+CZ46+EP46 -> 1099650 | U46: =+BK46+DA46+EQ46 -> 0 | V46: =+BL46+DB46+ER46 -> 0 | ... Z46: =+BP46+DF46+EV46 -> 0 | AA46: =+SUM(O46:Z46) -> 6931650 | AC46: =+BS46+DI46+EY46 -> 0 | AD46: =+BT46+DJ46+EZ46 -> 0 | AE46: =+BU46+DK46+FA46 -> 5195082.1 | AF46: =+BV46+DL46+FB46 -> 0 | AG46: =+BW46+DM46+FC46 -> 0 | AH46: =+BX46+DN46+FD46 -> 4984081.3 | AI46: =+BY46+DO46+FE46 -> 0 | AJ46: =+BZ46+DP46+FF46 -> 0 | ... AN46: =+CD46+DT46+FJ46 -> 5184929.8 | AO46: =+SUM(AC46:AN46) -> 20900102 | AQ46: =+PMGR!AQ46+BP!AQ46 -> 0 | AR46: =+PMGR!AR46+BP!AR46 -> 0 | AS46: =+PMGR!AS46+BP!AS46 -> 756204.8 | AT46: =+PMGR!AT46+BP!AT46 -> 0 | AU46: =+PMGR!AU46+BP!AU46 -> 0 | AV46: =+PMGR!AV46+BP!AV46 -> 1270110 | AW46: =+PMGR!AW46+BP!AW46 -> 0 | AX46: =+PMGR!AX46+BP!AX46 -> 0 | ... BB46: =+PMGR!BB46+BP!BB46 -> 1750882.5 | BC46: =+SUM(AQ46:BB46) -> 4990781.3 | BD46: =N46 -> Qualitative Quarterly Incentive | BE46: =+PMGR!BE46+BP!BE46 -> 0 | BF46: =+PMGR!BF46+BP!BF46 -> 0 | BG46: =+PMGR!BG46+BP!BG46 -> 1149450 | BH46: =+PMGR!BH46+BP!BH46 -> 0 | BI46: =+PMGR!BI46+BP!BI46 -> 0 | BJ46: =+PMGR!BJ46+BP!BJ46 -> 549825 | BK46: =+PMGR!BK46+BP!BK46 -> 0 | BL46: =+PMGR!BL46+BP!BL46 -> 0 | ... BP46: =+PMGR!BP46+BP!BP46 -> 0 | BQ46: =+SUM(BE46:BP46) -> 3465825 | BS46: =+PMGR!BS46+BP!BS46 -> 0 | BT46: =+PMGR!BT46+BP!BT46 -> 0 | BU46: =+PMGR!BU46+BP!BU46 -> 2857295.2 | BV46: =+PMGR!BV46+BP!BV46 -> 0 | BW46: =+PMGR!BW46+BP!BW46 -> 0 | BX46: =+PMGR!BX46+BP!BX46 -> 2741244.7 | BY46: =+PMGR!BY46+BP!BY46 -> 0 | BZ46: =+PMGR!BZ46+BP!BZ46 -> 0 | ... CD46: =+PMGR!CD46+BP!CD46 -> 2851711.4 | CE46: =+SUM(BS46:CD46) -> 11495056 | CG46: =+PMGR!CG46+BP!CG46 -> 0 | CH46: =+PMGR!CH46+BP!CH46 -> 0 | CI46: =+PMGR!CI46+BP!CI46 -> 483475.2 | CJ46: =+PMGR!CJ46+BP!CJ46 -> 0 | CK46: =+PMGR!CK46+BP!CK46 -> 0 | CL46: =+PMGR!CL46+BP!CL46 -> 846740 | CM46: =+PMGR!CM46+BP!CM46 -> 0 | CN46: =+PMGR!CN46+BP!CN46 -> 0 | ... CR46: =+PMGR!CR46+BP!CR46 -> 1167255 | CS46: =+SUM(CG46:CR46) -> 3306526.2 | CT46: =BD46 -> Qualitative Quarterly Incentive | CU46: =+PMGR!CU46+BP!CU46 -> 0 | CV46: =+PMGR!CV46+BP!CV46 -> 0 | CW46: =+PMGR!CW46+BP!CW46 -> 689670 | CX46: =+PMGR!CX46+BP!CX46 -> 0 | CY46: =+PMGR!CY46+BP!CY46 -> 0 | CZ46: =+PMGR!CZ46+BP!CZ46 -> 329895 | DA46: =+PMGR!DA46+BP!DA46 -> 0 | DB46: =+PMGR!DB46+BP!DB46 -> 0 | ... DF46: =+PMGR!DF46+BP!DF46 -> 0 | DG46: =+SUM(CU46:DF46) -> 2079495 | DI46: =+PMGR!DI46+BP!DI46 -> 0 | DJ46: =+PMGR!DJ46+BP!DJ46 -> 0 | DK46: =+PMGR!DK46+BP!DK46 -> 1818278.7 | DL46: =+PMGR!DL46+BP!DL46 -> 0 | DM46: =+PMGR!DM46+BP!DM46 -> 0 | DN46: =+PMGR!DN46+BP!DN46 -> 1744428.5 | DO46: =+PMGR!DO46+BP!DO46 -> 0 | DP46: =+PMGR!DP46+BP!DP46 -> 0 | ... DT46: =+PMGR!DT46+BP!DT46 -> 1814725.4 | DU46: =+SUM(DI46:DT46) -> 7315035.7 | DW46: =+PMGR!DW46+BP!DW46 -> 0 | DX46: =+PMGR!DX46+BP!DX46 -> 0 | DY46: =+PMGR!DY46+BP!DY46 -> 0 | DZ46: =+PMGR!DZ46+BP!DZ46 -> 0 | EA46: =+PMGR!EA46+BP!EA46 -> 0 | EB46: =+PMGR!EB46+BP!EB46 -> 0 | EC46: =+PMGR!EC46+BP!EC46 -> 0 | ED46: =+PMGR!ED46+BP!ED46 -> 0 | ... EH46: =+PMGR!EH46+BP!EH46 -> 0 | EI46: =+SUM(DW46:EH46) -> 0 | EJ46: =CT46 -> Qualitative Quarterly Incentive | EK46: =+PMGR!EK46+BP!EK46 -> 0 | EL46: =+PMGR!EL46+BP!EL46 -> 0 | EM46: =+PMGR!EM46+BP!EM46 -> 459780 | EN46: =+PMGR!EN46+BP!EN46 -> 0 | EO46: =+PMGR!EO46+BP!EO46 -> 0 | EP46: =+PMGR!EP46+BP!EP46 -> 219930 | EQ46: =+PMGR!EQ46+BP!EQ46 -> 0 | ER46: =+PMGR!ER46+BP!ER46 -> 0 | ... EV46: =+PMGR!EV46+BP!EV46 -> 0 | EW46: =+SUM(EK46:EV46) -> 1386330 | EY46: =+PMGR!EY46+BP!EY46 -> 0 | EZ46: =+PMGR!EZ46+BP!EZ46 -> 0 | FA46: =+PMGR!FA46+BP!FA46 -> 519508.21 | FB46: =+PMGR!FB46+BP!FB46 -> 0 | FC46: =+PMGR!FC46+BP!FC46 -> 0 | FD46: =+PMGR!FD46+BP!FD46 -> 498408.13 | FE46: =+PMGR!FE46+BP!FE46 -> 0 | FF46: =+PMGR!FF46+BP!FF46 -> 0 | ... FJ46: =+PMGR!FJ46+BP!FJ46 -> 518492.98 | FK46: =+SUM(EY46:FJ46) -> 2090010.2
A47: =+A43+A44+A45+A46 -> 11653308 | B47: =+B43+B44+B45+B46 -> 14209562 | C47: =+C43+C44+C45+C46 -> 13520212 | D47: =+D43+D44+D45+D46 -> 9432125.5 | E47: =+E43+E44+E45+E46 -> 9294233.5 | F47: =+F43+F44+F45+F46 -> 12572178 | G47: =+G43+G44+G45+G46 -> 11845345 | H47: =+H43+H44+H45+H46 -> 11927477 | ... M47: =+M43+M44+M45+M46 -> 1.5339736e+08 | N47: Gross Profit 2 | O47: =+O43+O44+O45+O46 -> 11156145 | P47: =+P43+P44+P45+P46 -> 8291887.3 | Q47: =+Q43+Q44+Q45+Q46 -> 16733949 | R47: =+R43+R44+R45+R46 -> 12241284 | S47: =+S43+S44+S45+S46 -> 17085077 | T47: =+T43+T44+T45+T46 -> 14750056 | U47: =+U43+U44+U45+U46 -> 14581234 | V47: =+V43+V44+V45+V46 -> 14412382 | ... AA47: =+AA43+AA44+AA45+AA46 -> 1.4106662e+08 | AC47: =+AC43+AC44+AC45+AC46 -> 14824152 | AD47: =+AD43+AD44+AD45+AD46 -> 14409272 | AE47: =+AE43+AE44+AE45+AE46 -> 21670179 | AF47: =+AF43+AF44+AF45+AF46 -> 12170218 | AG47: =+AG43+AG44+AG45+AG46 -> 14259734 | AH47: =+AH43+AH44+AH45+AH46 -> 21596564 | AI47: =+AI43+AI44+AI45+AI46 -> 15668369 | AJ47: =+AJ43+AJ44+AJ45+AJ46 -> 16071024 | ... AO47: =+AO43+AO44+AO45+AO46 -> 2.0164487e+08 | AQ47: =+AQ43+AQ44+AQ45+AQ46 -> 6395653.5 | AR47: =+AR43+AR44+AR45+AR46 -> 8825958.8 | AS47: =+AS43+AS44+AS45+AS46 -> 8021194.7 | AT47: =+AT43+AT44+AT45+AT46 -> 6387466.7 | AU47: =+AU43+AU44+AU45+AU46 -> 4034148.5 | AV47: =+AV43+AV44+AV45+AV46 -> 7213564.5 | AW47: =+AW43+AW44+AW45+AW46 -> 7119778.4 | AX47: =+AX43+AX44+AX45+AX46 -> 7025225.2 | ... BC47: =+BC43+BC44+BC45+BC46 -> 89375343 | BD47: =N47 -> Gross Profit 2 | BE47: =+BE43+BE44+BE45+BE46 -> 6198280.5 | BF47: =+BF43+BF44+BF45+BF46 -> 4927519.3 | BG47: =+BG43+BG44+BG45+BG46 -> 9840348.9 | BH47: =+BH43+BH44+BH45+BH46 -> 7922500.8 | BI47: =+BI43+BI44+BI45+BI46 -> 11511914 | BJ47: =+BJ43+BJ44+BJ45+BJ46 -> 7846243.9 | BK47: =+BK43+BK44+BK45+BK46 -> 8645965 | BL47: =+BL43+BL44+BL45+BL46 -> 7609876.8 | ... BQ47: =+BQ43+BQ44+BQ45+BQ46 -> 82745755 | BS47: =+BS43+BS44+BS45+BS46 -> 7842328.8 | BT47: =+BT43+BT44+BT45+BT46 -> 7582197.1 | BU47: =+BU43+BU44+BU45+BU46 -> 10845547 | BV47: =+BV43+BV44+BV45+BV46 -> 6437524.1 | BW47: =+BW43+BW44+BW45+BW46 -> 7248161.1 | BX47: =+BX43+BX44+BX45+BX46 -> 11177359 | BY47: =+BY43+BY44+BY45+BY46 -> 7764496.8 | BZ47: =+BZ43+BZ44+BZ45+BZ46 -> 8128925.1 | ... CE47: =+CE43+CE44+CE45+CE46 -> 1.046246e+08 | CG47: =+CG43+CG44+CG45+CG46 -> 5257654.1 | CH47: =+CH43+CH44+CH45+CH46 -> 5383603.1 | CI47: =+CI43+CI44+CI45+CI46 -> 5499017.2 | CJ47: =+CJ43+CJ44+CJ45+CJ46 -> 3044658.8 | CK47: =+CK43+CK44+CK45+CK46 -> 5260085 | CL47: =+CL43+CL44+CL45+CL46 -> 5358613.8 | CM47: =+CM43+CM44+CM45+CM46 -> 4725566.5 | CN47: =+CN43+CN44+CN45+CN46 -> 4902252 | ... CS47: =+CS43+CS44+CS45+CS46 -> 64022021 | CT47: =BD47 -> Gross Profit 2 | CU47: =+CU43+CU44+CU45+CU46 -> 4099032.6 | CV47: =+CV43+CV44+CV45+CV46 -> 2201339.5 | CW47: =+CW43+CW44+CW45+CW46 -> 5156202.4 | CX47: =+CX43+CX44+CX45+CX46 -> 3297793.4 | CY47: =+CY43+CY44+CY45+CY46 -> 4621621.2 | CZ47: =+CZ43+CZ44+CZ45+CZ46 -> 4547461.6 | DA47: =+DA43+DA44+DA45+DA46 -> 4702456.4 | DB47: =+DB43+DB44+DB45+DB46 -> 5159774.5 | ... DG47: =+DG43+DG44+DG45+DG46 -> 43221151 | DI47: =+DI43+DI44+DI45+DI46 -> 5085377.6 | DJ47: =+DJ43+DJ44+DJ45+DJ46 -> 5066651.4 | DK47: =+DK43+DK44+DK45+DK46 -> 8145495.9 | DL47: =+DL43+DL44+DL45+DL46 -> 3985046.5 | DM47: =+DM43+DM44+DM45+DM46 -> 4882201.1 | DN47: =+DN43+DN44+DN45+DN46 -> 7626914.4 | DO47: =+DO43+DO44+DO45+DO46 -> 5478182.6 | DP47: =+DP43+DP44+DP45+DP46 -> 5614198.8 | ... DU47: =+DU43+DU44+DU45+DU46 -> 70612476 | DW47: =+DW43+DW44+DW45+DW46 -> 0 | DX47: =+DX43+DX44+DX45+DX46 -> 0 | DY47: =+DY43+DY44+DY45+DY46 -> 0 | DZ47: =+DZ43+DZ44+DZ45+DZ46 -> 0 | EA47: =+EA43+EA44+EA45+EA46 -> 0 | EB47: =+EB43+EB44+EB45+EB46 -> 0 | EC47: =+EC43+EC44+EC45+EC46 -> 0 | ED47: =+ED43+ED44+ED45+ED46 -> 0 | ... EI47: =+EI43+EI44+EI45+EI46 -> 0 | EJ47: =CT47 -> Gross Profit 2 | EK47: =+EK43+EK44+EK45+EK46 -> 858831.67 | EL47: =+EL43+EL44+EL45+EL46 -> 1163028.6 | EM47: =+EM43+EM44+EM45+EM46 -> 1737398.2 | EN47: =+EN43+EN44+EN45+EN46 -> 1020990 | EO47: =+EO43+EO44+EO45+EO46 -> 951541.36 | EP47: =+EP43+EP44+EP45+EP46 -> 2356350.2 | EQ47: =+EQ43+EQ44+EQ45+EQ46 -> 1232813.1 | ER47: =+ER43+ER44+ER45+ER46 -> 1642730.4 | ... EW47: =+EW43+EW44+EW45+EW46 -> 15099710 | EY47: =+EY43+EY44+EY45+EY46 -> 1896445.2 | EZ47: =+EZ43+EZ44+EZ45+EZ46 -> 1760423.8 | FA47: =+FA43+FA44+FA45+FA46 -> 2679136.4 | FB47: =+FB43+FB44+FB45+FB46 -> 1747647.6 | FC47: =+FC43+FC44+FC45+FC46 -> 2129371.7 | FD47: =+FD43+FD44+FD45+FD46 -> 2792290.1 | FE47: =+FE43+FE44+FE45+FE46 -> 2425689.5 | FF47: =+FF43+FF44+FF45+FF46 -> 2327899.7 | ... FK47: =+FK43+FK44+FK45+FK46 -> 26407794
BD48: =N48 -> 0 | CT48: =BD48 -> 0 | EJ48: =CT48 -> 0
N49: Accessceries and VAS | BD49: =N49 -> Accessceries and VAS | CT49: =BD49 -> Accessceries and VAS | EJ49: =CT49 -> Accessceries and VAS
A50: =+AQ50+CG50+DW50 -> 0 | B50: =+AR50+CH50+DX50 -> 0 | C50: =+AS50+CI50+DY50 -> 0 | D50: =+AT50+CJ50+DZ50 -> 0 | E50: =+AU50+CK50+EA50 -> 0 | F50: =+AV50+CL50+EB50 -> 0 | G50: =+AW50+CM50+EC50 -> 0 | H50: =+AX50+CN50+ED50 -> 0 | ... L50: =+BB50+CR50+EH50 -> 0 | M50: =+SUM(A50:L50) -> 0 | N50: No of Cars | O50: =+BE50+CU50+EK50 -> 0 | P50: =+BF50+CV50+EL50 -> 0 | Q50: =+BG50+CW50+EM50 -> 0 | R50: =+BH50+CX50+EN50 -> 0 | S50: =+BI50+CY50+EO50 -> 0 | T50: =+BJ50+CZ50+EP50 -> 0 | U50: =+BK50+DA50+EQ50 -> 0 | V50: =+BL50+DB50+ER50 -> 0 | ... Z50: =+BP50+DF50+EV50 -> 0 | AA50: =+SUM(O50:Z50) -> 0 | AC50: =+BS50+DI50+EY50 -> 0 | AD50: =+BT50+DJ50+EZ50 -> 0 | AE50: =+BU50+DK50+FA50 -> 0 | AF50: =+BV50+DL50+FB50 -> 0 | AG50: =+BW50+DM50+FC50 -> 0 | AH50: =+BX50+DN50+FD50 -> 0 | AI50: =+BY50+DO50+FE50 -> 0 | AJ50: =+BZ50+DP50+FF50 -> 0 | ... AN50: =+CD50+DT50+FJ50 -> 0 | AO50: =+SUM(AC50:AN50) -> 0 | AQ50: =+PMGR!AQ50+BP!AQ50 -> 0 | AR50: =+PMGR!AR50+BP!AR50 -> 0 | AS50: =+PMGR!AS50+BP!AS50 -> 0 | AT50: =+PMGR!AT50+BP!AT50 -> 0 | AU50: =+PMGR!AU50+BP!AU50 -> 0 | AV50: =+PMGR!AV50+BP!AV50 -> 0 | AW50: =+PMGR!AW50+BP!AW50 -> 0 | AX50: =+PMGR!AX50+BP!AX50 -> 0 | ... BB50: =+PMGR!BB50+BP!BB50 -> 0 | BC50: =+SUM(AQ50:BB50) -> 0 | BD50: =N50 -> No of Cars | BE50: =+PMGR!BE50+BP!BE50 -> 0 | BF50: =+PMGR!BF50+BP!BF50 -> 0 | BG50: =+PMGR!BG50+BP!BG50 -> 0 | BH50: =+PMGR!BH50+BP!BH50 -> 0 | BI50: =+PMGR!BI50+BP!BI50 -> 0 | BJ50: =+PMGR!BJ50+BP!BJ50 -> 0 | BK50: =+PMGR!BK50+BP!BK50 -> 0 | BL50: =+PMGR!BL50+BP!BL50 -> 0 | ... BP50: =+PMGR!BP50+BP!BP50 -> 0 | BQ50: =+SUM(BE50:BP50) -> 0 | BS50: =+PMGR!BS50+BP!BS50 -> 0 | BT50: =+PMGR!BT50+BP!BT50 -> 0 | BU50: =+PMGR!BU50+BP!BU50 -> 0 | BV50: =+PMGR!BV50+BP!BV50 -> 0 | BW50: =+PMGR!BW50+BP!BW50 -> 0 | BX50: =+PMGR!BX50+BP!BX50 -> 0 | BY50: =+PMGR!BY50+BP!BY50 -> 0 | BZ50: =+PMGR!BZ50+BP!BZ50 -> 0 | ... CD50: =+PMGR!CD50+BP!CD50 -> 0 | CE50: =+SUM(BS50:CD50) -> 0 | CG50: =+PMGR!CG50+BP!CG50 -> 0 | CH50: =+PMGR!CH50+BP!CH50 -> 0 | CI50: =+PMGR!CI50+BP!CI50 -> 0 | CJ50: =+PMGR!CJ50+BP!CJ50 -> 0 | CK50: =+PMGR!CK50+BP!CK50 -> 0 | CL50: =+PMGR!CL50+BP!CL50 -> 0 | CM50: =+PMGR!CM50+BP!CM50 -> 0 | CN50: =+PMGR!CN50+BP!CN50 -> 0 | ... CR50: =+PMGR!CR50+BP!CR50 -> 0 | CS50: =+SUM(CG50:CR50) -> 0 | CT50: =BD50 -> No of Cars | CU50: =+PMGR!CU50+BP!CU50 -> 0 | CV50: =+PMGR!CV50+BP!CV50 -> 0 | CW50: =+PMGR!CW50+BP!CW50 -> 0 | CX50: =+PMGR!CX50+BP!CX50 -> 0 | CY50: =+PMGR!CY50+BP!CY50 -> 0 | CZ50: =+PMGR!CZ50+BP!CZ50 -> 0 | DA50: =+PMGR!DA50+BP!DA50 -> 0 | DB50: =+PMGR!DB50+BP!DB50 -> 0 | ... DF50: =+PMGR!DF50+BP!DF50 -> 0 | DG50: =+SUM(CU50:DF50) -> 0 | DI50: =+PMGR!DI50+BP!DI50 -> 0 | DJ50: =+PMGR!DJ50+BP!DJ50 -> 0 | DK50: =+PMGR!DK50+BP!DK50 -> 0 | DL50: =+PMGR!DL50+BP!DL50 -> 0 | DM50: =+PMGR!DM50+BP!DM50 -> 0 | DN50: =+PMGR!DN50+BP!DN50 -> 0 | DO50: =+PMGR!DO50+BP!DO50 -> 0 | DP50: =+PMGR!DP50+BP!DP50 -> 0 | ... DT50: =+PMGR!DT50+BP!DT50 -> 0 | DU50: =+SUM(DI50:DT50) -> 0 | DW50: =+PMGR!DW50+BP!DW50 -> 0 | DX50: =+PMGR!DX50+BP!DX50 -> 0 | DY50: =+PMGR!DY50+BP!DY50 -> 0 | DZ50: =+PMGR!DZ50+BP!DZ50 -> 0 | EA50: =+PMGR!EA50+BP!EA50 -> 0 | EB50: =+PMGR!EB50+BP!EB50 -> 0 | EC50: =+PMGR!EC50+BP!EC50 -> 0 | ED50: =+PMGR!ED50+BP!ED50 -> 0 | ... EH50: =+PMGR!EH50+BP!EH50 -> 0 | EI50: =+SUM(DW50:EH50) -> 0 | EJ50: =CT50 -> No of Cars | EK50: =+PMGR!EK50+BP!EK50 -> 0 | EL50: =+PMGR!EL50+BP!EL50 -> 0 | EM50: =+PMGR!EM50+BP!EM50 -> 0 | EN50: =+PMGR!EN50+BP!EN50 -> 0 | EO50: =+PMGR!EO50+BP!EO50 -> 0 | EP50: =+PMGR!EP50+BP!EP50 -> 0 | EQ50: =+PMGR!EQ50+BP!EQ50 -> 0 | ER50: =+PMGR!ER50+BP!ER50 -> 0 | ... EV50: =+PMGR!EV50+BP!EV50 -> 0 | EW50: =+SUM(EK50:EV50) -> 0 | EY50: =+PMGR!EY50+BP!EY50 -> 0 | EZ50: =+PMGR!EZ50+BP!EZ50 -> 0 | FA50: =+PMGR!FA50+BP!FA50 -> 0 | FB50: =+PMGR!FB50+BP!FB50 -> 0 | FC50: =+PMGR!FC50+BP!FC50 -> 0 | FD50: =+PMGR!FD50+BP!FD50 -> 0 | FE50: =+PMGR!FE50+BP!FE50 -> 0 | FF50: =+PMGR!FF50+BP!FF50 -> 0 | ... FJ50: =+PMGR!FJ50+BP!FJ50 -> 0 | FK50: =+SUM(EY50:FJ50) -> 0
A51: =+AQ51+CG51+DW51 -> 0 | B51: =+AR51+CH51+DX51 -> 0 | C51: =+AS51+CI51+DY51 -> 0 | D51: =+AT51+CJ51+DZ51 -> 0 | E51: =+AU51+CK51+EA51 -> 0 | F51: =+AV51+CL51+EB51 -> 0 | G51: =+AW51+CM51+EC51 -> 0 | H51: =+AX51+CN51+ED51 -> 0 | ... L51: =+BB51+CR51+EH51 -> 0 | M51: =+SUM(A51:L51) -> 0 | N51: Sale Revenue Accsories & Boutiques | O51: =+BE51+CU51+EK51 -> 0 | P51: =+BF51+CV51+EL51 -> 0 | Q51: =+BG51+CW51+EM51 -> 0 | R51: =+BH51+CX51+EN51 -> 0 | S51: =+BI51+CY51+EO51 -> 0 | T51: =+BJ51+CZ51+EP51 -> 0 | U51: =+BK51+DA51+EQ51 -> 0 | V51: =+BL51+DB51+ER51 -> 0 | ... Z51: =+BP51+DF51+EV51 -> 0 | AA51: =+SUM(O51:Z51) -> 0 | AC51: =+BS51+DI51+EY51 -> 0 | AD51: =+BT51+DJ51+EZ51 -> 0 | AE51: =+BU51+DK51+FA51 -> 0 | AF51: =+BV51+DL51+FB51 -> 0 | AG51: =+BW51+DM51+FC51 -> 0 | AH51: =+BX51+DN51+FD51 -> 0 | AI51: =+BY51+DO51+FE51 -> 0 | AJ51: =+BZ51+DP51+FF51 -> 0 | ... AN51: =+CD51+DT51+FJ51 -> 0 | AO51: =+SUM(AC51:AN51) -> 0 | AQ51: =+PMGR!AQ51+BP!AQ51 -> 0 | AR51: =+PMGR!AR51+BP!AR51 -> 0 | AS51: =+PMGR!AS51+BP!AS51 -> 0 | AT51: =+PMGR!AT51+BP!AT51 -> 0 | AU51: =+PMGR!AU51+BP!AU51 -> 0 | AV51: =+PMGR!AV51+BP!AV51 -> 0 | AW51: =+PMGR!AW51+BP!AW51 -> 0 | AX51: =+PMGR!AX51+BP!AX51 -> 0 | ... BB51: =+PMGR!BB51+BP!BB51 -> 0 | BC51: =+SUM(AQ51:BB51) -> 0 | BD51: =N51 -> Sale Revenue Accsories & Boutiques | BE51: =+PMGR!BE51+BP!BE51 -> 0 | BF51: =+PMGR!BF51+BP!BF51 -> 0 | BG51: =+PMGR!BG51+BP!BG51 -> 0 | BH51: =+PMGR!BH51+BP!BH51 -> 0 | BI51: =+PMGR!BI51+BP!BI51 -> 0 | BJ51: =+PMGR!BJ51+BP!BJ51 -> 0 | BK51: =+PMGR!BK51+BP!BK51 -> 0 | BL51: =+PMGR!BL51+BP!BL51 -> 0 | ... BP51: =+PMGR!BP51+BP!BP51 -> 0 | BQ51: =+SUM(BE51:BP51) -> 0 | BS51: =+PMGR!BS51+BP!BS51 -> 0 | BT51: =+PMGR!BT51+BP!BT51 -> 0 | BU51: =+PMGR!BU51+BP!BU51 -> 0 | BV51: =+PMGR!BV51+BP!BV51 -> 0 | BW51: =+PMGR!BW51+BP!BW51 -> 0 | BX51: =+PMGR!BX51+BP!BX51 -> 0 | BY51: =+PMGR!BY51+BP!BY51 -> 0 | BZ51: =+PMGR!BZ51+BP!BZ51 -> 0 | ... CD51: =+PMGR!CD51+BP!CD51 -> 0 | CE51: =+SUM(BS51:CD51) -> 0 | CG51: =+PMGR!CG51+BP!CG51 -> 0 | CH51: =+PMGR!CH51+BP!CH51 -> 0 | CI51: =+PMGR!CI51+BP!CI51 -> 0 | CJ51: =+PMGR!CJ51+BP!CJ51 -> 0 | CK51: =+PMGR!CK51+BP!CK51 -> 0 | CL51: =+PMGR!CL51+BP!CL51 -> 0 | CM51: =+PMGR!CM51+BP!CM51 -> 0 | CN51: =+PMGR!CN51+BP!CN51 -> 0 | ... CR51: =+PMGR!CR51+BP!CR51 -> 0 | CS51: =+SUM(CG51:CR51) -> 0 | CT51: =BD51 -> Sale Revenue Accsories & Boutiques | CU51: =+PMGR!CU51+BP!CU51 -> 0 | CV51: =+PMGR!CV51+BP!CV51 -> 0 | CW51: =+PMGR!CW51+BP!CW51 -> 0 | CX51: =+PMGR!CX51+BP!CX51 -> 0 | CY51: =+PMGR!CY51+BP!CY51 -> 0 | CZ51: =+PMGR!CZ51+BP!CZ51 -> 0 | DA51: =+PMGR!DA51+BP!DA51 -> 0 | DB51: =+PMGR!DB51+BP!DB51 -> 0 | ... DF51: =+PMGR!DF51+BP!DF51 -> 0 | DG51: =+SUM(CU51:DF51) -> 0 | DI51: =+PMGR!DI51+BP!DI51 -> 0 | DJ51: =+PMGR!DJ51+BP!DJ51 -> 0 | DK51: =+PMGR!DK51+BP!DK51 -> 0 | DL51: =+PMGR!DL51+BP!DL51 -> 0 | DM51: =+PMGR!DM51+BP!DM51 -> 0 | DN51: =+PMGR!DN51+BP!DN51 -> 0 | DO51: =+PMGR!DO51+BP!DO51 -> 0 | DP51: =+PMGR!DP51+BP!DP51 -> 0 | ... DT51: =+PMGR!DT51+BP!DT51 -> 0 | DU51: =+SUM(DI51:DT51) -> 0 | DW51: =+PMGR!DW51+BP!DW51 -> 0 | DX51: =+PMGR!DX51+BP!DX51 -> 0 | DY51: =+PMGR!DY51+BP!DY51 -> 0 | DZ51: =+PMGR!DZ51+BP!DZ51 -> 0 | EA51: =+PMGR!EA51+BP!EA51 -> 0 | EB51: =+PMGR!EB51+BP!EB51 -> 0 | EC51: =+PMGR!EC51+BP!EC51 -> 0 | ED51: =+PMGR!ED51+BP!ED51 -> 0 | ... EH51: =+PMGR!EH51+BP!EH51 -> 0 | EI51: =+SUM(DW51:EH51) -> 0 | EJ51: =CT51 -> Sale Revenue Accsories & Boutiques | EK51: =+PMGR!EK51+BP!EK51 -> 0 | EL51: =+PMGR!EL51+BP!EL51 -> 0 | EM51: =+PMGR!EM51+BP!EM51 -> 0 | EN51: =+PMGR!EN51+BP!EN51 -> 0 | EO51: =+PMGR!EO51+BP!EO51 -> 0 | EP51: =+PMGR!EP51+BP!EP51 -> 0 | EQ51: =+PMGR!EQ51+BP!EQ51 -> 0 | ER51: =+PMGR!ER51+BP!ER51 -> 0 | ... EV51: =+PMGR!EV51+BP!EV51 -> 0 | EW51: =+SUM(EK51:EV51) -> 0 | EY51: =+PMGR!EY51+BP!EY51 -> 0 | EZ51: =+PMGR!EZ51+BP!EZ51 -> 0 | FA51: =+PMGR!FA51+BP!FA51 -> 0 | FB51: =+PMGR!FB51+BP!FB51 -> 0 | FC51: =+PMGR!FC51+BP!FC51 -> 0 | FD51: =+PMGR!FD51+BP!FD51 -> 0 | FE51: =+PMGR!FE51+BP!FE51 -> 0 | FF51: =+PMGR!FF51+BP!FF51 -> 0 | ... FJ51: =+PMGR!FJ51+BP!FJ51 -> 0 | FK51: =+SUM(EY51:FJ51) -> 0
A52: =+AQ52+CG52+DW52 -> 0 | B52: =+AR52+CH52+DX52 -> 0 | C52: =+AS52+CI52+DY52 -> 0 | D52: =+AT52+CJ52+DZ52 -> 0 | E52: =+AU52+CK52+EA52 -> 0 | F52: =+AV52+CL52+EB52 -> 0 | G52: =+AW52+CM52+EC52 -> 0 | H52: =+AX52+CN52+ED52 -> 0 | ... L52: =+BB52+CR52+EH52 -> 0 | M52: =+SUM(A52:L52) -> 0 | N52: Internal Sales | O52: =+BE52+CU52+EK52 -> 0 | P52: =+BF52+CV52+EL52 -> 0 | Q52: =+BG52+CW52+EM52 -> 0 | R52: =+BH52+CX52+EN52 -> 0 | S52: =+BI52+CY52+EO52 -> 0 | T52: =+BJ52+CZ52+EP52 -> 0 | U52: =+BK52+DA52+EQ52 -> 0 | V52: =+BL52+DB52+ER52 -> 0 | ... Z52: =+BP52+DF52+EV52 -> 0 | AA52: =+SUM(O52:Z52) -> 0 | AC52: =+BS52+DI52+EY52 -> 0 | AD52: =+BT52+DJ52+EZ52 -> 0 | AE52: =+BU52+DK52+FA52 -> 0 | AF52: =+BV52+DL52+FB52 -> 0 | AG52: =+BW52+DM52+FC52 -> 0 | AH52: =+BX52+DN52+FD52 -> 0 | AI52: =+BY52+DO52+FE52 -> 0 | AJ52: =+BZ52+DP52+FF52 -> 0 | ... AN52: =+CD52+DT52+FJ52 -> 0 | AO52: =+SUM(AC52:AN52) -> 0 | AQ52: =+PMGR!AQ52+BP!AQ52 -> 0 | AR52: =+PMGR!AR52+BP!AR52 -> 0 | AS52: =+PMGR!AS52+BP!AS52 -> 0 | AT52: =+PMGR!AT52+BP!AT52 -> 0 | AU52: =+PMGR!AU52+BP!AU52 -> 0 | AV52: =+PMGR!AV52+BP!AV52 -> 0 | AW52: =+PMGR!AW52+BP!AW52 -> 0 | AX52: =+PMGR!AX52+BP!AX52 -> 0 | ... BB52: =+PMGR!BB52+BP!BB52 -> 0 | BC52: =+SUM(AQ52:BB52) -> 0 | BD52: =N52 -> Internal Sales | BE52: =+PMGR!BE52+BP!BE52 -> 0 | BF52: =+PMGR!BF52+BP!BF52 -> 0 | BG52: =+PMGR!BG52+BP!BG52 -> 0 | BH52: =+PMGR!BH52+BP!BH52 -> 0 | BI52: =+PMGR!BI52+BP!BI52 -> 0 | BJ52: =+PMGR!BJ52+BP!BJ52 -> 0 | BK52: =+PMGR!BK52+BP!BK52 -> 0 | BL52: =+PMGR!BL52+BP!BL52 -> 0 | ... BP52: =+PMGR!BP52+BP!BP52 -> 0 | BQ52: =+SUM(BE52:BP52) -> 0 | BS52: =+PMGR!BS52+BP!BS52 -> 0 | BT52: =+PMGR!BT52+BP!BT52 -> 0 | BU52: =+PMGR!BU52+BP!BU52 -> 0 | BV52: =+PMGR!BV52+BP!BV52 -> 0 | BW52: =+PMGR!BW52+BP!BW52 -> 0 | BX52: =+PMGR!BX52+BP!BX52 -> 0 | BY52: =+PMGR!BY52+BP!BY52 -> 0 | BZ52: =+PMGR!BZ52+BP!BZ52 -> 0 | ... CD52: =+PMGR!CD52+BP!CD52 -> 0 | CE52: =+SUM(BS52:CD52) -> 0 | CG52: =+PMGR!CG52+BP!CG52 -> 0 | CH52: =+PMGR!CH52+BP!CH52 -> 0 | CI52: =+PMGR!CI52+BP!CI52 -> 0 | CJ52: =+PMGR!CJ52+BP!CJ52 -> 0 | CK52: =+PMGR!CK52+BP!CK52 -> 0 | CL52: =+PMGR!CL52+BP!CL52 -> 0 | CM52: =+PMGR!CM52+BP!CM52 -> 0 | CN52: =+PMGR!CN52+BP!CN52 -> 0 | ... CR52: =+PMGR!CR52+BP!CR52 -> 0 | CS52: =+SUM(CG52:CR52) -> 0 | CT52: =BD52 -> Internal Sales | CU52: =+PMGR!CU52+BP!CU52 -> 0 | CV52: =+PMGR!CV52+BP!CV52 -> 0 | CW52: =+PMGR!CW52+BP!CW52 -> 0 | CX52: =+PMGR!CX52+BP!CX52 -> 0 | CY52: =+PMGR!CY52+BP!CY52 -> 0 | CZ52: =+PMGR!CZ52+BP!CZ52 -> 0 | DA52: =+PMGR!DA52+BP!DA52 -> 0 | DB52: =+PMGR!DB52+BP!DB52 -> 0 | ... DF52: =+PMGR!DF52+BP!DF52 -> 0 | DG52: =+SUM(CU52:DF52) -> 0 | DI52: =+PMGR!DI52+BP!DI52 -> 0 | DJ52: =+PMGR!DJ52+BP!DJ52 -> 0 | DK52: =+PMGR!DK52+BP!DK52 -> 0 | DL52: =+PMGR!DL52+BP!DL52 -> 0 | DM52: =+PMGR!DM52+BP!DM52 -> 0 | DN52: =+PMGR!DN52+BP!DN52 -> 0 | DO52: =+PMGR!DO52+BP!DO52 -> 0 | DP52: =+PMGR!DP52+BP!DP52 -> 0 | ... DT52: =+PMGR!DT52+BP!DT52 -> 0 | DU52: =+SUM(DI52:DT52) -> 0 | DW52: =+PMGR!DW52+BP!DW52 -> 0 | DX52: =+PMGR!DX52+BP!DX52 -> 0 | DY52: =+PMGR!DY52+BP!DY52 -> 0 | DZ52: =+PMGR!DZ52+BP!DZ52 -> 0 | EA52: =+PMGR!EA52+BP!EA52 -> 0 | EB52: =+PMGR!EB52+BP!EB52 -> 0 | EC52: =+PMGR!EC52+BP!EC52 -> 0 | ED52: =+PMGR!ED52+BP!ED52 -> 0 | ... EH52: =+PMGR!EH52+BP!EH52 -> 0 | EI52: =+SUM(DW52:EH52) -> 0 | EJ52: =CT52 -> Internal Sales | EK52: =+PMGR!EK52+BP!EK52 -> 0 | EL52: =+PMGR!EL52+BP!EL52 -> 0 | EM52: =+PMGR!EM52+BP!EM52 -> 0 | EN52: =+PMGR!EN52+BP!EN52 -> 0 | EO52: =+PMGR!EO52+BP!EO52 -> 0 | EP52: =+PMGR!EP52+BP!EP52 -> 0 | EQ52: =+PMGR!EQ52+BP!EQ52 -> 0 | ER52: =+PMGR!ER52+BP!ER52 -> 0 | ... EV52: =+PMGR!EV52+BP!EV52 -> 0 | EW52: =+SUM(EK52:EV52) -> 0 | EY52: =+PMGR!EY52+BP!EY52 -> 0 | EZ52: =+PMGR!EZ52+BP!EZ52 -> 0 | FA52: =+PMGR!FA52+BP!FA52 -> 0 | FB52: =+PMGR!FB52+BP!FB52 -> 0 | FC52: =+PMGR!FC52+BP!FC52 -> 0 | FD52: =+PMGR!FD52+BP!FD52 -> 0 | FE52: =+PMGR!FE52+BP!FE52 -> 0 | FF52: =+PMGR!FF52+BP!FF52 -> 0 | ... FJ52: =+PMGR!FJ52+BP!FJ52 -> 0 | FK52: =+SUM(EY52:FJ52) -> 0
A53: =+AQ53+CG53+DW53 -> 0 | B53: =+AR53+CH53+DX53 -> 0 | C53: =+AS53+CI53+DY53 -> 0 | D53: =+AT53+CJ53+DZ53 -> 0 | E53: =+AU53+CK53+EA53 -> 0 | F53: =+AV53+CL53+EB53 -> 0 | G53: =+AW53+CM53+EC53 -> 0 | H53: =+AX53+CN53+ED53 -> 0 | ... L53: =+BB53+CR53+EH53 -> 0 | M53: =+SUM(A53:L53) -> 0 | N53: Cost of Good sold | O53: =+BE53+CU53+EK53 -> 0 | P53: =+BF53+CV53+EL53 -> 0 | Q53: =+BG53+CW53+EM53 -> 0 | R53: =+BH53+CX53+EN53 -> 0 | S53: =+BI53+CY53+EO53 -> 0 | T53: =+BJ53+CZ53+EP53 -> 0 | U53: =+BK53+DA53+EQ53 -> 0 | V53: =+BL53+DB53+ER53 -> 0 | ... Z53: =+BP53+DF53+EV53 -> 0 | AA53: =+SUM(O53:Z53) -> 0 | AC53: =+BS53+DI53+EY53 -> 0 | AD53: =+BT53+DJ53+EZ53 -> 0 | AE53: =+BU53+DK53+FA53 -> 0 | AF53: =+BV53+DL53+FB53 -> 0 | AG53: =+BW53+DM53+FC53 -> 0 | AH53: =+BX53+DN53+FD53 -> 0 | AI53: =+BY53+DO53+FE53 -> 0 | AJ53: =+BZ53+DP53+FF53 -> 0 | ... AN53: =+CD53+DT53+FJ53 -> 0 | AO53: =+SUM(AC53:AN53) -> 0 | AQ53: =+PMGR!AQ53+BP!AQ53 -> 0 | AR53: =+PMGR!AR53+BP!AR53 -> 0 | AS53: =+PMGR!AS53+BP!AS53 -> 0 | AT53: =+PMGR!AT53+BP!AT53 -> 0 | AU53: =+PMGR!AU53+BP!AU53 -> 0 | AV53: =+PMGR!AV53+BP!AV53 -> 0 | AW53: =+PMGR!AW53+BP!AW53 -> 0 | AX53: =+PMGR!AX53+BP!AX53 -> 0 | ... BB53: =+PMGR!BB53+BP!BB53 -> 0 | BC53: =+SUM(AQ53:BB53) -> 0 | BD53: =N53 -> Cost of Good sold | BE53: =+PMGR!BE53+BP!BE53 -> 0 | BF53: =+PMGR!BF53+BP!BF53 -> 0 | BG53: =+PMGR!BG53+BP!BG53 -> 0 | BH53: =+PMGR!BH53+BP!BH53 -> 0 | BI53: =+PMGR!BI53+BP!BI53 -> 0 | BJ53: =+PMGR!BJ53+BP!BJ53 -> 0 | BK53: =+PMGR!BK53+BP!BK53 -> 0 | BL53: =+PMGR!BL53+BP!BL53 -> 0 | ... BP53: =+PMGR!BP53+BP!BP53 -> 0 | BQ53: =+SUM(BE53:BP53) -> 0 | BS53: =+PMGR!BS53+BP!BS53 -> 0 | BT53: =+PMGR!BT53+BP!BT53 -> 0 | BU53: =+PMGR!BU53+BP!BU53 -> 0 | BV53: =+PMGR!BV53+BP!BV53 -> 0 | BW53: =+PMGR!BW53+BP!BW53 -> 0 | BX53: =+PMGR!BX53+BP!BX53 -> 0 | BY53: =+PMGR!BY53+BP!BY53 -> 0 | BZ53: =+PMGR!BZ53+BP!BZ53 -> 0 | ... CD53: =+PMGR!CD53+BP!CD53 -> 0 | CE53: =+SUM(BS53:CD53) -> 0 | CG53: =+PMGR!CG53+BP!CG53 -> 0 | CH53: =+PMGR!CH53+BP!CH53 -> 0 | CI53: =+PMGR!CI53+BP!CI53 -> 0 | CJ53: =+PMGR!CJ53+BP!CJ53 -> 0 | CK53: =+PMGR!CK53+BP!CK53 -> 0 | CL53: =+PMGR!CL53+BP!CL53 -> 0 | CM53: =+PMGR!CM53+BP!CM53 -> 0 | CN53: =+PMGR!CN53+BP!CN53 -> 0 | ... CR53: =+PMGR!CR53+BP!CR53 -> 0 | CS53: =+SUM(CG53:CR53) -> 0 | CT53: =BD53 -> Cost of Good sold | CU53: =+PMGR!CU53+BP!CU53 -> 0 | CV53: =+PMGR!CV53+BP!CV53 -> 0 | CW53: =+PMGR!CW53+BP!CW53 -> 0 | CX53: =+PMGR!CX53+BP!CX53 -> 0 | CY53: =+PMGR!CY53+BP!CY53 -> 0 | CZ53: =+PMGR!CZ53+BP!CZ53 -> 0 | DA53: =+PMGR!DA53+BP!DA53 -> 0 | DB53: =+PMGR!DB53+BP!DB53 -> 0 | ... DF53: =+PMGR!DF53+BP!DF53 -> 0 | DG53: =+SUM(CU53:DF53) -> 0 | DI53: =+PMGR!DI53+BP!DI53 -> 0 | DJ53: =+PMGR!DJ53+BP!DJ53 -> 0 | DK53: =+PMGR!DK53+BP!DK53 -> 0 | DL53: =+PMGR!DL53+BP!DL53 -> 0 | DM53: =+PMGR!DM53+BP!DM53 -> 0 | DN53: =+PMGR!DN53+BP!DN53 -> 0 | DO53: =+PMGR!DO53+BP!DO53 -> 0 | DP53: =+PMGR!DP53+BP!DP53 -> 0 | ... DT53: =+PMGR!DT53+BP!DT53 -> 0 | DU53: =+SUM(DI53:DT53) -> 0 | DW53: =+PMGR!DW53+BP!DW53 -> 0 | DX53: =+PMGR!DX53+BP!DX53 -> 0 | DY53: =+PMGR!DY53+BP!DY53 -> 0 | DZ53: =+PMGR!DZ53+BP!DZ53 -> 0 | EA53: =+PMGR!EA53+BP!EA53 -> 0 | EB53: =+PMGR!EB53+BP!EB53 -> 0 | EC53: =+PMGR!EC53+BP!EC53 -> 0 | ED53: =+PMGR!ED53+BP!ED53 -> 0 | ... EH53: =+PMGR!EH53+BP!EH53 -> 0 | EI53: =+SUM(DW53:EH53) -> 0 | EJ53: =CT53 -> Cost of Good sold | EK53: =+PMGR!EK53+BP!EK53 -> 0 | EL53: =+PMGR!EL53+BP!EL53 -> 0 | EM53: =+PMGR!EM53+BP!EM53 -> 0 | EN53: =+PMGR!EN53+BP!EN53 -> 0 | EO53: =+PMGR!EO53+BP!EO53 -> 0 | EP53: =+PMGR!EP53+BP!EP53 -> 0 | EQ53: =+PMGR!EQ53+BP!EQ53 -> 0 | ER53: =+PMGR!ER53+BP!ER53 -> 0 | ... EV53: =+PMGR!EV53+BP!EV53 -> 0 | EW53: =+SUM(EK53:EV53) -> 0 | EY53: =+PMGR!EY53+BP!EY53 -> 0 | EZ53: =+PMGR!EZ53+BP!EZ53 -> 0 | FA53: =+PMGR!FA53+BP!FA53 -> 0 | FB53: =+PMGR!FB53+BP!FB53 -> 0 | FC53: =+PMGR!FC53+BP!FC53 -> 0 | FD53: =+PMGR!FD53+BP!FD53 -> 0 | FE53: =+PMGR!FE53+BP!FE53 -> 0 | FF53: =+PMGR!FF53+BP!FF53 -> 0 | ... FJ53: =+PMGR!FJ53+BP!FJ53 -> 0 | FK53: =+SUM(EY53:FJ53) -> 0
A54: =+A51+A52-A53 -> 0 | B54: =+B51+B52-B53 -> 0 | C54: =+C51+C52-C53 -> 0 | D54: =+D51+D52-D53 -> 0 | E54: =+E51+E52-E53 -> 0 | F54: =+F51+F52-F53 -> 0 | G54: =+G51+G52-G53 -> 0 | H54: =+H51+H52-H53 -> 0 | ... M54: =+M51+M52-M53 -> 0 | N54: Gross Profit | O54: =+O51+O52-O53 -> 0 | P54: =+P51+P52-P53 -> 0 | Q54: =+Q51+Q52-Q53 -> 0 | R54: =+R51+R52-R53 -> 0 | S54: =+S51+S52-S53 -> 0 | T54: =+T51+T52-T53 -> 0 | U54: =+U51+U52-U53 -> 0 | V54: =+V51+V52-V53 -> 0 | ... AA54: =+AA51+AA52-AA53 -> 0 | AC54: =+AC51+AC52-AC53 -> 0 | AD54: =+AD51+AD52-AD53 -> 0 | AE54: =+AE51+AE52-AE53 -> 0 | AF54: =+AF51+AF52-AF53 -> 0 | AG54: =+AG51+AG52-AG53 -> 0 | AH54: =+AH51+AH52-AH53 -> 0 | AI54: =+AI51+AI52-AI53 -> 0 | AJ54: =+AJ51+AJ52-AJ53 -> 0 | ... AO54: =+AO51+AO52-AO53 -> 0 | AQ54: =+AQ51+AQ52-AQ53 -> 0 | AR54: =+AR51+AR52-AR53 -> 0 | AS54: =+AS51+AS52-AS53 -> 0 | AT54: =+AT51+AT52-AT53 -> 0 | AU54: =+AU51+AU52-AU53 -> 0 | AV54: =+AV51+AV52-AV53 -> 0 | AW54: =+AW51+AW52-AW53 -> 0 | AX54: =+AX51+AX52-AX53 -> 0 | ... BC54: =+BC51+BC52-BC53 -> 0 | BD54: =N54 -> Gross Profit | BE54: =+BE51+BE52-BE53 -> 0 | BF54: =+BF51+BF52-BF53 -> 0 | BG54: =+BG51+BG52-BG53 -> 0 | BH54: =+BH51+BH52-BH53 -> 0 | BI54: =+BI51+BI52-BI53 -> 0 | BJ54: =+BJ51+BJ52-BJ53 -> 0 | BK54: =+BK51+BK52-BK53 -> 0 | BL54: =+BL51+BL52-BL53 -> 0 | ... BQ54: =+BQ51+BQ52-BQ53 -> 0 | BS54: =+BS51+BS52-BS53 -> 0 | BT54: =+BT51+BT52-BT53 -> 0 | BU54: =+BU51+BU52-BU53 -> 0 | BV54: =+BV51+BV52-BV53 -> 0 | BW54: =+BW51+BW52-BW53 -> 0 | BX54: =+BX51+BX52-BX53 -> 0 | BY54: =+BY51+BY52-BY53 -> 0 | BZ54: =+BZ51+BZ52-BZ53 -> 0 | ... CE54: =+CE51+CE52-CE53 -> 0 | CG54: =+CG51+CG52-CG53 -> 0 | CH54: =+CH51+CH52-CH53 -> 0 | CI54: =+CI51+CI52-CI53 -> 0 | CJ54: =+CJ51+CJ52-CJ53 -> 0 | CK54: =+CK51+CK52-CK53 -> 0 | CL54: =+CL51+CL52-CL53 -> 0 | CM54: =+CM51+CM52-CM53 -> 0 | CN54: =+CN51+CN52-CN53 -> 0 | ... CS54: =+CS51+CS52-CS53 -> 0 | CT54: =BD54 -> Gross Profit | CU54: =+CU51+CU52-CU53 -> 0 | CV54: =+CV51+CV52-CV53 -> 0 | CW54: =+CW51+CW52-CW53 -> 0 | CX54: =+CX51+CX52-CX53 -> 0 | CY54: =+CY51+CY52-CY53 -> 0 | CZ54: =+CZ51+CZ52-CZ53 -> 0 | DA54: =+DA51+DA52-DA53 -> 0 | DB54: =+DB51+DB52-DB53 -> 0 | ... DG54: =+DG51+DG52-DG53 -> 0 | DI54: =+DI51+DI52-DI53 -> 0 | DJ54: =+DJ51+DJ52-DJ53 -> 0 | DK54: =+DK51+DK52-DK53 -> 0 | DL54: =+DL51+DL52-DL53 -> 0 | DM54: =+DM51+DM52-DM53 -> 0 | DN54: =+DN51+DN52-DN53 -> 0 | DO54: =+DO51+DO52-DO53 -> 0 | DP54: =+DP51+DP52-DP53 -> 0 | ... DU54: =+DU51+DU52-DU53 -> 0 | DW54: =+DW51+DW52-DW53 -> 0 | DX54: =+DX51+DX52-DX53 -> 0 | DY54: =+DY51+DY52-DY53 -> 0 | DZ54: =+DZ51+DZ52-DZ53 -> 0 | EA54: =+EA51+EA52-EA53 -> 0 | EB54: =+EB51+EB52-EB53 -> 0 | EC54: =+EC51+EC52-EC53 -> 0 | ED54: =+ED51+ED52-ED53 -> 0 | ... EI54: =+EI51+EI52-EI53 -> 0 | EJ54: =CT54 -> Gross Profit | EK54: =+EK51+EK52-EK53 -> 0 | EL54: =+EL51+EL52-EL53 -> 0 | EM54: =+EM51+EM52-EM53 -> 0 | EN54: =+EN51+EN52-EN53 -> 0 | EO54: =+EO51+EO52-EO53 -> 0 | EP54: =+EP51+EP52-EP53 -> 0 | EQ54: =+EQ51+EQ52-EQ53 -> 0 | ER54: =+ER51+ER52-ER53 -> 0 | ... EW54: =+EW51+EW52-EW53 -> 0 | EY54: =+EY51+EY52-EY53 -> 0 | EZ54: =+EZ51+EZ52-EZ53 -> 0 | FA54: =+FA51+FA52-FA53 -> 0 | FB54: =+FB51+FB52-FB53 -> 0 | FC54: =+FC51+FC52-FC53 -> 0 | FD54: =+FD51+FD52-FD53 -> 0 | FE54: =+FE51+FE52-FE53 -> 0 | FF54: =+FF51+FF52-FF53 -> 0 | ... FK54: =+FK51+FK52-FK53 -> 0
A55: =+AQ55+CG55+DW55 -> 415400 | B55: =+AR55+CH55+DX55 -> 518260 | C55: =+AS55+CI55+DY55 -> 372239 | D55: =+AT55+CJ55+DZ55 -> 363995 | E55: =+AU55+CK55+EA55 -> 483090 | F55: =+AV55+CL55+EB55 -> 667887.5 | G55: =+AW55+CM55+EC55 -> 760903.2 | H55: =+AX55+CN55+ED55 -> 584876 | ... L55: =+BB55+CR55+EH55 -> 630990 | M55: =+SUM(A55:L55) -> 6830133.5 | N55: VAS | O55: =+BE55+CU55+EK55 -> 593580 | P55: =+BF55+CV55+EL55 -> 477880 | Q55: =+BG55+CW55+EM55 -> 633980 | R55: =+BH55+CX55+EN55 -> 475640 | S55: =+BI55+CY55+EO55 -> 767018 | T55: =+BJ55+CZ55+EP55 -> 625958 | U55: =+BK55+DA55+EQ55 -> 610955 | V55: =+BL55+DB55+ER55 -> 523992 | ... Z55: =+BP55+DF55+EV55 -> 0 | AA55: =+SUM(O55:Z55) -> 6086218 | AC55: =+BS55+DI55+EY55 -> 550000 | AD55: =+BT55+DJ55+EZ55 -> 489000 | AE55: =+BU55+DK55+FA55 -> 568000 | AF55: =+BV55+DL55+FB55 -> 546000 | AG55: =+BW55+DM55+FC55 -> 462400 | AH55: =+BX55+DN55+FD55 -> 529600 | AI55: =+BY55+DO55+FE55 -> 537800 | AJ55: =+BZ55+DP55+FF55 -> 478800 | ... AN55: =+CD55+DT55+FJ55 -> 503400 | AO55: =+SUM(AC55:AN55) -> 6119400 | AQ55: =+PMGR!AQ55+BP!AQ55 -> 259740 | AR55: =+PMGR!AR55+BP!AR55 -> 424940 | AS55: =+PMGR!AS55+BP!AS55 -> 274690 | AT55: =+PMGR!AT55+BP!AT55 -> 292625 | AU55: =+PMGR!AU55+BP!AU55 -> 253560 | AV55: =+PMGR!AV55+BP!AV55 -> 315660 | AW55: =+PMGR!AW55+BP!AW55 -> 516995.2 | AX55: =+PMGR!AX55+BP!AX55 -> 440732 | ... BB55: =+PMGR!BB55+BP!BB55 -> 494406 | BC55: =+SUM(AQ55:BB55) -> 4754389 | BD55: =N55 -> VAS | BE55: =+PMGR!BE55+BP!BE55 -> 222270 | BF55: =+PMGR!BF55+BP!BF55 -> 207732 | BG55: =+PMGR!BG55+BP!BG55 -> 386242 | BH55: =+PMGR!BH55+BP!BH55 -> 235000 | BI55: =+PMGR!BI55+BP!BI55 -> 489578 | BJ55: =+PMGR!BJ55+BP!BJ55 -> 389813 | BK55: =+PMGR!BK55+BP!BK55 -> 403785 | BL55: =+PMGR!BL55+BP!BL55 -> 330638 | ... BP55: =+PMGR!BP55+BP!BP55 -> 0 | BQ55: =+SUM(BE55:BP55) -> 3446663 | BS55: =+PMGR!BS55+BP!BS55 -> 275000 | BT55: =+PMGR!BT55+BP!BT55 -> 244500 | BU55: =+PMGR!BU55+BP!BU55 -> 284000 | BV55: =+PMGR!BV55+BP!BV55 -> 273000 | BW55: =+PMGR!BW55+BP!BW55 -> 231200 | BX55: =+PMGR!BX55+BP!BX55 -> 264800 | BY55: =+PMGR!BY55+BP!BY55 -> 268900 | BZ55: =+PMGR!BZ55+BP!BZ55 -> 239400 | ... CD55: =+PMGR!CD55+BP!CD55 -> 251700 | CE55: =+SUM(BS55:CD55) -> 3059700 | CG55: =+PMGR!CG55+BP!CG55 -> 155660 | CH55: =+PMGR!CH55+BP!CH55 -> 93320 | CI55: =+PMGR!CI55+BP!CI55 -> 97549 | CJ55: =+PMGR!CJ55+BP!CJ55 -> 71370 | CK55: =+PMGR!CK55+BP!CK55 -> 229530 | CL55: =+PMGR!CL55+BP!CL55 -> 352227.5 | CM55: =+PMGR!CM55+BP!CM55 -> 243908 | CN55: =+PMGR!CN55+BP!CN55 -> 144144 | ... CR55: =+PMGR!CR55+BP!CR55 -> 136584 | CS55: =+SUM(CG55:CR55) -> 2075744.5 | CT55: =BD55 -> VAS | CU55: =+PMGR!CU55+BP!CU55 -> 310540 | CV55: =+PMGR!CV55+BP!CV55 -> 212238 | CW55: =+PMGR!CW55+BP!CW55 -> 211458 | CX55: =+PMGR!CX55+BP!CX55 -> 219060 | CY55: =+PMGR!CY55+BP!CY55 -> 250680 | CZ55: =+PMGR!CZ55+BP!CZ55 -> 180010 | DA55: =+PMGR!DA55+BP!DA55 -> 200000 | DB55: =+PMGR!DB55+BP!DB55 -> 152164 | ... DF55: =+PMGR!DF55+BP!DF55 -> 0 | DG55: =+SUM(CU55:DF55) -> 2273800 | DI55: =+PMGR!DI55+BP!DI55 -> 165000 | DJ55: =+PMGR!DJ55+BP!DJ55 -> 146700 | DK55: =+PMGR!DK55+BP!DK55 -> 170400 | DL55: =+PMGR!DL55+BP!DL55 -> 163800 | DM55: =+PMGR!DM55+BP!DM55 -> 138720 | DN55: =+PMGR!DN55+BP!DN55 -> 158880 | DO55: =+PMGR!DO55+BP!DO55 -> 161340 | DP55: =+PMGR!DP55+BP!DP55 -> 143640 | ... DT55: =+PMGR!DT55+BP!DT55 -> 151020 | DU55: =+SUM(DI55:DT55) -> 1835820 | DW55: =+PMGR!DW55+BP!DW55 -> 0 | DX55: =+PMGR!DX55+BP!DX55 -> 0 | DY55: =+PMGR!DY55+BP!DY55 -> 0 | DZ55: =+PMGR!DZ55+BP!DZ55 -> 0 | EA55: =+PMGR!EA55+BP!EA55 -> 0 | EB55: =+PMGR!EB55+BP!EB55 -> 0 | EC55: =+PMGR!EC55+BP!EC55 -> 0 | ED55: =+PMGR!ED55+BP!ED55 -> 0 | ... EH55: =+PMGR!EH55+BP!EH55 -> 0 | EI55: =+SUM(DW55:EH55) -> 0 | EJ55: =CT55 -> VAS | EK55: =+PMGR!EK55+BP!EK55 -> 60770 | EL55: =+PMGR!EL55+BP!EL55 -> 57910 | EM55: =+PMGR!EM55+BP!EM55 -> 36280 | EN55: =+PMGR!EN55+BP!EN55 -> 21580 | EO55: =+PMGR!EO55+BP!EO55 -> 26760 | EP55: =+PMGR!EP55+BP!EP55 -> 56135 | EQ55: =+PMGR!EQ55+BP!EQ55 -> 7170 | ER55: =+PMGR!ER55+BP!ER55 -> 41190 | ... EV55: =+PMGR!EV55+BP!EV55 -> 0 | EW55: =+SUM(EK55:EV55) -> 365755 | EY55: =+PMGR!EY55+BP!EY55 -> 110000 | EZ55: =+PMGR!EZ55+BP!EZ55 -> 97800 | FA55: =+PMGR!FA55+BP!FA55 -> 113600 | FB55: =+PMGR!FB55+BP!FB55 -> 109200 | FC55: =+PMGR!FC55+BP!FC55 -> 92480 | FD55: =+PMGR!FD55+BP!FD55 -> 105920 | FE55: =+PMGR!FE55+BP!FE55 -> 107560 | FF55: =+PMGR!FF55+BP!FF55 -> 95760 | ... FJ55: =+PMGR!FJ55+BP!FJ55 -> 100680 | FK55: =+SUM(EY55:FJ55) -> 1223880
